Workbook
Name IQ_CH: 110000
Name IQ_CQ: 5000
Name IQ_CY: 10000
Name IQ_DAILY: 500000
Name IQ_FH: 100000
Name IQ_FQ: 500
Name IQ_FY: 1000
Name IQ_LTM: 2000
Name IQ_MONTH: 15000
Name IQ_NTM: 6000
Name IQ_WEEK: 50000
Name IQ_YTD: 3000

Sheet Valuation Summary
C2: Tullow Oil Valuation Summary
C4: Valuation Summary
C5: Intrinsic Valuation | K5: Low | L5: Med | M5: High
C6: Liquidation Valuation | K6: ='Liquidation Value'!L47 -> 633.48 | L6: ='Liquidation Value'!M47 -> 1305.01 | M6: ='Liquidation Value'!N47 -> 1431.9555
C7: Discounted Cash Flow Valuation | K7: =DCF!T25 -> 2288.2377 | L7: =DCF!U25 -> 2535.6915 | M7: =DCF!V25 -> 2809.9751
C9: Relative Valuation | K9: Low (25th) | L9: Med (Median) | M9: High (75th)
C10: Trading Comps Valuation (EV/EBITDA) | K10: ='Trading Comps'!E18*'Trading Comps'!R6 -> 2433.4561 | L10: ='Trading Comps'!E19*'Trading Comps'!R6 -> 3910.4795 | M10: ='Trading Comps'!E21*'Trading Comps'!R6 -> 5051.0746
C11: Precedent Transactions (EV/EBITDA) | K11: ='Precedent Transactions '!G20*'Precedent Transactions '!$N$8 -> 1232.8133 | L11: ='Precedent Transactions '!G21*'Precedent Transactions '!N8 -> 1510.1717 | M11: ='Precedent Transactions '!G23*'Precedent Transactions '!N8 -> 2592.4637
C13: Indicated Enterprise Value Range | K13: =MIN(MIN(K6:M7),MIN(K10:M11)) -> 633.48 | L13: to | M13: =MAX(MAX(K6:M7),MAX(K10:M11)) -> 5051.0746
C15: Trading Comps Valuation
C17: Relevant Financial Measures | G17: Selected Multiples | K17: Indicated Enterprise Value
C19: EBITDA (2024E): | G19: Low | H19: Med | I19: High | K19: Low | L19: Med | M19: High
C20: Adjusted EBITDA | E20: ='Trading Comps'!$R$6 -> 666.9 | G20: ='Trading Comps'!E18 -> 3.648907 | H20: ='Trading Comps'!E19 -> 5.863667 | I20: ='Trading Comps'!E21 -> 7.573961 | K20: =$E20*G20 -> 2433.4561 | L20: =$E20*H20 -> 3910.4795 | M20: =$E20*I20 -> 5051.0746
C22: Precedent Transaction Valuation
C24: Relevant Financial Measures | G24: Selected Multiples | K24: Indicated Enterprise Value
C26: EBITDA (2024E): | G26: Low | H26: Med | I26: High | K26: Low | L26: Med | M26: High
C27: Adjusted EBITDA | E27: ='Trading Comps'!$R$6 -> 666.9 | G27: ='Precedent Transactions '!G20 -> 1.848573 | H27: ='Precedent Transactions '!G21 -> 2.2644651 | I27: ='Precedent Transactions '!G23 -> 3.8873349 | K27: =$E27*G27 -> 1232.8133 | L27: =$E27*H27 -> 1510.1717 | M27: =$E27*I27 -> 2592.4637
C29: Discounted Cash Flow Valuation
C31: Relevant Financial Measures | G31: Selected WACC | K31: Indicated Enterprise Value
C33: EBITDA (2024E): | G33: Low | H33: Med | I33: High | K33: Low | L33: Med | M33: High
C34: Adjusted EBITDA | E34: ='Trading Comps'!$R$6 -> 666.9 | G34: =DCF!J37 -> 0.24412793 | H34: =DCF!K37 -> 0.20779362 | I34: =DCF!L37 -> 0.1714593 | K34: =DCF!T25 -> 2288.2377 | L34: =DCF!U25 -> 2535.6915 | M34: =DCF!V25 -> 2809.9751
C36: Liquidation Valuation
C38: Relevant Financial Measures | G38: Avg. Asset Recovery Values | K38: Indicated Enterprise Value
C40: Pre-Restructuring Balance Sheet | G40: Low | H40: Med | I40: High | K40: Low | L40: Med | M40: High
C41: Total Assets | E41: =+'Liquidation Value'!F19 -> 3872.1 | G41: =AVERAGE('Liquidation Value'!H9:H18) -> 0.395 | H41: =AVERAGE('Liquidation Value'!I9:I18) -> 0.585 | I41: =AVERAGE('Liquidation Value'!J9:J18) -> 0.775 | K41: ='Liquidation Value'!L47 -> 633.48 | L41: ='Liquidation Value'!M47 -> 1305.01 | M41: ='Liquidation Value'!N47 -> 1431.9555
C43: Football Field Valuation Range
C44: Valuation | D44: Low (bar) | E44: Lo (Label) | F44: High (Bar) | G44: High (Label)
C45: Liquidation Valuation | D45: =MIN($K$41:$M$41) -> 633.48 | E45: =D45 -> 633.48 | F45: =MAX($K$41:$M$41) -> 1431.9555 | G45: =F45 -> 1431.9555
C46: Discounted Cash Flow | D46: =MIN($K$34:$M$34) -> 2288.2377 | E46: =D46 -> 2288.2377 | F46: =MAX($K$34:$M$34) -> 2809.9751 | G46: =F46 -> 2809.9751
C47: Precedent Transactions | D47: =MIN($K$27:$M$27) -> 1232.8133 | E47: =D47 -> 1232.8133 | F47: =MAX($K$27:$M$27) -> 2592.4637 | G47: =F47 -> 2592.4637
C48: Trading Comps | D48: =MIN($K$20:$M$20) -> 2433.4561 | E48: =D48 -> 2433.4561 | F48: =MAX($K$20:$M$20) -> 5051.0746 | G48: =F48 -> 5051.0746

Sheet IS
D1: 2019 | E1: =D1+1 -> 2020 | F1: =E1+1 -> 2021 | G1: =F1+1 -> 2022 | H1: =G1+1 -> 2023 | I1: =H1+1 -> 2024 | J1: =I1+1 -> 2025 | K1: =J1+1 -> 2026 | L1: =K1+1 -> 2027 | ... Q1: =P1+1 -> 2032
C2: Tullow Oil Income Statement
C4: Income Statement
C5: Revenue | D5: 1682.6 | E5: 1396.1 | F5: 1285.4 | G5: 1783.1 | H5: 1634.1 | I5: 1534.9 | J5: ='Revenue Build'!J5 -> 1145.735 | K5: ='Revenue Build'!K5 -> 996.45 | L5: ='Revenue Build'!L5 -> 1003.6441 | M5: ='Revenue Build'!M5 -> 986.084 | N5: ='Revenue Build'!N5 -> 967.85955 | O5: ='Revenue Build'!O5 -> 948.9708 | P5: ='Revenue Build'!P5 -> 917.829 | Q5: ='Revenue Build'!Q5 -> 885.7674
C6: YOY Growth | D6: 0 | E6: =(E5-D5)/D5 -> -0.1702722 | F6: =(F5-E5)/E5 -> -0.079292314 | G6: =(G5-F5)/F5 -> 0.38719465 | H6: =(H5-G5)/G5 -> -0.083562335 | I6: =(I5-H5)/H5 -> -0.060706199 | J6: =(J5-I5)/I5 -> -0.2535442 | K6: =(K5-J5)/J5 -> -0.13029627 | L6: =(L5-K5)/K5 -> 0.0072197802 | ... Q6: =(Q5-P5)/P5 -> -0.034931997
C8: Cost Of Goods Sold | D8: -970.9 | E8: -993.6 | F8: -631 | G8: -682.8 | H8: -843.3 | I8: -772.6 | J8: =-J$5*J63 -> -607.61498 | K8: =-K$5*K63 -> -528.44501 | L8: =-L$5*L63 -> -532.26027 | M8: =-M$5*M63 -> -522.94764 | N8: =-N$5*N63 -> -513.28271 | O8: =-O$5*O63 -> -503.26548 | P8: =-P$5*P63 -> -486.75012 | Q8: =-Q$5*Q63 -> -469.74697
C9: Gross Profit | D9: =D5+D8 -> 711.7 | E9: =E5+E8 -> 402.5 | F9: =F5+F8 -> 654.4 | G9: =G5+G8 -> 1100.3 | H9: =H5+H8 -> 790.8 | I9: =I5+I8 -> 762.3 | J9: =J5+J8 -> 538.12002 | K9: =K5+K8 -> 468.00499 | ... Q9: =Q5+Q8 -> 416.02043
C10: Gross Margin | D10: =D9/D$5 -> 0.42297635 | E10: =E9/E$5 -> 0.28830313 | F10: =F9/F$5 -> 0.50910222 | G10: =G9/G$5 -> 0.61707139 | H10: =H9/H$5 -> 0.48393611 | I10: =I9/I$5 -> 0.49664473 | J10: =J9/J$5 -> 0.46967232 | K10: =K9/K$5 -> 0.46967232 | ... Q10: =Q9/Q$5 -> 0.46967232
C12: Selling General & Admin Exp. | D12: -111.5 | E12: -86.7 | F12: -64.1 | G12: -51 | H12: -56.1 | I12: -53.2 | J12: =-J$5*J66 -> -52.671107 | K12: =-K$5*K66 -> -45.808258 | L12: =-L$5*L66 -> -46.138984 | M12: =-M$5*M66 -> -45.331718 | N12: =-N$5*N66 -> -44.493914 | O12: =-O$5*O66 -> -43.62557 | P12: =-P$5*P66 -> -42.193936 | Q12: =-Q$5*Q66 -> -40.720018
C13: Provision for Bad Debts | D13: 0 | E13: 0 | F13: 0 | G13: 0 | H13: 0 | I13: -6.6 | J13: 0 | K13: =J13 -> 0 | L13: =K13 -> 0 | M13: =L13 -> 0 | N13: =M13 -> 0 | O13: =N13 -> 0 | P13: =O13 -> 0 | Q13: =P13 -> 0
C14: Impair. of Oil, Gas & Mineral Prop. | D14: 0 | E14: 0 | F14: -114.2 | G14: -496.4 | H14: -27 | I14: -212.6 | J14: =-J71 -> -155.32415 | K14: =J14 -> -155.32415 | L14: =K14 -> -155.32415 | M14: =L14 -> -155.32415 | N14: =M14 -> -155.32415 | O14: =N14 -> -155.32415 | P14: =O14 -> -155.32415 | Q14: =P14 -> -155.32415
C15: Other Operating Expense/(Income) | D15: -17.8 | E15: -38.9 | F15: -7.6 | G15: -7 | H15: 12.1 | I15: 59 | J15: =J74 -> -44.040892 | K15: =J15 -> -44.040892 | L15: =K15 -> -44.040892 | M15: =L15 -> -44.040892 | N15: =M15 -> -44.040892 | O15: =N15 -> -44.040892 | P15: =O15 -> -44.040892 | Q15: =P15 -> -44.040892
C17: Other Operating Expenses | D17: =SUM(D12:D15) -> -129.3 | E17: =SUM(E12:E15) -> -125.6 | F17: =SUM(F12:F15) -> -185.9 | G17: =SUM(G12:G15) -> -554.4 | H17: =SUM(H12:H15) -> -71 | I17: =SUM(I12:I15) -> -213.4 | J17: =SUM(J12:J15) -> -252.03615 | K17: =SUM(K12:K15) -> -245.1733 | ... Q17: =SUM(Q12:Q15) -> -240.08506
C18: Operating Income | D18: =D9+D17 -> 582.4 | E18: =E9+E17 -> 276.9 | F18: =F9+F17 -> 468.5 | G18: =G9+G17 -> 545.9 | H18: =H9+H17 -> 719.8 | I18: =I9+I17 -> 548.9 | J18: =J9+J17 -> 286.08387 | K18: =K9+K17 -> 222.83169 | ... Q18: =Q9+Q17 -> 175.93538
C19: Operating Margin | D19: =D18/D$5 -> 0.34613099 | E19: =E18/E$5 -> 0.19833823 | F19: =F18/F$5 -> 0.36447798 | G19: =G18/G$5 -> 0.30615221 | H19: =H18/H$5 -> 0.44048712 | I19: =I18/I$5 -> 0.35761287 | J19: =J18/J$5 -> 0.24969463 | K19: =K18/K$5 -> 0.22362556 | ... Q19: =Q18/Q$5 -> 0.1986248
C21: Interest Expense | D21: -305.3 | E21: -300.4 | F21: -329.4 | G21: -329.2 | H21: -317.6 | I21: -331.2 | J21: =-'Debt Schedule'!J54 -> -204.87245 | K21: =-'Debt Schedule'!K54 -> -129.59312 | L21: =-'Debt Schedule'!L54 -> -95.73 | M21: =-'Debt Schedule'!M54 -> -82.966 | N21: =-'Debt Schedule'!N54 -> -70.202 | O21: =-'Debt Schedule'!O54 -> -57.438 | P21: =-'Debt Schedule'!P54 -> -44.674 | Q21: =-'Debt Schedule'!Q54 -> -19.146
C22: Interest and Invest. Income | D22: 50 | E22: 40.6 | F22: 38.8 | G22: 29.6 | H22: 30.1 | I22: 48.1 | J22: =I22 -> 48.1 | K22: =J22 -> 48.1 | L22: =K22 -> 48.1 | M22: =L22 -> 48.1 | N22: =M22 -> 48.1 | O22: =N22 -> 48.1 | P22: =O22 -> 48.1 | Q22: =P22 -> 48.1
C23: Net Interest Exp. | D23: =SUM(D21:D22) -> -255.3 | E23: =SUM(E21:E22) -> -259.8 | F23: =SUM(F21:F22) -> -290.6 | G23: =SUM(G21:G22) -> -299.6 | H23: =SUM(H21:H22) -> -287.5 | I23: =SUM(I21:I22) -> -283.1 | J23: =SUM(J21:J22) -> -156.77245 | K23: =SUM(K21:K22) -> -81.493124 | ... Q23: =SUM(Q21:Q22) -> 28.954
C25: Other Non-Operating Inc. (Exp.) | D25: 4.8 | E25: 18 | F25: -13.6 | G25: 13.8 | H25: 11.6 | I25: 20.4 | J25: 0 | K25: 0 | L25: 0 | M25: 0 | N25: 0 | O25: 0 | P25: 0 | Q25: 0
C26: EBT Incl. Unusual Items | D26: =D18+D23+D25 -> 331.9 | E26: =E18+E23+E25 -> 35.1 | F26: =F18+F23+F25 -> 164.3 | G26: =G18+G23+G25 -> 260.1 | H26: =H18+H23+H25 -> 443.9 | I26: =I18+I23+I25 -> 286.2 | J26: =J18+J23+J25 -> 129.31143 | K26: =K18+K23+K25 -> 141.33857 | ... Q26: =Q18+Q23+Q25 -> 204.88938
C28: Restructuring Charges | D28: -4.2 | E28: -67.8 | F28: -3.1 | G28: -0.1 | H28: 0 | I28: -7.1 | J28: =I28 -> -7.1 | K28: =J28 -> -7.1 | L28: =K28 -> -7.1 | M28: =L28 -> -7.1 | N28: =M28 -> -7.1 | O28: =N28 -> -7.1 | P28: =O28 -> -7.1 | Q28: =P28 -> -7.1
C29: Impairment of Goodwill | D29: 0 | E29: 0 | F29: 0 | G29: 0 | H29: 0 | I29: 0 | J29: =I29 -> 0 | K29: =J29 -> 0 | L29: =K29 -> 0 | M29: =L29 -> 0 | N29: =M29 -> 0 | O29: =N29 -> 0 | P29: =O29 -> 0 | Q29: =P29 -> 0
C30: Gain (Loss) On Sale Of Assets | D30: 6.6 | E30: -3.4 | F30: 120.3 | G30: 0 | H30: 0 | I30: 0 | J30: =+'Forecast Assumptions'!D89 -> 142.43333 | K30: =+'Forecast Assumptions'!E89 -> 3.6333333 | L30: =+'Forecast Assumptions'!F89 -> 0 | M30: =+'Forecast Assumptions'!G89 -> 0.72666667 | N30: =+'Forecast Assumptions'!H89 -> 0.72666667 | O30: =+'Forecast Assumptions'!I89 -> 0.72666667 | P30: =+'Forecast Assumptions'!J89 -> 0.72666667 | Q30: =+'Forecast Assumptions'!K89 -> 0.72666667
C31: Asset Write-down | D31: -2034.6 | E31: -1237.3 | F31: 0 | G31: 0 | H31: -408.1 | I31: 50.7 | J31: 0 | K31: =J31 -> 0 | L31: =K31 -> 0 | M31: =L31 -> 0 | N31: =M31 -> 0 | O31: =N31 -> 0 | P31: =O31 -> 0 | Q31: =P31 -> 0
C32: Insurance Settlements | D32: 46.9 | E32: 0 | F32: 0 | G32: 0 | H32: 0 | I32: 0 | J32: =I32 -> 0 | K32: =J32 -> 0 | L32: =K32 -> 0 | M32: =L32 -> 0 | N32: =M32 -> 0 | O32: =N32 -> 0 | P32: =O32 -> 0 | Q32: =P32 -> 0
C33: Other Unusual Items | D33: 0 | E33: 0 | F33: -66.6 | G33: 182.1 | H33: 60.1 | I33: -8.3 | J33: -65.4 | K33: 0 | L33: =K33 -> 0 | M33: =L33 -> 0 | N33: =M33 -> 0 | O33: =N33 -> 0 | P33: =O33 -> 0 | Q33: =P33 -> 0
C34: EBT Excl. Unusual Items | D34: =SUM(D26:D33) -> -1653.4 | E34: =SUM(E26:E33) -> -1273.4 | F34: =SUM(F26:F33) -> 214.9 | G34: =SUM(G26:G33) -> 442.1 | H34: =SUM(H26:H33) -> 95.9 | I34: =SUM(I26:I33) -> 321.5 | J34: =SUM(J28:J33)+J26 -> 199.24476 | K34: =SUM(K28:K33)+K26 -> 137.8719 | L34: =SUM(L28:L33)+L26 -> 171.14986 | M34: =SUM(M28:M33)+M26 -> 177.20027 | N34: =SUM(N28:N33)+N26 -> 182.24256 | O34: =SUM(O28:O33)+O26 -> 187.00338 | P34: =SUM(P28:P33)+P26 -> 186.57257 | Q34: =SUM(Q28:Q33)+Q26 -> 198.51604
C36: Income Tax Expense | D36: -40.7 | E36: 51.9 | F36: -295.6 | G36: -393 | H36: -205.5 | I36: -266.9 | J36: =-J34*J37 -> -119.7461 | K36: =-K34*K37 -> -82.861011 | L36: =-L34*L37 -> -102.86106 | M36: =-M34*M37 -> -106.49736 | N36: =-N34*N37 -> -109.52778 | O36: =-O34*O37 -> -112.38903 | P36: =-P34*P37 -> -112.13011 | Q36: =-Q34*Q37 -> -119.30814
C37: Adj. Effective Tax Rate | D37: 0.716 | E37: 0.356 | F37: 1.17 | G37: 0.703 | H37: 0.702 | I37: 0.601 | J37: =I37 -> 0.601 | K37: =J37 -> 0.601 | L37: =K37 -> 0.601 | M37: =L37 -> 0.601 | N37: =M37 -> 0.601 | O37: =N37 -> 0.601 | P37: =O37 -> 0.601 | Q37: =P37 -> 0.601
C38: Earnings from Cont. Ops. | D38: =D34+D36 -> -1694.1 | E38: =E34+E36 -> -1221.5 | F38: =F34+F36 -> -80.7 | G38: =G34+G36 -> 49.1 | H38: =H34+H36 -> -109.6 | I38: =I34+I36 -> 54.6 | J38: =J34+J36 -> 79.498659 | K38: =K34+K36 -> 55.010888 | ... Q38: =Q34+Q36 -> 79.207901
C39: Earnings of Discontinued Ops. | D39: 0 | E39: 0 | F39: 0 | G39: 0 | H39: 0 | I39: 0 | J39: 0 | K39: =J39 -> 0 | L39: =K39 -> 0 | M39: =L39 -> 0 | N39: =M39 -> 0 | O39: =N39 -> 0 | P39: =O39 -> 0 | Q39: =P39 -> 0
C40: Net Income | D40: =D38 -> -1694.1 | E40: =E38 -> -1221.5 | F40: =F38 -> -80.7 | G40: =G38 -> 49.1 | H40: =H38 -> -109.6 | I40: =I38 -> 54.6 | J40: =J38 -> 79.498659 | K40: =K38 -> 55.010888 | ... Q40: =Q38 -> 79.207901
C41: Net Income Margin | D41: =D40/D$5 -> -1.0068347 | E41: =E40/E$5 -> -0.87493733 | F41: =F40/F$5 -> -0.062782013 | G41: =G40/G$5 -> 0.027536313 | H41: =H40/H$5 -> -0.067070559 | I41: =I40/I$5 -> 0.03557235 | J41: =J40/J$5 -> 0.069386602 | K41: =K40/K$5 -> 0.055206872 | ... Q41: =Q40/Q$5 -> 0.089422913
C43: Cap IQ Net Income | D43: -1694.1 | E43: -1221.5 | F43: -80.7 | G43: 49.1 | H43: -109.6 | I43: 54.6
C44: Net Income | D44: =D40 -> -1694.1 | E44: =E40 -> -1221.5 | F44: =F40 -> -80.7 | G44: =G40 -> 49.1 | H44: =H40 -> -109.6 | I44: =I40 -> 54.6
C45: Check | D45: =D43-D44 -> 0 | E45: =E43-E44 -> 0 | F45: =F43-F44 -> -1.563194e-13 | G45: =G43-G44 -> 0 | H45: =H43-H44 -> 0 | I45: =I43-I44 -> -7.8159701e-14
C46: EBIT | D46: =D18 -> 582.4 | E46: =E18 -> 276.9 | F46: =F18 -> 468.5 | G46: =G18 -> 545.9 | H46: =H18 -> 719.8 | I46: =I18 -> 548.9 | J46: =J18 -> 286.08387 | K46: =K18 -> 222.83169 | ... Q46: =Q18 -> 175.93538
C47: EBIT Margin | D47: =D46/D$5 -> 0.34613099 | E47: =E46/E$5 -> 0.19833823 | F47: =F46/F$5 -> 0.36447798 | G47: =G46/G$5 -> 0.30615221 | H47: =H46/H$5 -> 0.44048712 | I47: =I46/I$5 -> 0.35761287 | J47: =J46/J$5 -> 0.24969463 | K47: =K46/K$5 -> 0.22362556 | ... Q47: =Q46/Q$5 -> 0.1986248
C49: Depreciation & Amort. | D49: 724.6 | E49: 467.1 | F49: 378.9 | G49: 425.8 | H49: 436.6 | I49: 444.2 | J49: =J78 -> 354.29339 | K49: =K78 -> 308.13028 | L49: =L78 -> 310.35492 | M49: =M78 -> 304.92483 | N49: =N78 -> 299.28932 | O49: =O78 -> 293.44838 | P49: =P78 -> 283.81847 | Q49: =Q78 -> 273.90412
C50: Amortization of Intangibles | D50: 16.3 | E50: 13.1 | F50: 7.6 | G50: 6 | H50: 10.1 | I50: 11.4 | J50: =J80 -> 11.765894 | K50: =K80 -> 9.1354775 | L50: =L80 -> 7.8027433 | M50: =M80 -> 10.870798 | N50: =N80 -> 10.706372 | O50: =O80 -> 10.151356 | P50: =P80 -> 7.4221957 | Q50: =Q80 -> 6.3696527
C51: Depreciation Adjustment | D51: -85.9 | E51: -72.4 | F51: -60.6 | G51: -60.9 | H51: -81.4 | I51: -91.4 | J51: =J82 -> -82.327026 | K51: =K82 -> -67.814923 | L51: =L82 -> -61.734135 | M51: =M82 -> -85.899473 | N51: =N82 -> -82.539922 | O51: =O82 -> -77.707691 | P51: =P82 -> -56.301906 | Q51: =Q82 -> -49.001179
C52: Impairment of Oil, Gas & Mineral Properties | D52: 0 | E52: 250 | F52: 54.3 | G52: 496.4 | H52: 426.1 | I52: 200.8 | J52: =J84 -> 249.9456 | K52: =K84 -> 241.95129 | L52: =L84 -> 221.53132 | M52: =M84 -> 345.9708 | N52: =N84 -> 294.08417 | O52: =O84 -> 255.5645 | P52: =P84 -> 197.58081 | Q52: =Q84 -> 175.80625
C53: Exploration Costs Write-Off | D53: 0 | E53: 0 | F53: 59.9 | G53: 0 | H53: 0 | I53: 0 | J53: 0
C54: Depreciation & Amort. | D54: =SUM(D49:D53) -> 655 | E54: =SUM(E49:E53) -> 657.8 | F54: =SUM(F49:F53) -> 440.1 | G54: =SUM(G49:G53) -> 867.3 | H54: =SUM(H49:H53) -> 791.4 | I54: =SUM(I49:I53) -> 565 | J54: =SUM(J49:J53) -> 533.67787 | K54: =SUM(K49:K53) -> 491.40212 | ... Q54: =SUM(Q49:Q53) -> 407.07884
C55: EBITDA | D55: =D46+D54 -> 1237.4 | E55: =E46+E54 -> 934.7 | F55: =F46+F54 -> 908.6 | G55: =G46+G54 -> 1413.2 | H55: =H46+H54 -> 1511.2 | I55: =I46+I54 -> 1113.9 | J55: =J46+J54 -> 819.76174 | K55: =K46+K54 -> 714.23381 | ... Q55: =Q46+Q54 -> 583.01422
D56: =D55/D5 -> 0.73540949 | E56: =E55/E5 -> 0.66950791 | F56: =F55/F5 -> 0.70686168 | G56: =G55/G5 -> 0.7925523 | H56: =H55/H5 -> 0.9247904 | I56: =I55/I5 -> 0.72571503
C57: Cap IQ Net Income | D57: 1237.4 | E57: 934.7 | F57: 908.6 | G57: 1413.2 | H57: 1511.2 | I57: 1113.9
C58: EBITDA | D58: =D55 -> 1237.4 | E58: =E55 -> 934.7 | F58: =F55 -> 908.6 | G58: =G55 -> 1413.2 | H58: =H55 -> 1511.2 | I58: =I55 -> 1113.9
C59: Check | D59: =D57-D58 -> 0 | E59: =E57-E58 -> 0 | F59: =F57-F58 -> 0 | G59: =G57-G58 -> 0 | H59: =H57-H58 -> 0 | I59: =I57-I58 -> 0
C61: Account | D61: 2019 | E61: =D61+1 -> 2020 | F61: =E61+1 -> 2021 | G61: =F61+1 -> 2022 | H61: =G61+1 -> 2023 | I61: =H61+1 -> 2024 | J61: =I61+1 -> 2025 | K61: =J61+1 -> 2026 | L61: =K61+1 -> 2027 | ... Q61: =P61+1 -> 2032 | S61: Step:
C62: COGS | D62: =-D8 -> 970.9 | E62: =-E8 -> 993.6 | F62: =-F8 -> 631 | G62: =-G8 -> 682.8 | H62: =-H8 -> 843.3 | I62: =-I8 -> 772.6 | J62: =-J8 -> 607.61498 | K62: =-K8 -> 528.44501 | ... Q62: =-Q8 -> 469.74697
C63: (% of Revenue) | D63: =+D62/D$5 -> 0.57702365 | E63: =+E62/E5 -> 0.71169687 | F63: =+F62/F5 -> 0.49089778 | G63: =+G62/G5 -> 0.38292861 | H63: =+H62/H5 -> 0.51606389 | I63: =+I62/I5 -> 0.50335527 | J63: =AVERAGE(D63:I63) -> 0.53032768 | K63: =J63 -> 0.53032768 | L63: =K63 -> 0.53032768 | M63: =L63 -> 0.53032768 | N63: =M63 -> 0.53032768 | O63: =N63 -> 0.53032768 | P63: =O63 -> 0.53032768 | Q63: =P63 -> 0.53032768
C65: SG&A | D65: =-D12 -> 111.5 | E65: =-E12 -> 86.7 | F65: =-F12 -> 64.1 | G65: =-G12 -> 51 | H65: =-H12 -> 56.1 | I65: =-I12 -> 53.2 | J65: =-J12 -> 52.671107 | K65: =-K12 -> 45.808258 | ... Q65: =-Q12 -> 40.720018
C66: (% of Revenue) | D66: =+D65/D$5 -> 0.066266492 | E66: =+E65/E$5 -> 0.062101569 | F66: =+F65/F$5 -> 0.049867745 | G66: =+G65/G$5 -> 0.028601873 | H66: =+H65/H$5 -> 0.034330824 | I66: =+I65/I$5 -> 0.034660238 | J66: =AVERAGE(D66:I66) -> 0.045971457 | K66: =J66 -> 0.045971457 | L66: =K66 -> 0.045971457 | M66: =L66 -> 0.045971457 | N66: =M66 -> 0.045971457 | O66: =N66 -> 0.045971457 | P66: =O66 -> 0.045971457 | Q66: =P66 -> 0.045971457
C68: Capex | D68: =-CFS!D26 -> 261.5 | E68: =-CFS!E26 -> 217.3 | F68: =-CFS!F26 -> 150.4 | G68: =-CFS!G26 -> 263.8 | H68: =-CFS!H26 -> 262.3 | I68: =-CFS!I26 -> 196.7 | J68: =J69*J5 -> 170.8446 | K68: =K69*K5 -> 153.56644 | L68: =L69*L5 -> 159.69338 | M68: =M69*M5 -> 161.82974 | N68: =N69*N5 -> 163.67816 | O68: =O69*O5 -> 165.22867 | P68: =P69*P5 -> 164.3956 | Q68: =Q69*Q5 -> 163.08177
C69: (% of Revenue) | D69: =D68/D5 -> 0.15541424 | E69: =E68/E5 -> 0.15564788 | F69: =F68/F5 -> 0.11700638 | G69: =G68/G5 -> 0.14794459 | H69: =H68/H5 -> 0.16051649 | I69: =I68/I5 -> 0.12815167 | J69: =AVERAGE(D69:I69)+$S$69 -> 0.14911354 | K69: =J69+$S$69 -> 0.15411354 | L69: =K69+$S$69 -> 0.15911354 | M69: =L69+$S$69 -> 0.16411354 | N69: =M69+$S$69 -> 0.16911354 | O69: =N69+$S$69 -> 0.17411354 | P69: =O69+$S$69 -> 0.17911354 | Q69: =P69+$S$69 -> 0.18411354 | S69: 0.005
C71: Impair. of Oil, Gas & Mineral Prop. | D71: =ABS(D14) -> 0 | E71: =ABS(E14) -> 0 | F71: =ABS(F14) -> 114.2 | G71: =ABS(G14) -> 496.4 | H71: =ABS(H14) -> 27 | I71: =ABS(I14) -> 212.6 | J71: =J72*J5 -> 155.32415 | K71: =K72*K5 -> 146.72535 | L71: =L72*L5 -> 114.87933 | M71: =M72*M5 -> 137.01346 | N71: =N72*N5 -> 134.58682 | O71: =O72*O5 -> 132.78794 | P71: =P72*P5 -> 126.75076 | Q71: =Q72*Q5 -> 127.55715
C72: (% of Revenue) | D72: =D71/D5 -> 0 | E72: =E71/E5 -> 0 | F72: =F71/F5 -> 0.08884394 | G72: =G71/G5 -> 0.27839157 | H72: =H71/H5 -> 0.016522857 | I72: =I71/I5 -> 0.13851065 | J72: =AVERAGE(F72:I72)+$S$72 -> 0.13556725 | K72: =AVERAGE(G72:J72)+$S$72 -> 0.14724808 | L72: =AVERAGE(H72:K72)+$S$72 -> 0.11446221 | M72: =AVERAGE(I72:L72)+$S$72 -> 0.13894705 | N72: =AVERAGE(J72:M72)+$S$72 -> 0.13905615 | O72: =AVERAGE(K72:N72)+$S$72 -> 0.13992837 | P72: =AVERAGE(L72:O72)+$S$72 -> 0.13809845 | Q72: =AVERAGE(M72:P72)+$S$72 -> 0.1440075 | S72: 0.005
C74: Other Operating Expense/(Income) | D74: =D15 -> -17.8 | E74: =E15 -> -38.9 | F74: =F15 -> -7.6 | G74: =G15 -> -7 | H74: =H15 -> 12.1 | I74: =I15 -> 59 | J74: =J5*J75 -> -44.040892 | K74: =K5*K75 -> -38.302528 | L74: =L5*L75 -> -38.579064 | M74: =M5*M75 -> -37.904069 | N74: =N5*N75 -> -37.20354 | O74: =O5*O75 -> -36.477476 | P74: =P5*P75 -> -35.280416 | Q74: =Q5*Q75 -> -34.048001
C75: (% of Revenue) | D75: =D74/D5 -> -0.010578866 | E75: =E74/E5 -> -0.027863334 | F75: =F74/F5 -> -0.0059125564 | G75: =G74/G5 -> -0.0039257473 | H75: =H74/H5 -> 0.0074046876 | I75: =I74/I5 -> 0.038438986 | J75: =-I75 -> -0.038438986 | K75: =J75 -> -0.038438986 | L75: =K75 -> -0.038438986 | M75: =L75 -> -0.038438986 | N75: =M75 -> -0.038438986 | O75: =N75 -> -0.038438986 | P75: =O75 -> -0.038438986 | Q75: =P75 -> -0.038438986
C78: Depreciation & Amort. | D78: =D49 -> 724.6 | E78: =E49 -> 467.1 | F78: =F49 -> 378.9 | G78: =G49 -> 425.8 | H78: =H49 -> 436.6 | I78: =I49 -> 444.2 | J78: =J79*J5 -> 354.29339 | K78: =K79*K5 -> 308.13028 | L78: =L79*L5 -> 310.35492 | M78: =M79*M5 -> 304.92483 | N78: =N79*N5 -> 299.28932 | O78: =O79*O5 -> 293.44838 | P78: =P79*P5 -> 283.81847 | Q78: =Q79*Q5 -> 273.90412
C79: (% of Revenue) | D79: =D78/D5 -> 0.43064305 | E79: =E78/E5 -> 0.33457489 | F79: =F78/F5 -> 0.29477206 | G79: =G78/G5 -> 0.2387976 | H79: =H78/H5 -> 0.26718071 | I79: =I78/I5 -> 0.28939996 | J79: =AVERAGE(D79:I79) -> 0.30922804 | K79: =J79 -> 0.30922804 | L79: =K79 -> 0.30922804 | M79: =L79 -> 0.30922804 | N79: =M79 -> 0.30922804 | O79: =N79 -> 0.30922804 | P79: =O79 -> 0.30922804 | Q79: =P79 -> 0.30922804
C80: Amortization of Intangibles | D80: =D50 -> 16.3 | E80: =E50 -> 13.1 | F80: =F50 -> 7.6 | G80: =G50 -> 6 | H80: =H50 -> 10.1 | I80: =I50 -> 11.4 | J80: =J81*D5 -> 11.765894 | K80: =K81*E5 -> 9.1354775 | L80: =L81*F5 -> 7.8027433 | M80: =M81*G5 -> 10.870798 | N80: =N81*H5 -> 10.706372 | O80: =O81*I5 -> 10.151356 | P80: =P81*J5 -> 7.4221957 | Q80: =Q81*K5 -> 6.3696527
C81: (% of Revenue) | D81: =D80/D5 -> 0.0096873886 | E81: =E80/E5 -> 0.009383282 | F81: =F80/F5 -> 0.0059125564 | G81: =G80/G5 -> 0.0033649263 | H81: =H80/H5 -> 0.0061807723 | I81: =I80/I5 -> 0.007427194 | J81: =AVERAGE(D81:I81) -> 0.0069926866 | K81: =AVERAGE(E81:J81) -> 0.0065435696 | L81: =AVERAGE(F81:K81) -> 0.0060702842 | M81: =AVERAGE(G81:L81) -> 0.0060965721 | N81: =AVERAGE(H81:M81) -> 0.0065518465 | O81: =AVERAGE(I81:N81) -> 0.0066136921 | P81: =AVERAGE(J81:O81) -> 0.0064781085 | Q81: =AVERAGE(K81:P81) -> 0.0063923455
C82: Depreciation Adjustment | D82: =D51 -> -85.9 | E82: =E51 -> -72.4 | F82: =F51 -> -60.6 | G82: =G51 -> -60.9 | H82: =H51 -> -81.4 | I82: =I51 -> -91.4 | J82: =J83*D5 -> -82.327026 | K82: =K83*E5 -> -67.814923 | L82: =L83*F5 -> -61.734135 | M82: =M83*G5 -> -85.899473 | N82: =N83*H5 -> -82.539922 | O82: =O83*I5 -> -77.707691 | P82: =P83*J5 -> -56.301906 | Q82: =Q83*K5 -> -49.001179
C83: (% of Revenue) | D83: =D82/D5 -> -0.051051943 | E83: =E82/E5 -> -0.051858749 | F83: =F82/F5 -> -0.047144858 | G83: =G82/G5 -> -0.034154001 | H83: =H82/H5 -> -0.049813353 | I83: =I82/I5 -> -0.059547853 | J83: =AVERAGE(D83:I83) -> -0.04892846 | K83: =AVERAGE(E83:J83) -> -0.048574546 | L83: =AVERAGE(F83:K83) -> -0.048027178 | M83: =AVERAGE(G83:L83) -> -0.048174232 | N83: =AVERAGE(H83:M83) -> -0.050510937 | O83: =AVERAGE(I83:N83) -> -0.050627201 | P83: =AVERAGE(J83:O83) -> -0.049140426 | Q83: =AVERAGE(K83:P83) -> -0.049175753
C84: Impairment of Oil, Gas & Mineral Properties | D84: =D52 -> 0 | E84: =E52 -> 250 | F84: =F52 -> 54.3 | G84: =G52 -> 496.4 | H84: =H52 -> 426.1 | I84: =I52 -> 200.8 | J84: =J85*D5 -> 249.9456 | K84: =K85*E5 -> 241.95129 | L84: =L85*F5 -> 221.53132 | M84: =M85*G5 -> 345.9708 | N84: =N85*H5 -> 294.08417 | O84: =O85*I5 -> 255.5645 | P84: =P85*J5 -> 197.58081 | Q84: =Q85*K5 -> 175.80625
C85: (% of Revenue) | D85: =D84/D5 -> 0 | E85: =E84/E5 -> 0.17907027 | F85: =F84/F5 -> 0.04224366 | G85: =G84/G5 -> 0.27839157 | H85: =H84/H5 -> 0.26075516 | I85: =I84/I5 -> 0.13082285 | J85: =AVERAGE(D85:I85) -> 0.14854725 | K85: =AVERAGE(E85:J85) -> 0.17330513 | L85: =AVERAGE(F85:K85) -> 0.17234427 | M85: =AVERAGE(G85:L85) -> 0.1940277 | N85: =AVERAGE(H85:M85) -> 0.17996706 | O85: =AVERAGE(I85:N85) -> 0.16650238 | P85: =AVERAGE(J85:O85) -> 0.17244896 | Q85: =AVERAGE(K85:P85) -> 0.17643258
C86: Total Depreciation & Amort. | D86: =D78+D80+D82 -> 655 | E86: =E78+E80+E82 -> 407.8 | F86: =F78+F80+F82 -> 325.9 | G86: =G78+G80+G82 -> 370.9 | H86: =H78+H80+H82 -> 365.3 | I86: =I78+I80+I82 -> 364.2 | J86: =J78+J80+J82+J84 -> 533.67787 | K86: =K78+K80+K82+K84 -> 491.40212 | L86: =L78+L80+L82+L84 -> 477.95485 | M86: =M78+M80+M82+M84 -> 575.86695 | N86: =N78+N80+N82+N84 -> 521.53994 | O86: =O78+O80+O82+O84 -> 481.45655 | P86: =P78+P80+P82+P84 -> 432.51957 | Q86: =Q78+Q80+Q82+Q84 -> 407.07884

Sheet BS
D1: 2019 | E1: =D1+1 -> 2020 | F1: =E1+1 -> 2021 | G1: =F1+1 -> 2022 | H1: =G1+1 -> 2023 | I1: =H1+1 -> 2024 | J1: =I1+1 -> 2025 | K1: =J1+1 -> 2026 | L1: =K1+1 -> 2027 | ... N1: =M1+1 -> 2029 | O1: =+N1+1 -> 2030 | P1: =+O1+1 -> 2031 | Q1: =+P1+1 -> 2032
C2: Tullow Oil Balance Sheet
C4: Balance Sheet
C5: Assets:
C6: Cash And Equivalents | D6: 288.8 | E6: 805.4 | F6: 469.1 | G6: 636.3 | H6: 499 | I6: 555.1 | J6: =+I6+CFS!J45 -> 388.58455 | K6: =+J6+CFS!K45 -> 374.62667 | L6: =+K6+CFS!L45 -> 526.2095 | M6: =+L6+CFS!M45 -> 824.84174 | N6: =+M6+CFS!N45 -> 1080.7474 | O6: =+N6+CFS!O45 -> 1306.872 | P6: =+O6+CFS!P45 -> 1479.0295 | Q6: =+P6+CFS!Q45 -> 1383.9009
C7: Total Cash & ST Investments | D7: =SUM(D6) -> 288.8 | E7: =SUM(E6) -> 805.4 | F7: =SUM(F6) -> 469.1 | G7: =SUM(G6) -> 636.3 | H7: =SUM(H6) -> 499 | I7: =SUM(I6) -> 555.1 | J7: =J6 -> 388.58455 | K7: =K6 -> 374.62667 | L7: =L6 -> 526.2095 | M7: =M6 -> 824.84174 | N7: =N6 -> 1080.7474 | O7: =O6 -> 1306.872 | P7: =P6 -> 1479.0295 | Q7: =Q6 -> 1383.9009
C9: Accounts Receivable | D9: 38.7 | E9: 79 | F9: 99.8 | G9: 26.8 | H9: 43.5 | I9: 137.9 | J9: =IS!J5/365*NWC!J20 -> 102.2179 | K9: =IS!K5/365*NWC!K20 -> 83.439286 | L9: =IS!L5/365*NWC!L20 -> 84.041699 | M9: =IS!M5/365*NWC!M20 -> 82.571273 | N9: =IS!N5/365*NWC!N20 -> 81.04522 | O9: =IS!O5/365*NWC!O20 -> 79.463541 | P9: =IS!P5/365*NWC!P20 -> 76.855834 | Q9: =IS!Q5/365*NWC!Q20 -> 74.171107
C10: Other Receivables | D10: 754.7 | E10: 558.3 | F10: 642.3 | G10: 467.7 | H10: 501.9 | I10: 357.1 | J10: =IS!J5/365*NWC!J22 -> 448.26347 | K10: =IS!K5/365*NWC!K22 -> 384.39641 | L10: =IS!L5/365*NWC!L22 -> 381.67225 | M10: =IS!M5/365*NWC!M22 -> 369.59116 | N10: =IS!N5/365*NWC!N22 -> 357.45717 | O10: =IS!O5/365*NWC!O22 -> 345.28119 | P10: =IS!P5/365*NWC!P22 -> 328.92111 | Q10: =IS!Q5/365*NWC!Q22 -> 312.57772
C11: Total Receivables | D11: =SUM(D9:D10) -> 793.4 | E11: =SUM(E9:E10) -> 637.3 | F11: =SUM(F9:F10) -> 742.1 | G11: =SUM(G9:G10) -> 494.5 | H11: =SUM(H9:H10) -> 545.4 | I11: =SUM(I9:I10) -> 495 | J11: =SUM(J9:J10) -> 550.48137 | K11: =SUM(K9:K10) -> 467.8357 | ... Q11: =SUM(Q9:Q10) -> 386.74883
C13: Inventory | D13: 191.5 | E13: 96.1 | F13: 134.8 | G13: 181.6 | H13: 107.3 | I13: 132.4 | J13: =IS!$J$8/365*-NWC!J24 -> 108.57666 | K13: =IS!K8/365*-NWC!K24 -> 94.429526 | L13: =IS!L8/365*-NWC!L24 -> 95.111286 | M13: =IS!M8/365*-NWC!M24 -> 93.447182 | N13: =IS!N8/365*-NWC!N24 -> 91.720125 | O13: =IS!O8/365*-NWC!O24 -> 89.930115 | P13: =IS!P8/365*-NWC!P24 -> 86.978933 | Q13: =IS!Q8/365*-NWC!Q24 -> 83.940585
C14: Prepaid Exp. | D14: 69.5 | E14: 60.7 | F14: 49.6 | G14: 31.3 | H14: 21.1 | I14: 17.1 | J14: =NWC!J26 -> 31.503395 | K14: =NWC!K26 -> 27.39862 | L14: =NWC!L26 -> 27.596432 | M14: =NWC!M26 -> 27.113594 | N14: =NWC!N26 -> 26.61249 | O14: =NWC!O26 -> 26.093121 | P14: =NWC!P26 -> 25.236839 | Q14: =NWC!Q26 -> 24.355266
C15: Other Current Assets | D15: 148.1 | E15: 307.3 | F15: 32.3 | G15: 84.3 | H15: 107.8 | I15: 24.7 | J15: =NWC!J29 -> 88.335898 | K15: =NWC!K29 -> 76.82606 | L15: =NWC!L29 -> 77.380727 | M15: =NWC!M29 -> 76.026843 | N15: =NWC!N29 -> 74.621743 | O15: =NWC!O29 -> 73.165424 | P15: =NWC!P29 -> 70.764399 | Q15: =NWC!Q29 -> 68.292457
C16: Total Current Assets | D16: =SUM(D13:D15)+D11+D7 -> 1491.3 | E16: =SUM(E13:E15)+E11+E7 -> 1906.8 | F16: =SUM(F13:F15)+F11+F7 -> 1427.9 | G16: =SUM(G13:G15)+G11+G7 -> 1428 | H16: =SUM(H13:H15)+H11+H7 -> 1280.6 | I16: =SUM(I13:I15)+I11+I7 -> 1224.3 | J16: =SUM(J13:J15)+J11+J7 -> 1167.4819 | K16: =SUM(K13:K15)+K11+K7 -> 1041.1166 | ... Q16: =SUM(Q13:Q15)+Q11+Q7 -> 1947.238
C18: Gross Property, Plant & Equipment | D18: 12508.7 | E18: 11548.4 | F18: 11682.9 | G18: 12409.4 | H18: 12572.8 | I18: 12661.6 | J18: =I18-CFS!J26+'Forecast Assumptions'!D89-'Forecast Assumptions'!D88 -> 12627.878 | K18: =J18-CFS!K26+'Forecast Assumptions'!E89-'Forecast Assumptions'!E88 -> 12745.078 | L18: =K18-CFS!L26+'Forecast Assumptions'!F89-'Forecast Assumptions'!F88 -> 12904.771 | M18: =L18-CFS!M26+'Forecast Assumptions'!G89-'Forecast Assumptions'!G88 -> 13059.327 | N18: =M18-CFS!N26+'Forecast Assumptions'!H89-'Forecast Assumptions'!H88 -> 13215.732 | O18: =N18-CFS!O26+'Forecast Assumptions'!I89-'Forecast Assumptions'!I88 -> 13373.688 | P18: =O18-CFS!P26+'Forecast Assumptions'!J89-'Forecast Assumptions'!J88 -> 13530.81 | Q18: =P18-CFS!Q26+'Forecast Assumptions'!K89-'Forecast Assumptions'!K88 -> 13686.618
C19: Accumulated Depreciation | D19: -8617 | E19: -8310.5 | F19: -8768.3 | G19: -9428 | H19: -10040 | I19: -10337.5 | J19: =I19-CFS!J10 -> -10953.505 | K19: =J19-CFS!K10 -> -11512.722 | L19: =K19-CFS!L10 -> -12052.411 | M19: =L19-CFS!M10 -> -12714.177 | N19: =M19-CFS!N10 -> -13318.257 | O19: =N19-CFS!O10 -> -13877.421 | P19: =O19-CFS!P10 -> -14366.243 | Q19: =P19-CFS!Q10 -> -14822.323
C20: Net Property, Plant & Equipment | D20: =SUM(D18:D19) -> 3891.7 | E20: =SUM(E18:E19) -> 3237.9 | F20: =SUM(F18:F19) -> 2914.6 | G20: =SUM(G18:G19) -> 2981.4 | H20: =SUM(H18:H19) -> 2532.8 | I20: =SUM(I18:I19) -> 2324.1 | J20: =SUM(J18:J19) -> 1674.373 | K20: =SUM(K18:K19) -> 1232.3558 | ... Q20: =SUM(Q18:Q19) -> -1135.7046
C22: Goodwill | D22: 0 | E22: 0 | F22: 0 | G22: 0 | H22: 0 | I22: 44.9 | J22: =I22 -> 44.9 | K22: =J22 -> 44.9 | L22: =K22 -> 44.9 | M22: =L22 -> 44.9 | N22: =M22 -> 44.9 | O22: =N22 -> 44.9 | P22: =O22 -> 44.9 | Q22: =P22 -> 44.9
C23: Other Intangibles | D23: 1764.4 | E23: 368.2 | F23: 354.6 | G23: 288.6 | H23: 287 | I23: 109.1 | J23: =I23 -> 109.1 | K23: =J23 -> 109.1 | L23: =K23 -> 109.1 | M23: =L23 -> 109.1 | N23: =M23 -> 109.1 | O23: =N23 -> 109.1 | P23: =O23 -> 109.1 | Q23: =P23 -> 109.1
C24: Deferred Tax Assets, LT | D24: 517.5 | E24: 494.3 | F24: 354.4 | G24: 14.5 | H24: 19.6 | I24: 8.3 | J24: =I24 -> 8.3 | K24: =J24 -> 8.3 | L24: =K24 -> 8.3 | M24: =L24 -> 8.3 | N24: =M24 -> 8.3 | O24: =N24 -> 8.3 | P24: =O24 -> 8.3 | Q24: =P24 -> 8.3
C25: Other Long-Term Assets | D25: 626.3 | E25: 550 | F25: 489.1 | G25: 327.1 | H25: 338.6 | I25: 340.8 | J25: =I25 -> 340.8 | K25: =J25 -> 340.8 | L25: =K25 -> 340.8 | M25: =L25 -> 340.8 | N25: =M25 -> 340.8 | O25: =N25 -> 340.8 | P25: =O25 -> 340.8 | Q25: =P25 -> 340.8
C26: Total Assets | D26: =SUM(D22:D25)+D20+D16 -> 8291.2 | E26: =SUM(E22:E25)+E20+E16 -> 6557.2 | F26: =SUM(F22:F25)+F20+F16 -> 5540.6 | G26: =SUM(G22:G25)+G20+G16 -> 5039.6 | H26: =SUM(H22:H25)+H20+H16 -> 4458.6 | I26: =SUM(I22:I25)+I20+I16 -> 4051.5 | J26: =SUM(J22:J25)+J20+J16 -> 3344.9549 | K26: =SUM(K22:K25)+K20+K16 -> 2776.5723 | ... Q26: =SUM(Q22:Q25)+Q20+Q16 -> 1314.6334
C28: Liabilities:
C29: Accounts Payable | D29: 95.4 | E29: 38.3 | F29: 60.2 | G29: 68.4 | H29: 22.3 | I29: 75.7 | J29: =-IS!J8/365*NWC!J32 -> 46.260816 | K29: =-IS!K8/365*NWC!K32 -> 40.233204 | L29: =-IS!L8/365*NWC!L32 -> 40.523679 | M29: =-IS!M8/365*NWC!M32 -> 39.814661 | N29: =-IS!N8/365*NWC!N32 -> 39.078821 | O29: =-IS!O8/365*NWC!O32 -> 38.316158 | P29: =-IS!P8/365*NWC!P32 -> 37.05876 | Q29: =-IS!Q8/365*NWC!Q32 -> 35.764224
C30: Accrued Exp. | D30: 695.5 | E30: 418.3 | F30: 381.3 | G30: 379.2 | H30: 498.6 | I30: 373.8 | J30: =J61 -> 401.00725 | K30: =K61 -> 348.7575 | L30: =L61 -> 351.27545 | M30: =M61 -> 345.1294 | N30: =N61 -> 338.75084 | O30: =O61 -> 332.13978 | P30: =P61 -> 321.24015 | Q30: =Q61 -> 310.01859
C31: Short-term Borrowings | D31: 0 | E31: 0 | F31: 0 | G31: 0 | H31: 0 | I31: 0 | J31: ='Debt Schedule'!J18 -> 0 | K31: ='Debt Schedule'!K18 -> 0 | L31: ='Debt Schedule'!L18 -> 0 | M31: ='Debt Schedule'!M18 -> 0 | N31: ='Debt Schedule'!N18 -> 0 | O31: ='Debt Schedule'!O18 -> 0 | P31: ='Debt Schedule'!P18 -> 0 | Q31: ='Debt Schedule'!Q18 -> 0
C32: Curr. Port. of LT Debt | D32: 0 | E32: 3170.5 | F32: 100 | G32: 100 | H32: 100 | I32: 589.4 | J32: =ABS(SUM('Debt Schedule'!J38:J39,'Debt Schedule'!J28:J29,'Debt Schedule'!J48:J49)) -> 775.55066 | K32: =ABS(SUM('Debt Schedule'!K38:K39,'Debt Schedule'!K28:K29,'Debt Schedule'!K48:K49)) -> 351.02934 | L32: =ABS(SUM('Debt Schedule'!L38:L39,'Debt Schedule'!L28:L29,'Debt Schedule'!L48:L49)) -> 127.64 | M32: =ABS(SUM('Debt Schedule'!M38:M39,'Debt Schedule'!M28:M29,'Debt Schedule'!M48:M49)) -> 127.64 | N32: =ABS(SUM('Debt Schedule'!N38:N39,'Debt Schedule'!N28:N29,'Debt Schedule'!N48:N49)) -> 127.64 | O32: =ABS(SUM('Debt Schedule'!O38:O39,'Debt Schedule'!O28:O29,'Debt Schedule'!O48:O49)) -> 127.64 | P32: =ABS(SUM('Debt Schedule'!P38:P39,'Debt Schedule'!P28:P29,'Debt Schedule'!P48:P49)) -> 127.64 | Q32: =ABS(SUM('Debt Schedule'!Q38:Q39,'Debt Schedule'!Q28:Q29,'Debt Schedule'!Q48:Q49)) -> 382.92
C33: Curr. Port. of Leases | D33: 284.2 | E33: 240.8 | F33: 251.5 | G33: 251.2 | H33: 185.7 | I33: 151.9 | J33: ='Debt Schedule'!J59 -> 132.95654 | K33: ='Debt Schedule'!K59 -> 114.01309 | L33: ='Debt Schedule'!L59 -> 95.069628 | M33: ='Debt Schedule'!M59 -> 76.12617 | N33: ='Debt Schedule'!N59 -> 57.182713 | O33: ='Debt Schedule'!O59 -> 38.239255 | P33: ='Debt Schedule'!P59 -> 19.295798 | Q33: ='Debt Schedule'!Q59 -> 0.35234002
C34: Curr. Income Taxes Payable | D34: 159.6 | E34: 52.2 | F34: 115.1 | G34: 186 | H34: 230.5 | I34: 175.3 | J34: =+I34 -> 175.3 | K34: =+J34 -> 175.3 | L34: =+K34 -> 175.3 | M34: =+L34 -> 175.3 | N34: =+M34 -> 175.3 | O34: =+N34 -> 175.3 | P34: =+O34 -> 175.3 | Q34: =+P34 -> 175.3
C35: Other Current Liabilities | D35: 240.1 | E35: 488.2 | F35: 435.5 | G35: 336.5 | H35: 188.9 | I35: 171.3 | J35: =J64 -> 194.77495 | K35: =K64 -> 169.3965 | L35: =L64 -> 170.61951 | M35: =M64 -> 167.63428 | N35: =N64 -> 164.53612 | O35: =O64 -> 161.32504 | P35: =P64 -> 156.03093 | Q35: =Q64 -> 150.58046
C36: Total Current Liabilities | D36: =SUM(D29:D35) -> 1474.8 | E36: =SUM(E29:E35) -> 4408.3 | F36: =SUM(F29:F35) -> 1343.6 | G36: =SUM(G29:G35) -> 1321.3 | H36: =SUM(H29:H35) -> 1226 | I36: =SUM(I29:I35) -> 1537.4 | J36: =SUM(J29:J35) -> 1725.8502 | K36: =SUM(K29:K35) -> 1198.7296 | ... Q36: =SUM(Q29:Q35) -> 1054.9356
C38: Long-Term Debt | D38: 3071.7 | E38: 0 | F38: 2468.7 | G38: 2372.8 | H38: 1984.6 | I38: 1386.4 | J38: ='Debt Schedule'!J40+'Debt Schedule'!J30+'Debt Schedule'!J50-J32 -> 596.59869 | K38: ='Debt Schedule'!K40+'Debt Schedule'!K30+'Debt Schedule'!K50-K32 -> 670.09066 | L38: ='Debt Schedule'!L40+'Debt Schedule'!L30+'Debt Schedule'!L50-L32 -> 765.84 | M38: ='Debt Schedule'!M40+'Debt Schedule'!M30+'Debt Schedule'!M50-M32 -> 638.2 | N38: ='Debt Schedule'!N40+'Debt Schedule'!N30+'Debt Schedule'!N50-N32 -> 510.56 | O38: ='Debt Schedule'!O40+'Debt Schedule'!O30+'Debt Schedule'!O50-O32 -> 382.92 | P38: ='Debt Schedule'!P40+'Debt Schedule'!P30+'Debt Schedule'!P50-P32 -> 255.28 | Q38: ='Debt Schedule'!Q40+'Debt Schedule'!Q30+'Debt Schedule'!Q50-Q32 -> -382.92
C39: Long-Term Leases | D39: 1140.9 | E39: 975.7 | F39: 911.9 | G39: 732.9 | H39: 721 | I39: 581 | J39: ='Debt Schedule'!J71 -> 508.54346 | K39: ='Debt Schedule'!K71 -> 436.08691 | L39: ='Debt Schedule'!L71 -> 363.63037 | M39: ='Debt Schedule'!M71 -> 291.17383 | N39: ='Debt Schedule'!N71 -> 218.71729 | O39: ='Debt Schedule'!O71 -> 146.26074 | P39: ='Debt Schedule'!P71 -> 73.804202 | Q39: ='Debt Schedule'!Q71 -> 1.34766
C40: Def. Tax Liability, Non-Curr. | D40: 793.4 | E40: 673.3 | F40: 677.3 | G40: 551.5 | H40: 420.5 | I40: 413 | J40: =+I40 -> 413 | K40: =+J40 -> 413 | L40: =+K40 -> 413 | M40: =+L40 -> 413 | N40: =+M40 -> 413 | O40: =+N40 -> 413 | P40: =+O40 -> 413 | Q40: =+P40 -> 413
C41: Other Non-Current Liabilities | D41: 826.8 | E41: 709.9 | F41: 605.2 | G41: 520.6 | H41: 465.9 | I41: 406.4 | J41: =I41 -> 406.4 | K41: =J41 -> 406.4 | L41: =K41 -> 406.4 | M41: =L41 -> 406.4 | N41: =M41 -> 406.4 | O41: =N41 -> 406.4 | P41: =O41 -> 406.4 | Q41: =P41 -> 406.4
C42: Total Liabilities | D42: =SUM(D38:D41)+D36 -> 7307.6 | E42: =SUM(E38:E41)+E36 -> 6767.2 | F42: =SUM(F38:F41)+F36 -> 6006.7 | G42: =SUM(G38:G41)+G36 -> 5499.1 | H42: =SUM(H38:H41)+H36 -> 4818 | I42: =SUM(I38:I41)+I36 -> 4324.2 | J42: =SUM(J38:J41)+J36 -> 3650.3924 | K42: =SUM(K38:K41)+K36 -> 3124.3072 | ... Q42: =SUM(Q38:Q41)+Q36 -> 1492.7633
C44: Equity:
C45: Common Stock | D45: 210.9 | E45: 211.7 | F45: 214.2 | G45: 215.2 | H45: 216.7 | I45: 217.5 | J45: =I45 -> 217.5 | K45: =J45 -> 217.5 | L45: =K45 -> 217.5 | M45: =L45 -> 217.5 | N45: =M45 -> 217.5 | O45: =N45 -> 217.5 | P45: =O45 -> 217.5 | Q45: =P45 -> 217.5
C46: Additional Paid In Capital | D46: 1294.7 | E46: 1294.7 | F46: 1294.7 | G46: 1294.7 | H46: 1294.7 | I46: 1294.7 | J46: =I46 -> 1294.7 | K46: =J46 -> 1294.7 | L46: =K46 -> 1294.7 | M46: =L46 -> 1294.7 | N46: =M46 -> 1294.7 | O46: =N46 -> 1294.7 | P46: =O46 -> 1294.7 | Q46: =P46 -> 1294.7
C47: Retained Earnings | D47: -1070.6 | E47: -2272 | F47: -2295.2 | G47: -2241.3 | H47: -2346.4 | I47: -2285.7 | J47: =I47+IS!J40-'Debt Schedule'!J77 -> -2318.4374 | K47: =J47+IS!K40-'Debt Schedule'!K77 -> -2360.7349 | L47: =K47+IS!L40-'Debt Schedule'!L77 -> -2374.8266 | M47: =L47+IS!M40-'Debt Schedule'!M77 -> -2371.5764 | N47: =M47+IS!N40-'Debt Schedule'!N77 -> -2351.3866 | O47: =N47+IS!O40-'Debt Schedule'!O77 -> -2314.3693 | P47: =O47+IS!P40-'Debt Schedule'!P77 -> -2262.5962 | Q47: =P47+IS!Q40-'Debt Schedule'!Q77 -> -2191.1299
C48: Treasury Stock | D48: 0 | E48: 0 | F48: 0 | G48: 0 | H48: 0 | I48: 0 | J48: =I48 -> 0 | K48: =J48 -> 0 | L48: =K48 -> 0 | M48: =L48 -> 0 | N48: =M48 -> 0 | O48: =N48 -> 0 | P48: =O48 -> 0 | Q48: =P48 -> 0
C49: Comprehensive Inc. and Other | D49: 548.6 | E49: 555.6 | F49: 320.2 | G49: 271.9 | H49: 475.6 | I49: 500.8 | J49: =+I49 -> 500.8 | K49: =+J49 -> 500.8 | L49: =+K49 -> 500.8 | M49: =+L49 -> 500.8 | N49: =+M49 -> 500.8 | O49: =+N49 -> 500.8 | P49: =+O49 -> 500.8 | Q49: =+P49 -> 500.8
C50: Total Common Equity | D50: =SUM(D45:D49) -> 983.6 | E50: =SUM(E45:E49) -> -210 | F50: =SUM(F45:F49) -> -466.1 | G50: =SUM(G45:G49) -> -459.5 | H50: =SUM(H45:H49) -> -359.4 | I50: =SUM(I45:I49) -> -272.7 | J50: =SUM(J45:J49) -> -305.43744 | K50: =SUM(K45:K49) -> -347.73487 | ... Q50: =SUM(Q45:Q49) -> -178.12987
C52: Total Equity | D52: =D50 -> 983.6 | E52: =E50 -> -210 | F52: =F50 -> -466.1 | G52: =G50 -> -459.5 | H52: =H50 -> -359.4 | I52: =I50 -> -272.7 | J52: =J50 -> -305.43744 | K52: =K50 -> -347.73487 | ... Q52: =Q50 -> -178.12987
C54: Total Liabilities And Equity | D54: =D52+D42 -> 8291.2 | E54: =E52+E42 -> 6557.2 | F54: =F52+F42 -> 5540.6 | G54: =G52+G42 -> 5039.6 | H54: =H52+H42 -> 4458.6 | I54: =I52+I42 -> 4051.5 | J54: =J52+J42 -> 3344.9549 | K54: =K52+K42 -> 2776.5723 | ... Q54: =Q52+Q42 -> 1314.6334
C56: Balance Sheet Check | D56: =D54-D26 -> 0 | E56: =E54-E26 -> 0 | F56: =F54-F26 -> 0 | G56: =G54-G26 -> 0 | H56: =H54-H26 -> 0 | I56: =I54-I26 -> 0 | J56: =J54-J26 -> 0 | K56: =K54-K26 -> 0 | ... Q56: =Q54-Q26 -> -4.0927262e-12
C57: Capital IQ Balance Sheet | D57: 8291.2 | E57: 6557.2 | F57: 5540.6 | G57: 5039.6 | H57: 4458.6 | I57: 4051.5 | R57: .
C58: Capital IQ Check | D58: =D54-D57 -> 0 | E58: =E54-E57 -> 0 | F58: =F54-F57 -> 0 | G58: =G54-G57 -> 0 | H58: =H54-H57 -> 0 | I58: =I54-I57 -> 0
C60: Account | D60: 2019 | E60: =D60+1 -> 2020 | F60: =E60+1 -> 2021 | G60: =F60+1 -> 2022 | H60: =G60+1 -> 2023 | I60: =H60+1 -> 2024 | J60: =I60+1 -> 2025 | K60: =J60+1 -> 2026 | L60: =K60+1 -> 2027 | ... Q60: =P60+1 -> 2032
C61: =C30 -> Accrued Exp. | D61: =D30 -> 695.5 | E61: =E30 -> 418.3 | F61: =F30 -> 381.3 | G61: =G30 -> 379.2 | H61: =H30 -> 498.6 | I61: =I30 -> 373.8 | J61: =J62*IS!J5 -> 401.00725 | K61: =K62*IS!K5 -> 348.7575 | L61: =L62*IS!L5 -> 351.27545 | M61: =M62*IS!M5 -> 345.1294 | N61: =N62*IS!N5 -> 338.75084 | O61: =O62*IS!O5 -> 332.13978 | P61: =P62*IS!P5 -> 321.24015 | Q61: =Q62*IS!Q5 -> 310.01859
C62: (% of Revenue) | D62: =-D61/IS!J8 -> 1.1446393 | E62: =E61/IS!K5 -> 0.41979026 | F62: =F61/IS!L5 -> 0.37991553 | G62: =G61/IS!M5 -> 0.38455142 | H62: =H61/IS!N5 -> 0.51515739 | I62: =I61/IS!O5 -> 0.39390042 | J62: 0.35 | K62: =J62 -> 0.35 | L62: =K62 -> 0.35 | M62: =L62 -> 0.35 | N62: =M62 -> 0.35 | O62: =N62 -> 0.35 | P62: =O62 -> 0.35 | Q62: =P62 -> 0.35
C64: Other Current Liabilities | D64: =D35 -> 240.1 | E64: =E35 -> 488.2 | F64: =F35 -> 435.5 | G64: =G35 -> 336.5 | H64: =H35 -> 188.9 | I64: =I35 -> 171.3 | J64: =J65*IS!J5 -> 194.77495 | K64: =K65*IS!K5 -> 169.3965 | L64: =L65*IS!L5 -> 170.61951 | M64: =M65*IS!M5 -> 167.63428 | N64: =N65*IS!N5 -> 164.53612 | O64: =O65*IS!O5 -> 161.32504 | P64: =P65*IS!P5 -> 156.03093 | Q64: =Q65*IS!Q5 -> 150.58046
C65: (% of Revenue) | D65: =D64/IS!J5 -> 0.2095598 | E65: =E64/IS!K5 -> 0.48993928 | F65: =F64/IS!L5 -> 0.43391874 | G65: =G64/IS!M5 -> 0.34124882 | H65: =H64/IS!N5 -> 0.19517295 | I65: =I64/IS!O5 -> 0.18051135 | J65: 0.17 | K65: =J65 -> 0.17 | L65: =K65 -> 0.17 | M65: =L65 -> 0.17 | N65: =M65 -> 0.17 | O65: =N65 -> 0.17 | P65: =O65 -> 0.17 | Q65: =P65 -> 0.17

Sheet CFS
D1: 2019 | E1: =D1+1 -> 2020 | F1: =E1+1 -> 2021 | G1: =F1+1 -> 2022 | H1: =G1+1 -> 2023 | I1: =H1+1 -> 2024 | J1: =I1+1 -> 2025 | K1: =J1+1 -> 2026 | L1: =K1+1 -> 2027 | ... N1: =M1+1 -> 2029 | O1: =+N1+1 -> 2030 | P1: =+O1+1 -> 2031 | Q1: =+P1+1 -> 2032
C2: Tullow Oil Cash Flow Statement
C4: Cash Flow Statement
C5: Change in Cash: Operations
C6: Net Income | D6: =IS!D40 -> -1694.1 | E6: =IS!E40 -> -1221.5 | F6: =IS!F40 -> -80.7 | G6: =IS!G40 -> 49.1 | H6: =IS!H40 -> -109.6 | I6: =IS!I40 -> 54.6 | J6: =IS!J40 -> 79.498659 | K6: =IS!K40 -> 55.010888 | ... Q6: =IS!Q40 -> 79.207901
C7: Depreciation & Amort. | D7: 724.6 | E7: 467.1 | F7: 378.9 | G7: 425.8 | H7: 436.6 | I7: 444.2 | J7: =IS!J78 -> 354.29339 | K7: =IS!K78 -> 308.13028 | L7: =IS!L78 -> 310.35492 | M7: =IS!M78 -> 304.92483 | N7: =IS!N78 -> 299.28932 | O7: =IS!O78 -> 293.44838 | P7: =IS!P78 -> 283.81847 | Q7: =IS!Q78 -> 273.90412
C8: Amort. of Goodwill and Intangibles | D8: 16.3 | E8: 13.1 | F8: 7.6 | G8: 6 | H8: 10.1 | I8: 11.4 | J8: =IS!J80 -> 11.765894 | K8: =IS!K80 -> 9.1354775 | L8: =IS!L80 -> 7.8027433 | M8: =IS!M80 -> 10.870798 | N8: =IS!N80 -> 10.706372 | O8: =IS!O80 -> 10.151356 | P8: =IS!P80 -> 7.4221957 | Q8: =IS!Q80 -> 6.3696527
C9: Impair. of Oil, Gas & Mineral Prop. | D9: 0 | E9: 250 | F9: 114.2 | G9: 496.4 | H9: 426.1 | I9: 200.8 | J9: =IS!J84 -> 249.9456 | K9: =IS!K84 -> 241.95129 | L9: =IS!L84 -> 221.53132 | M9: =IS!M84 -> 345.9708 | N9: =IS!N84 -> 294.08417 | O9: =IS!O84 -> 255.5645 | P9: =IS!P84 -> 197.58081 | Q9: =IS!Q84 -> 175.80625
C10: Depreciation & Amort., Total | D10: =SUM(D7:D9) -> 740.9 | E10: =SUM(E7:E9) -> 730.2 | F10: =SUM(F7:F9) -> 500.7 | G10: =SUM(G7:G9) -> 928.2 | H10: =SUM(H7:H9) -> 872.8 | I10: =SUM(I7:I9) -> 656.4 | J10: =SUM(J7:J9) -> 616.00489 | K10: =SUM(K7:K9) -> 559.21705 | ... Q10: =SUM(Q7:Q9) -> 456.08002
C12: (Gain) Loss From Sale Of Assets | D12: -6.6 | E12: 3.4 | F12: -120.3 | G12: -3.1 | H12: -0.2 | I12: 0 | J12: =-IS!J30 -> -142.43333 | K12: =-IS!K30 -> -3.6333333 | L12: =-IS!L30 -> 0 | M12: =-IS!M30 -> -0.72666667 | N12: =-IS!N30 -> -0.72666667 | O12: =-IS!O30 -> -0.72666667 | P12: =-IS!P30 -> -0.72666667 | Q12: =-IS!Q30 -> -0.72666667
C13: Asset Write-down & Restructuring Costs | D13: 2013.8 | E13: 1021.7 | F13: 49.2 | G13: 0.1 | H13: 9 | I13: -38.9
C14: Stock-Based Compensation | D14: 24.8 | E14: 20.9 | F14: 11.6 | G14: 5.8 | H14: 6 | I14: 6.9 | J14: 0 | K14: 0 | L14: 0 | M14: 0 | N14: 0 | O14: 0 | P14: 0 | Q14: 0
C15: Net Cash From Discontinued Ops. | D15: 0 | E15: 0 | F15: 0 | G15: 0 | H15: 0 | I15: 0 | J15: 0 | K15: =J15 -> 0 | L15: =K15 -> 0 | M15: =L15 -> 0 | N15: =M15 -> 0 | O15: =N15 -> 0 | P15: =O15 -> 0 | Q15: =P15 -> 0
C16: Other Operating Activities | D16: 126.6 | E16: 25.5 | F16: 478.7 | G16: 50.4 | H16: 9.2 | I16: 54 | J16: =+BS!J35-BS!I35 -> 23.47495 | K16: =+BS!K35-BS!J35 -> -25.37845 | L16: =+BS!L35-BS!K35 -> 1.2230055 | M16: =+BS!M35-BS!L35 -> -2.9852255 | N16: =+BS!N35-BS!M35 -> -3.0981565 | O16: =+BS!O35-BS!N35 -> -3.2110875 | P16: =+BS!P35-BS!O35 -> -5.294106 | Q16: =+BS!Q35-BS!P35 -> -5.450472
C17: Change in Acc. Receivable | D17: 241.4 | E17: 195.2 | F17: -17.9 | G17: 288.4 | H17: -36.3 | I17: 0.7 | J17: =BS!I11-BS!J11 -> -55.481365 | K17: =BS!J11-BS!K11 -> 82.64567 | L17: =BS!K11-BS!L11 -> 2.1217491 | M17: =BS!L11-BS!M11 -> 13.551513 | N17: =BS!M11-BS!N11 -> 13.660044 | O17: =BS!N11-BS!O11 -> 13.757654 | P17: =BS!O11-BS!P11 -> 18.967791 | Q17: =BS!P11-BS!Q11 -> 19.028119
C18: Change In Inventories | D18: -56.6 | E18: 85.1 | F18: -41.9 | G18: -48 | H18: 66.6 | I18: -25.1 | J18: =BS!I13-BS!J13 -> 23.82334 | K18: =BS!J13-BS!K13 -> 14.147134 | L18: =BS!K13-BS!L13 -> -0.68176042 | M18: =BS!L13-BS!M13 -> 1.6641042 | N18: =BS!M13-BS!N13 -> 1.7270572 | O18: =BS!N13-BS!O13 -> 1.7900102 | P18: =BS!O13-BS!P13 -> 2.9511821 | Q18: =BS!P13-BS!Q13 -> 3.0383478
C19: Change In Prepaid Expenses | J19: =+BS!I14-BS!J14 -> -14.403395 | K19: =+BS!J14-BS!K14 -> 4.1047749 | L19: =+BS!K14-BS!L14 -> -0.19781202 | M19: =+BS!L14-BS!M14 -> 0.48283795 | N19: =+BS!M14-BS!N14 -> 0.5011037 | O19: =+BS!N14-BS!O14 -> 0.51936945 | P19: =+BS!O14-BS!P14 -> 0.85628215 | Q19: =+BS!P14-BS!Q14 -> 0.88157318
C20: Change in Acc. Payable | D20: -131.5 | E20: -161.9 | F20: 7.5 | G20: -193.1 | H20: 58.7 | I20: 49.9 | J20: =BS!J29-BS!I29 -> -29.439184 | K20: =BS!K29-BS!J29 -> -6.0276119 | L20: =BS!L29-BS!K29 -> 0.29047489 | M20: =BS!M29-BS!L29 -> -0.70901812 | N20: =BS!N29-BS!M29 -> -0.73584025 | O20: =BS!O29-BS!N29 -> -0.76266239 | P20: =BS!P29-BS!O29 -> -1.2573982 | Q20: =BS!Q29-BS!P29 -> -1.2945365
C21: Change in Other Net Operating Assets | D21: 0 | E21: 0 | F21: 0 | G21: 0 | H21: 0 | I21: 0 | J21: =BS!I15-BS!J15 -> -63.635898 | K21: =BS!J15-BS!K15 -> 11.509838 | L21: =BS!K15-BS!L15 -> -0.55466727 | M21: =BS!L15-BS!M15 -> 1.3538834 | N21: =BS!M15-BS!N15 -> 1.4051008 | O21: =BS!N15-BS!O15 -> 1.4563182 | P21: =BS!O15-BS!P15 -> 2.4010254 | Q21: =BS!P15-BS!Q15 -> 2.4719418
C22: Change in Accrued Expenses | D22: 0 | E22: 0 | F22: 0 | G22: 0 | H22: 0 | I22: 0 | J22: =+BS!J30-BS!I30 -> 27.20725 | K22: =+BS!K30-BS!J30 -> -52.24975 | L22: =+BS!L30-BS!K30 -> 2.5179525 | M22: =+BS!M30-BS!L30 -> -6.1460525 | N22: =+BS!N30-BS!M30 -> -6.3785575 | O22: =+BS!O30-BS!N30 -> -6.6110625 | P22: =+BS!P30-BS!O30 -> -10.89963 | Q22: =+BS!Q30-BS!P30 -> -11.22156
C23: Cash from Ops. | D23: =SUM(D12:D22)+D10+D6 -> 1258.7 | E23: =SUM(E12:E22)+E10+E6 -> 698.6 | F23: =SUM(F12:F22)+F10+F6 -> 786.9 | G23: =SUM(G12:G22)+G10+G6 -> 1077.8 | H23: =SUM(H12:H22)+H10+H6 -> 876.2 | I23: =SUM(I12:I22)+I10+I6 -> 758.5 | J23: =SUM(J12:J22)+J10+J6 -> 464.61592 | K23: =SUM(K12:K22)+K10+K6 -> 639.34621 | ... Q23: =SUM(Q12:Q22)+Q10+Q6 -> 542.01467
C25: Change in Cash: Investing
C26: Capital Expenditure | D26: -261.5 | E26: -217.3 | F26: -150.4 | G26: -263.8 | H26: -262.3 | I26: -196.7 | J26: =-IS!J68 -> -170.8446 | K26: =-IS!K68 -> -153.56644 | L26: =-IS!L68 -> -159.69338 | M26: =-IS!M68 -> -161.82974 | N26: =-IS!N68 -> -163.67816 | O26: =-IS!O68 -> -165.22867 | P26: =-IS!P68 -> -164.3956 | Q26: =-IS!Q68 -> -163.08177
C27: Sale of Property, Plant, and Equipment | D27: 7 | E27: 513.4 | F27: 132.8 | G27: 68.1 | H27: 0.7 | I27: 0 | J27: 0 | K27: 0 | L27: 0 | M27: 0 | N27: 0 | O27: 0 | P27: 0 | Q27: 0
C28: Cash Acquisitions | D28: 0 | E28: 0 | F28: 0 | G28: -126.8 | H28: 0 | I28: -8.1 | J28: 0 | K28: 0 | L28: 0 | M28: 0 | N28: 0 | O28: 0 | P28: 0 | Q28: 0
C29: Divestitures | D29: 0 | E29: 0 | F29: 0 | G29: 0 | H29: 0 | I29: 0 | J29: =+'Forecast Assumptions'!D88 -> 347 | K29: =+'Forecast Assumptions'!E88 -> 40 | L29: =+'Forecast Assumptions'!F88 -> 0 | M29: =+'Forecast Assumptions'!G88 -> 8 | N29: =+'Forecast Assumptions'!H88 -> 8 | O29: =+'Forecast Assumptions'!I88 -> 8 | P29: =+'Forecast Assumptions'!J88 -> 8 | Q29: =+'Forecast Assumptions'!K88 -> 8
C30: Sale (Purchase) of Intangible assets | D30: -259.4 | E30: -213.6 | F30: -86.1 | G30: -42.6 | H30: -30.2 | I30: -27.8 | J30: 0 | K30: 0 | L30: 0 | M30: 0 | N30: 0 | O30: 0 | P30: 0 | Q30: 0
C31: Invest. in Marketable & Equity Securt. | D31: 0 | E31: 0 | F31: 0 | G31: 0 | H31: 0 | I31: 0 | J31: 0 | K31: 0 | L31: 0 | M31: 0 | N31: 0 | O31: 0 | P31: 0 | Q31: 0
C32: Net (Inc.) Dec. in Loans Originated/Sold | D32: 0 | E32: 0 | F32: 0 | G32: 0 | H32: 0 | I32: 0 | J32: 0 | K32: 0 | L32: 0 | M32: 0 | N32: 0 | O32: 0 | P32: 0 | Q32: 0
C33: Other Investing Activities | D33: 1.9 | E33: 1.8 | F33: 2 | G33: 8.9 | H33: 23.3 | I33: 19.5
C34: Cash from Investing | D34: =SUM(D26:D33) -> -512 | E34: =SUM(E26:E33) -> 84.3 | F34: =SUM(F26:F33) -> -101.7 | G34: =SUM(G26:G33) -> -356.2 | H34: =SUM(H26:H33) -> -268.5 | I34: =SUM(I26:I33) -> -213.1 | J34: =SUM(J26:J33) -> 176.1554 | K34: =SUM(K26:K33) -> -113.56644 | ... Q34: =SUM(Q26:Q33) -> -155.08177
C36: Change in Cash: Financing
C37: Net Debt Issued/Repaid | D37: -317.1 | E37: -73.2 | F37: -735.8 | G37: -303.8 | H37: -497.5 | I37: -269 | J37: =BS!J32-BS!I32+BS!J38-BS!I38 -> -603.65066 | K37: =BS!K32-BS!J32+BS!K38-BS!J38 -> -351.02934 | L37: =BS!L32-BS!K32+BS!L38-BS!K38 -> -127.64 | M37: =BS!M32-BS!L32+BS!M38-BS!L38 -> -127.64 | N37: =BS!N32-BS!M32+BS!N38-BS!M38 -> -127.64 | O37: =BS!O32-BS!N32+BS!O38-BS!N38 -> -127.64 | P37: =BS!P32-BS!O32+BS!P38-BS!O38 -> -127.64 | Q37: =BS!Q32-BS!P32+BS!Q38-BS!P38 -> -382.92
C38: Short-term Borrowings | D38: 0 | E38: =BS!E31-BS!D31 -> 0 | F38: =BS!F31-BS!E31 -> 0 | G38: =BS!G31-BS!F31 -> 0 | H38: =BS!H31-BS!G31 -> 0 | I38: =BS!I31-BS!H31 -> 0 | J38: =BS!J31-BS!I31 -> 0 | K38: =BS!K31-BS!J31 -> 0 | L38: =BS!L31-BS!K31 -> 0 | ... Q38: =BS!Q31-BS!P31 -> 0
C39: Common Dividends Paid | D39: -100.9 | E39: 0 | F39: 0 | G39: 0 | H39: 0 | I39: 0 | J39: =I39 -> 0 | K39: =J39 -> 0 | L39: =K39 -> 0 | M39: =L39 -> 0 | N39: =M39 -> 0 | O39: =N39 -> 0 | P39: =O39 -> 0 | Q39: =P39 -> 0
C40: Special Dividend Paid | D40: 0 | E40: 0 | F40: 0 | G40: 0 | H40: 0 | I40: 0 | J40: =I40 -> 0 | K40: =J40 -> 0 | L40: =K40 -> 0 | M40: =L40 -> 0 | N40: =M40 -> 0 | O40: =N40 -> 0 | P40: =O40 -> 0 | Q40: =P40 -> 0
C41: Other Financing Activities | D41: -215.4 | E41: -198.5 | F41: -291.5 | G41: -249 | H41: -245 | I41: -223.2 | J41: ='Debt Schedule'!J71-'Debt Schedule'!I71+'Debt Schedule'!J59-'Debt Schedule'!I59-'Debt Schedule'!J77 -> -203.6361 | K41: ='Debt Schedule'!K71-'Debt Schedule'!J71+'Debt Schedule'!K59-'Debt Schedule'!J59-'Debt Schedule'!K77 -> -188.70831 | L41: ='Debt Schedule'!L71-'Debt Schedule'!K71+'Debt Schedule'!L59-'Debt Schedule'!K59-'Debt Schedule'!L77 -> -173.78052 | M41: ='Debt Schedule'!M71-'Debt Schedule'!L71+'Debt Schedule'!M59-'Debt Schedule'!L59-'Debt Schedule'!M77 -> -158.85272 | N41: ='Debt Schedule'!N71-'Debt Schedule'!M71+'Debt Schedule'!N59-'Debt Schedule'!M59-'Debt Schedule'!N77 -> -143.92493 | O41: ='Debt Schedule'!O71-'Debt Schedule'!N71+'Debt Schedule'!O59-'Debt Schedule'!N59-'Debt Schedule'!O77 -> -128.99713 | P41: ='Debt Schedule'!P71-'Debt Schedule'!O71+'Debt Schedule'!P59-'Debt Schedule'!O59-'Debt Schedule'!P77 -> -114.06934 | Q41: ='Debt Schedule'!Q71-'Debt Schedule'!P71+'Debt Schedule'!Q59-'Debt Schedule'!P59-'Debt Schedule'!Q77 -> -99.141547
C42: Cash from Financing | D42: =D37+D39+D41+D38 -> -633.4 | E42: =E37+E39+E41+E38 -> -271.7 | F42: =F37+F39+F41+F38 -> -1027.3 | G42: =G37+G39+G41+G38 -> -552.8 | H42: =H37+H39+H41+H38 -> -742.5 | I42: =I37+I39+I41+I38 -> -492.2 | J42: =J37+J39+J41+J38 -> -807.28676 | K42: =K37+K39+K41+K38 -> -539.73765 | ... Q42: =Q37+Q39+Q41+Q38 -> -482.06155
C44: Foreign Exchange Rate Adj. | D44: -4.3 | E44: 5.4 | F44: 5.8 | G44: -1.6 | H44: -2.5 | I44: 2.9 | J44: 0 | K44: =J44 -> 0 | L44: =K44 -> 0 | M44: =L44 -> 0 | N44: =M44 -> 0 | O44: =N44 -> 0 | P44: =O44 -> 0 | Q44: =P44 -> 0
C45: Net Change in Cash | D45: =D23+D34+D42+D44 -> 109 | E45: =E23+E34+E42+E44 -> 516.6 | F45: =F23+F34+F42+F44 -> -336.3 | G45: =G23+G34+G42+G44 -> 167.2 | H45: =H23+H34+H42+H44 -> -137.3 | I45: =I23+I34+I42+I44 -> 56.1 | J45: =J23+J34+J42+J44 -> -166.51545 | K45: =K23+K34+K42+K44 -> -13.957884 | ... Q45: =Q23+Q34+Q42+Q44 -> -95.128652
C48: Capital IQ Change in Cash | D48: 109 | E48: 516.6 | F48: -336.3 | G48: 167.2 | H48: -137.3 | I48: 56.1
C49: Check | D49: =D45-D48 -> 2.9842795e-13 | E49: =E45-E48 -> 0 | F49: =F45-F48 -> 0 | G49: =G45-G48 -> 0 | H49: =H45-H48 -> 0 | I49: =I45-I48 -> 0
C50: Supplemental Items:
C51: Cash Interest Paid | D51: 215.4 | E51: 198.5 | F51: 234.9 | G51: 249 | H51: 240 | I51: 223.2
C52: Cash Taxes Paid | D52: 91 | E52: 107.5 | F52: 56.1 | G52: 229.3 | H52: 274.5 | I52: 360.3
C53: Levered Free Cash Flow | D53: 1383.3875 | E53: 213.1125 | F53: 500.4375 | G53: 908.1375 | H53: 817.975 | I53: 543.0625 | J53: =IS!J18*(1-IS!J37)+CFS!J7+CFS!J26-NWC!J17-IS!J23 -> 338.70715 | K53: =IS!K18*(1-IS!K37)+CFS!K7+CFS!K26-NWC!K17-IS!K23 -> 405.96817 | L53: =IS!L18*(1-IS!L37)+CFS!L7+CFS!L26-NWC!L17-IS!L23 -> 290.6186 | M53: =IS!M18*(1-IS!M37)+CFS!M7+CFS!M26-NWC!M17-IS!M23 -> 278.47659 | N53: =IS!N18*(1-IS!N37)+CFS!N7+CFS!N26-NWC!N17-IS!N23 -> 255.24891 | O53: =IS!O18*(1-IS!O37)+CFS!O7+CFS!O26-NWC!O17-IS!O23 -> 231.99049 | P53: =IS!P18*(1-IS!P37)+CFS!P7+CFS!P26-NWC!P17-IS!P23 -> 210.24008 | Q53: =IS!Q18*(1-IS!Q37)+CFS!Q7+CFS!Q26-NWC!Q17-IS!Q23 -> 170.74154
C54: Unlevered Free Cash Flow | D54: 1574.2 | E54: 400.8625 | F54: 706.3125 | G54: 1113.8875 | H54: 1016.475 | I54: 750.0625 | J54: =IS!J18*(1-IS!J37)+CFS!J7+CFS!J26-NWC!J17 -> 181.9347 | K54: =IS!K18*(1-IS!K37)+CFS!K7+CFS!K26-NWC!K17 -> 324.47505 | L54: =IS!L18*(1-IS!L37)+CFS!L7+CFS!L26-NWC!L17 -> 242.9886 | M54: =IS!M18*(1-IS!M37)+CFS!M7+CFS!M26-NWC!M17 -> 243.61059 | N54: =IS!N18*(1-IS!N37)+CFS!N7+CFS!N26-NWC!N17 -> 233.14691 | O54: =IS!O18*(1-IS!O37)+CFS!O7+CFS!O26-NWC!O17 -> 222.65249 | P54: =IS!P18*(1-IS!P37)+CFS!P7+CFS!P26-NWC!P17 -> 213.66608 | Q54: =IS!Q18*(1-IS!Q37)+CFS!Q7+CFS!Q26-NWC!Q17 -> 199.69554
C55: Change in Net Working Capital | D55: -964.4 | E55: 92.5 | F55: -137.7 | G55: -145.1 | H55: 19.7 | I55: 31.8 | J55: =NWC!J17 -> 115.66155 | K55: =NWC!K17 -> -81.001355 | L55: =NWC!L17 -> -2.2009898 | M55: =NWC!M17 -> -13.358095 | N55: =NWC!N17 -> -13.459308 | O55: =NWC!O17 -> -13.549602 | P55: =NWC!P17 -> -18.624776 | Q55: =NWC!Q17 -> -18.674973
C56: Net Debt Issued | D56: -317.1 | E56: -73.2 | F56: -735.8 | G56: -303.8 | H56: -497.5 | I56: -269
C57: Filing Date | D57: 44285 | E57: 44644 | F57: 45008 | G57: 45372 | H57: 45761 | I57: 45761
C58: Restatement Type | D58: NC | E58: NC | F58: NC | G58: NC | H58: NC | I58: O
C59: Calculation Type | D59: REP | E59: REP | F59: REP | G59: REP | H59: REP | I59: REP

Sheet NWC
D1: 2019 | E1: =D1+1 -> 2020 | F1: =E1+1 -> 2021 | G1: =F1+1 -> 2022 | H1: =G1+1 -> 2023 | I1: =H1+1 -> 2024 | J1: =I1+1 -> 2025 | K1: =J1+1 -> 2026 | L1: =K1+1 -> 2027 | ... N1: =M1+1 -> 2029 | O1: =+N1+1 -> 2030 | P1: =+O1+1 -> 2031 | Q1: =+P1+1 -> 2032
C2: Tullow Oil Net Working Capital
C4: Net Working Capital
C5: Net Working Capital:
C6: Accounts Receivable | D6: =BS!D9 -> 38.7 | E6: =BS!E9 -> 79 | F6: =BS!F9 -> 99.8 | G6: =BS!G9 -> 26.8 | H6: =BS!H9 -> 43.5 | I6: =BS!I9 -> 137.9 | J6: =BS!J9 -> 102.2179 | K6: =BS!K9 -> 83.439286 | ... Q6: =BS!Q9 -> 74.171107
C7: Other Receivables | D7: =BS!D10 -> 754.7 | E7: =BS!E10 -> 558.3 | F7: =BS!F10 -> 642.3 | G7: =BS!G10 -> 467.7 | H7: =BS!H10 -> 501.9 | I7: =BS!I10 -> 357.1 | J7: =BS!J10 -> 448.26347 | K7: =BS!K10 -> 384.39641 | ... Q7: =BS!Q10 -> 312.57772
C8: Inventory | D8: =BS!D13 -> 191.5 | E8: =BS!E13 -> 96.1 | F8: =BS!F13 -> 134.8 | G8: =BS!G13 -> 181.6 | H8: =BS!H13 -> 107.3 | I8: =BS!I13 -> 132.4 | J8: =BS!J13 -> 108.57666 | K8: =BS!K13 -> 94.429526 | ... Q8: =BS!Q13 -> 83.940585
C9: Prepaid Exp. | D9: =BS!D14 -> 69.5 | E9: =BS!E14 -> 60.7 | F9: =BS!F14 -> 49.6 | G9: =BS!G14 -> 31.3 | H9: =BS!H14 -> 21.1 | I9: =BS!I14 -> 17.1 | J9: =BS!J14 -> 31.503395 | K9: =BS!K14 -> 27.39862 | ... Q9: =BS!Q14 -> 24.355266
C10: Other Current Assets | D10: =BS!D15 -> 148.1 | E10: =BS!E15 -> 307.3 | F10: =BS!F15 -> 32.3 | G10: =BS!G15 -> 84.3 | H10: =BS!H15 -> 107.8 | I10: =BS!I15 -> 24.7 | J10: =BS!J15 -> 88.335898 | K10: =BS!K15 -> 76.82606 | ... Q10: =BS!Q15 -> 68.292457
C12: Accounts Payable | D12: =BS!D29 -> 95.4 | E12: =BS!E29 -> 38.3 | F12: =BS!F29 -> 60.2 | G12: =BS!G29 -> 68.4 | H12: =BS!H29 -> 22.3 | I12: =BS!I29 -> 75.7 | J12: =BS!J29 -> 46.260816 | K12: =BS!K29 -> 40.233204 | ... Q12: =BS!Q29 -> 35.764224
C13: Other Current Liabilities | D13: =BS!D35 -> 240.1 | E13: =BS!E35 -> 488.2 | F13: =BS!F35 -> 435.5 | G13: =BS!G35 -> 336.5 | H13: =BS!H35 -> 188.9 | I13: =BS!I35 -> 171.3 | J13: =BS!J35 -> 194.77495 | K13: =BS!K35 -> 169.3965 | ... Q13: =BS!Q35 -> 150.58046
C14: Total NWC | D14: =SUM(D6:D10)-SUM(D12:D13) -> 867 | E14: =SUM(E6:E10)-SUM(E12:E13) -> 574.9 | F14: =SUM(F6:F10)-SUM(F12:F13) -> 463.1 | G14: =SUM(G6:G10)-SUM(G12:G13) -> 386.8 | H14: =SUM(H6:H10)-SUM(H12:H13) -> 570.4 | I14: =SUM(I6:I10)-SUM(I12:I13) -> 422.2 | J14: =SUM(J6:J10)-SUM(J12:J13) -> 537.86155 | K14: =SUM(K6:K10)-SUM(K12:K13) -> 456.8602 | ... Q14: =SUM(Q6:Q10)-SUM(Q12:Q13) -> 376.99245
C15: NWC (% of Sales) | D15: =D14/IS!D5 -> 0.51527398 | E15: =E14/IS!E5 -> 0.41178999 | F15: =F14/IS!F5 -> 0.36027696 | G15: =G14/IS!G5 -> 0.21692558 | H15: =H14/IS!H5 -> 0.34906065 | I15: =I14/IS!I5 -> 0.27506678 | J15: =J14/IS!J5 -> 0.46944673 | K15: =K14/IS!K5 -> 0.45848783 | ... Q15: =Q14/IS!Q5 -> 0.42561112
C17: NWC Change | E17: =+E14-D14 -> -292.1 | F17: =+F14-E14 -> -111.8 | G17: =+G14-F14 -> -76.3 | H17: =+H14-G14 -> 183.6 | I17: =+I14-H14 -> -148.2 | J17: =+J14-I14 -> 115.66155 | K17: =+K14-J14 -> -81.001355 | L17: =+L14-K14 -> -2.2009898 | ... Q17: =+Q14-P14 -> -18.674973
C19: Account | D19: 2019 | E19: =D19+1 -> 2020 | F19: =E19+1 -> 2021 | G19: =F19+1 -> 2022 | H19: =G19+1 -> 2023 | I19: =H19+1 -> 2024 | J19: =I19+1 -> 2025 | K19: =J19+1 -> 2026 | L19: =K19+1 -> 2027 | ... Q19: =P19+1 -> 2032 | S19: 2025 Step | T19: Fwd. Step
C20: Days Sales Outstanding | D20: =(D6/IS!D5)*365 -> 8.3950434 | E20: =(E6/IS!E5)*365 -> 20.653965 | F20: =(F6/IS!F5)*365 -> 28.339038 | G20: =(G6/IS!G5)*365 -> 5.4859514 | H20: =(H6/IS!H5)*365 -> 9.7163576 | I20: =(I6/IS!I5)*365 -> 32.79269 | J20: =AVERAGE(D20:I20)+S20 -> 32.563841 | K20: =J20-T20 -> 30.563841 | L20: =K20 -> 30.563841 | M20: =L20 -> 30.563841 | N20: =M20 -> 30.563841 | O20: =N20 -> 30.563841 | P20: =O20 -> 30.563841 | Q20: =P20 -> 30.563841 | S20: 15 | T20: 2
C22: Days Other Sales Outstanding | D22: =D7/IS!D5*365 -> 163.71419 | E22: =E7/IS!E5*365 -> 145.9634 | F22: =F7/IS!F5*365 -> 182.38642 | G22: =G7/IS!G5*365 -> 95.73804 | H22: =H7/IS!H5*365 -> 112.10666 | I22: =I7/IS!I5*365 -> 84.918561 | J22: =AVERAGE(D22:I22)+S22 -> 142.80455 | K22: =J22-$T$22 -> 140.80455 | L22: =K22-$T$22 -> 138.80455 | M22: =L22-$T$22 -> 136.80455 | N22: =M22-$T$22 -> 134.80455 | O22: =N22-$T$22 -> 132.80455 | P22: =O22-$T$22 -> 130.80455 | Q22: =P22-$T$22 -> 128.80455 | S22: 12 | T22: 2
C24: Days Inventory Outstanding | D24: =-D8/IS!D8*365 -> 71.992481 | E24: =-E8/IS!E8*365 -> 35.302436 | F24: =-F8/IS!F8*365 -> 77.974643 | G24: =-G8/IS!G8*365 -> 97.076743 | H24: =-H8/IS!H8*365 -> 46.441954 | I24: =-I8/IS!I8*365 -> 62.549832 | J24: =AVERAGE(D24:I24) -> 65.223015 | K24: =J24 -> 65.223015 | L24: =K24 -> 65.223015 | M24: =L24 -> 65.223015 | N24: =M24 -> 65.223015 | O24: =N24 -> 65.223015 | P24: =O24 -> 65.223015 | Q24: =P24 -> 65.223015
C26: =C9 -> Prepaid Exp. | D26: =D9 -> 69.5 | E26: =E9 -> 60.7 | F26: =F9 -> 49.6 | G26: =G9 -> 31.3 | H26: =H9 -> 21.1 | I26: =I9 -> 17.1 | J26: =IS!J5*J27 -> 31.503395 | K26: =IS!K5*K27 -> 27.39862 | L26: =IS!L5*L27 -> 27.596432 | M26: =IS!M5*M27 -> 27.113594 | N26: =IS!N5*N27 -> 26.61249 | O26: =IS!O5*O27 -> 26.093121 | P26: =IS!P5*P27 -> 25.236839 | Q26: =IS!Q5*Q27 -> 24.355266
C27: (% of Revenue) | D27: =D26/IS!D5 -> 0.041305123 | E27: =E26/IS!E5 -> 0.043478261 | F27: =F26/IS!F5 -> 0.03858721 | G27: =G26/IS!G5 -> 0.017553699 | H27: =H26/IS!H5 -> 0.012912306 | I27: =I26/IS!I5 -> 0.011140791 | J27: =AVERAGE(D27:I27) -> 0.027496232 | K27: =J27 -> 0.027496232 | L27: =K27 -> 0.027496232 | M27: =L27 -> 0.027496232 | N27: =M27 -> 0.027496232 | O27: =N27 -> 0.027496232 | P27: =O27 -> 0.027496232 | Q27: =P27 -> 0.027496232
C29: =C10 -> Other Current Assets | D29: =D10 -> 148.1 | E29: =E10 -> 307.3 | F29: =F10 -> 32.3 | G29: =G10 -> 84.3 | H29: =H10 -> 107.8 | I29: =I10 -> 24.7 | J29: =IS!J5*J30 -> 88.335898 | K29: =IS!K5*K30 -> 76.82606 | L29: =IS!L5*L30 -> 77.380727 | M29: =IS!M5*M30 -> 76.026843 | N29: =IS!N5*N30 -> 74.621743 | O29: =IS!O5*O30 -> 73.165424 | P29: =IS!P5*P30 -> 70.764399 | Q29: =IS!Q5*Q30 -> 68.292457
C30: (% of Revenue) | D30: =D29/IS!D5 -> 0.088018543 | E30: =E29/IS!E5 -> 0.22011317 | F30: =F29/IS!F5 -> 0.025128365 | G30: =G29/IS!G5 -> 0.047277214 | H30: =H29/IS!H5 -> 0.065969035 | I30: =I29/IS!I5 -> 0.016092254 | J30: =AVERAGE(D30:I30) -> 0.077099764 | K30: =J30 -> 0.077099764 | L30: =K30 -> 0.077099764 | M30: =L30 -> 0.077099764 | N30: =M30 -> 0.077099764 | O30: =N30 -> 0.077099764 | P30: =O30 -> 0.077099764 | Q30: =P30 -> 0.077099764
C32: Days Payable Outstanding | D32: =-D12/IS!D8*365 -> 35.864662 | E32: =-E12/IS!E8*365 -> 14.069545 | F32: =-F12/IS!F8*365 -> 34.822504 | G32: =-G12/IS!G8*365 -> 36.564148 | H32: =-H12/IS!H8*365 -> 9.6519625 | I32: =-I12/IS!I8*365 -> 35.763008 | J32: =AVERAGE(D32:I32) -> 27.789305 | K32: =J32 -> 27.789305 | L32: =K32 -> 27.789305 | M32: =L32 -> 27.789305 | N32: =M32 -> 27.789305 | O32: =N32 -> 27.789305 | P32: =O32 -> 27.789305 | Q32: =P32 -> 27.789305
C34: Other Current Liabilities | D34: =D13 -> 240.1 | E34: =E13 -> 488.2 | F34: =F13 -> 435.5 | G34: =G13 -> 336.5 | H34: =H13 -> 188.9 | I34: =I13 -> 171.3 | J34: =IS!J5*J35 -> 238.1425 | K34: =IS!K5*K35 -> 207.11342 | L34: =IS!L5*L35 -> 208.60873 | M34: =IS!M5*M35 -> 204.95883 | N34: =IS!N5*N35 -> 201.17085 | O34: =IS!O5*O35 -> 197.2448 | P34: =IS!P5*P35 -> 190.77194 | Q34: =IS!Q5*Q35 -> 184.1079
C35: (% of Revenue) | D35: =D34/IS!D5 -> 0.14269583 | E35: =E34/IS!E5 -> 0.34968842 | F35: =F34/IS!F5 -> 0.33880504 | G35: =G34/IS!G5 -> 0.18871628 | H35: =H34/IS!H5 -> 0.1155988 | I35: =I34/IS!I5 -> 0.11160336 | J35: =AVERAGE(D35:I35) -> 0.20785129 | K35: =J35 -> 0.20785129 | L35: =K35 -> 0.20785129 | M35: =L35 -> 0.20785129 | N35: =M35 -> 0.20785129 | O35: =N35 -> 0.20785129 | P35: =O35 -> 0.20785129 | Q35: =P35 -> 0.20785129

Sheet Debt Schedule
I1: 2024 | J1: =I1+1 -> 2025 | K1: =J1+1 -> 2026 | L1: =K1+1 -> 2027 | M1: =L1+1 -> 2028 | N1: =M1+1 -> 2029 | O1: =N1+1 -> 2030 | P1: =O1+1 -> 2031 | Q1: =P1+1 -> 2032
C2: Tullow Oil Debt Schedule
U3: TRUE | V3: FALSE
C4: Debt Schedule | S4: Refinance SD to 2032 | U4: Need Capital
C5: Beginning cash | J5: =BS!I6 -> 555.1 | K5: =BS!J6 -> 388.58455 | L5: =BS!K6 -> 374.62667 | M5: =BS!L6 -> 526.2095 | N5: =BS!M6 -> 824.84174 | O5: =BS!N6 -> 1080.7474 | P5: =BS!O6 -> 1306.872 | Q5: =BS!P6 -> 1479.0295 | S5: TRUE | U5: =IF(SUM(J22:Q22)>0,"Yes","No") -> No
C6: Add: CF from operations | J6: =CFS!J23 -> 464.61592 | K6: =CFS!K23 -> 639.34621 | L6: =CFS!L23 -> 612.69672 | M6: =CFS!M23 -> 738.95471 | N6: =CFS!N23 -> 683.14873 | O6: =CFS!O23 -> 639.99046 | P6: =CFS!P23 -> 570.26241 | Q6: =CFS!Q23 -> 542.01467
C7: Add: CF from investing | J7: =CFS!J34 -> 176.1554 | K7: =CFS!K34 -> -113.56644 | L7: =CFS!L34 -> -159.69338 | M7: =CFS!M34 -> -153.82974 | N7: =CFS!N34 -> -155.67816 | O7: =CFS!O34 -> -157.22867 | P7: =CFS!P34 -> -156.3956 | Q7: =CFS!Q34 -> -155.08177
C8: Less: Mandatory repayments | J8: =J48+J28+J38 -> -655.23 | K8: =K48+K28+K38 -> -165.83 | L8: =L48+L28+L38 -> -127.64 | M8: =M48+M28+M38 -> -127.64 | N8: =N48+N28+N38 -> -127.64 | O8: =O48+O28+O38 -> -127.64 | P8: =P48+P28+P38 -> -127.64 | Q8: =Q48+Q28+Q38 -> -382.92
C9: Less: Minimum Cash Balance | J9: =-'Forecast Assumptions'!$D$7 -> -300 | K9: =-'Forecast Assumptions'!$D$7 -> -300 | L9: =-'Forecast Assumptions'!$D$7 -> -300 | M9: =-'Forecast Assumptions'!$D$7 -> -300 | N9: =-'Forecast Assumptions'!$D$7 -> -300 | O9: =-'Forecast Assumptions'!$D$7 -> -300 | P9: =-'Forecast Assumptions'!$D$7 -> -300 | Q9: =-'Forecast Assumptions'!$D$7 -> -300
C10: Cash Available for optional Repayment of Debt (CARD) | J10: =SUM(J5:J9) -> 240.64131 | K10: =SUM(K5:K9) -> 448.53432 | L10: =SUM(L5:L9) -> 399.99001 | M10: =SUM(M5:M9) -> 683.69447 | N10: =SUM(N5:N9) -> 924.67231 | O10: =SUM(O5:O9) -> 1135.8692 | P10: =SUM(P5:P9) -> 1293.0989 | Q10: =SUM(Q5:Q9) -> 1183.0424
C12: CARD for revolver | J12: =J10 -> 240.64131 | K12: =K10 -> 448.53432 | L12: =L10 -> 399.99001 | M12: =M10 -> 683.69447 | N12: =N10 -> 924.67231 | O12: =O10 -> 1135.8692 | P12: =P10 -> 1293.0989 | Q12: =Q10 -> 1183.0424
C14: Revolver
C15: Beginning balance | J15: =I18 -> 150 | K15: 0 | L15: =K15 -> 0 | M15: =L15 -> 0 | N15: =M15 -> 0 | O15: =N15 -> 0 | P15: =O15 -> 0 | Q15: =P15 -> 0
C16: Mandatory repayments | J16: =IF(J1='Maturity Schedule'!$I$8,-'Debt Schedule'!J15,-MIN('Debt Schedule'!J15,'Maturity Schedule'!J8*'Maturity Schedule'!E8)) -> -150 | K16: 0 | L16: =K16 -> 0 | M16: =L16 -> 0 | N16: =M16 -> 0 | O16: =N16 -> 0 | P16: =O16 -> 0 | Q16: =P16 -> 0
C17: Optional draw (repayment) | J17: =IF(J12>0,-MIN(J15+J16,J12*'Maturity Schedule'!$K$8),-'Debt Schedule'!J12) -> 0 | K17: 0 | L17: =K17 -> 0 | M17: =L17 -> 0 | N17: =M17 -> 0 | O17: =N17 -> 0 | P17: =O17 -> 0 | Q17: =P17 -> 0
C18: Ending balance | I18: ='Maturity Schedule'!E8 -> 150 | J18: =SUM(J15:J17) -> 0 | K18: 0 | L18: =K18 -> 0 | M18: =L18 -> 0 | N18: =M18 -> 0 | O18: =N18 -> 0 | P18: =O18 -> 0 | Q18: =P18 -> 0
C19: Cash interest rate | J19: ='Maturity Schedule'!$G$7 -> 0.1 | K19: 0 | L19: =K19 -> 0 | M19: =L19 -> 0 | N19: =M19 -> 0 | O19: =N19 -> 0 | P19: =O19 -> 0 | Q19: =P19 -> 0
C20: Cash interest paid | J20: =J19*AVERAGE(I18:J18) -> 7.5 | K20: 0 | L20: =K20 -> 0 | M20: =L20 -> 0 | N20: =M20 -> 0 | O20: =N20 -> 0 | P20: =O20 -> 0 | Q20: =P20 -> 0
C22: Amount that Needs to be Refinanced | J22: =IF($S$5=TRUE," ",IF(J12>=0,0,-J12)) | K22: =IF($S$5=TRUE," ",IF(K12>=0,0,-K12)) | L22: =IF($S$5=TRUE," ",IF(L12>=0,0,-L12)) | M22: =IF($S$5=TRUE," ",IF(M12>=0,0,-M12)) | N22: =IF($S$5=TRUE," ",IF(N12>=0,0,-N12)) | O22: =IF($S$5=TRUE," ",IF(O12>=0,0,-O12)) | P22: =IF($S$5=TRUE," ",IF(P12>=0,0,-P12)) | Q22: =IF($S$5=TRUE," ",IF(Q12>=0,0,-Q12))
C24: CARD for Secured Notes | J24: =IF(J12>0,J12+J17,0) -> 240.64131 | K24: =IF(K12>0,K12+K17,0) -> 448.53432 | L24: =IF(L12>0,L12+L17,0) -> 399.99001 | M24: =IF(M12>0,M12+M17,0) -> 683.69447 | N24: =IF(N12>0,N12+N17,0) -> 924.67231 | O24: =IF(O12>0,O12+O17,0) -> 1135.8692 | P24: =IF(P12>0,P12+P17,0) -> 1293.0989 | Q24: =IF(Q12>0,Q12+Q17,0) -> 1183.0424
C26: Secured Notes
C27: Beginning balance | J27: =I30 -> 381.9 | K27: =J30 -> 223.38934 | L27: =K30 -> 0 | M27: =L30 -> 0 | N27: =M30 -> 0 | O27: =N30 -> 0 | P27: =O30 -> 0 | Q27: =P30 -> 0
C28: Mandatory repayments | J28: =IF(J1='Maturity Schedule'!$I$10,-'Debt Schedule'!J27,-MIN('Debt Schedule'!J27,'Maturity Schedule'!$J$10*'Maturity Schedule'!$E$10)) -> -38.19 | K28: =IF(K1='Maturity Schedule'!$I$10,-'Debt Schedule'!K27,-MIN('Debt Schedule'!K27,'Maturity Schedule'!$J$10*'Maturity Schedule'!$E$10)) -> -38.19 | L28: =IF(L1='Maturity Schedule'!$I$10,-'Debt Schedule'!L27,-MIN('Debt Schedule'!L27,'Maturity Schedule'!$J$10*'Maturity Schedule'!$E$10)) -> 0 | M28: =IF(M1='Maturity Schedule'!$I$10,-'Debt Schedule'!M27,-MIN('Debt Schedule'!M27,'Maturity Schedule'!$J$10*'Maturity Schedule'!$E$10)) -> 0 | N28: =IF(N1='Maturity Schedule'!$I$10,-'Debt Schedule'!N27,-MIN('Debt Schedule'!N27,'Maturity Schedule'!$J$10*'Maturity Schedule'!$E$10)) -> 0 | O28: =IF(O1='Maturity Schedule'!$I$10,-'Debt Schedule'!O27,-MIN('Debt Schedule'!O27,'Maturity Schedule'!$J$10*'Maturity Schedule'!$E$10)) -> 0 | P28: =IF(P1='Maturity Schedule'!$I$10,-'Debt Schedule'!P27,-MIN('Debt Schedule'!P27,'Maturity Schedule'!$J$10*'Maturity Schedule'!$E$10)) -> 0 | Q28: =IF(Q1='Maturity Schedule'!$I$10,-'Debt Schedule'!Q27,-MIN('Debt Schedule'!Q27,'Maturity Schedule'!$J$10*'Maturity Schedule'!$E$10)) -> 0
C29: Optional draw (repayment) | J29: =IF(J24>0,-MIN(J27+J28,J24*'Maturity Schedule'!$K$10),-J24) -> -120.32066 | K29: =IF(K24>0,-MIN(K27+K28,K24*'Maturity Schedule'!$K$10),-K24) -> -185.19934 | L29: =IF(L24>0,-MIN(L27+L28,L24*'Maturity Schedule'!$K$10),-L24) -> 0 | M29: =IF(M24>0,-MIN(M27+M28,M24*'Maturity Schedule'!$K$10),-M24) -> 0 | N29: =IF(N24>0,-MIN(N27+N28,N24*'Maturity Schedule'!$K$10),-N24) -> 0 | O29: =IF(O24>0,-MIN(O27+O28,O24*'Maturity Schedule'!$K$10),-O24) -> 0 | P29: =IF(P24>0,-MIN(P27+P28,P24*'Maturity Schedule'!$K$10),-P24) -> 0 | Q29: =IF(Q24>0,-MIN(Q27+Q28,Q24*'Maturity Schedule'!$K$10),-Q24) -> 0
C30: Ending balance | I30: ='Maturity Schedule'!E10 -> 381.9 | J30: =SUM(J27:J29) -> 223.38934 | K30: =SUM(K27:K29) -> 0 | L30: =SUM(L27:L29) -> 0 | M30: =SUM(M27:M29) -> 0 | N30: =SUM(N27:N29) -> 0 | O30: =SUM(O27:O29) -> 0 | P30: =SUM(P27:P29) -> 0 | Q30: =SUM(Q27:Q29) -> 0
C31: Cash interest rate | J31: ='Maturity Schedule'!$G$10+'Maturity Schedule'!Q6 -> 0.1949 | K31: ='Maturity Schedule'!$G$10+'Maturity Schedule'!R6 -> 0.1889 | L31: ='Maturity Schedule'!$G$10+'Maturity Schedule'!S6 -> 0.1901 | M31: ='Maturity Schedule'!$G$10+'Maturity Schedule'!T6 -> 0.1915 | N31: ='Maturity Schedule'!$G$10+'Maturity Schedule'!U6 -> 0.1929 | O31: ='Maturity Schedule'!$G$10+'Maturity Schedule'!V6 -> 0.1946 | P31: ='Maturity Schedule'!$G$10+'Maturity Schedule'!W6 -> 0.1961 | Q31: ='Maturity Schedule'!$G$10+'Maturity Schedule'!X6 -> 0.1974
C32: Cash interest paid | J32: =J31*AVERAGE(I30:J30) -> 58.985447 | K32: =K31*AVERAGE(J30:K30) -> 21.099124 | L32: =L31*AVERAGE(K30:L30) -> 0 | M32: =M31*AVERAGE(L30:M30) -> 0 | N32: =N31*AVERAGE(M30:N30) -> 0 | O32: =O31*AVERAGE(N30:O30) -> 0 | P32: =P31*AVERAGE(O30:P30) -> 0 | Q32: =Q31*AVERAGE(P30:Q30) -> 0
C34: CARD for Senior Notes | J34: =IF(J24>0,J24+J29,0) -> 120.32066 | K34: =IF(K24>0,K24+K29,0) -> 263.33498 | L34: =IF(L24>0,L24+L29,0) -> 399.99001 | M34: =IF(M24>0,M24+M29,0) -> 683.69447 | N34: =IF(N24>0,N24+N29,0) -> 924.67231 | O34: =IF(O24>0,O24+O29,0) -> 1135.8692 | P34: =IF(P24>0,P24+P29,0) -> 1293.0989 | Q34: =IF(Q24>0,Q24+Q29,0) -> 1183.0424
C36: Senior Notes
C37: Beginning balance | J37: =I40 -> 489.4 | K37: =J40 -> 0 | L37: =K40 -> 0 | M37: =L40 -> 0 | N37: =M40 -> 0 | O37: =N40 -> 0 | P37: =O40 -> 0 | Q37: =P40 -> 0
C38: Mandatory repayments | J38: =IF(J1='Maturity Schedule'!$I$9,-'Debt Schedule'!J37,-MIN('Debt Schedule'!J37,'Maturity Schedule'!J9*'Maturity Schedule'!E9)) -> -489.4 | K38: =IF(K1='Maturity Schedule'!$I$9,-'Debt Schedule'!K37,-MIN('Debt Schedule'!K37,'Maturity Schedule'!K9*'Maturity Schedule'!F9)) -> 0 | L38: =IF(L1='Maturity Schedule'!$I$9,-'Debt Schedule'!L37,-MIN('Debt Schedule'!L37,'Maturity Schedule'!L9*'Maturity Schedule'!G9)) -> 0 | M38: =IF(M1='Maturity Schedule'!$I$9,-'Debt Schedule'!M37,-MIN('Debt Schedule'!M37,'Maturity Schedule'!M9*'Maturity Schedule'!H9)) -> 0 | N38: =IF(N1='Maturity Schedule'!$I$9,-'Debt Schedule'!N37,-MIN('Debt Schedule'!N37,'Maturity Schedule'!N9*'Maturity Schedule'!I9)) -> 0 | O38: =IF(O1='Maturity Schedule'!$I$9,-'Debt Schedule'!O37,-MIN('Debt Schedule'!O37,'Maturity Schedule'!O9*'Maturity Schedule'!J9)) -> 0 | P38: =IF(P1='Maturity Schedule'!$I$9,-'Debt Schedule'!P37,-MIN('Debt Schedule'!P37,'Maturity Schedule'!P9*'Maturity Schedule'!K9)) -> 0 | Q38: =IF(Q1='Maturity Schedule'!$I$9,-'Debt Schedule'!Q37,-MIN('Debt Schedule'!Q37,'Maturity Schedule'!Q9*'Maturity Schedule'!L9)) -> 0
C39: Optional draw (repayment) | J39: =IF(J34>0,-MIN(J37+J38,J34*'Maturity Schedule'!$K$9),-'Debt Schedule'!J34) -> 0 | K39: =IF(K34>0,-MIN(K37+K38,K34*'Maturity Schedule'!$K$9),-'Debt Schedule'!K34) -> 0 | L39: =IF(L34>0,-MIN(L37+L38,L34*'Maturity Schedule'!$K$9),-'Debt Schedule'!L34) -> 0 | M39: =IF(M34>0,-MIN(M37+M38,M34*'Maturity Schedule'!$K$9),-'Debt Schedule'!M34) -> 0 | N39: =IF(N34>0,-MIN(N37+N38,N34*'Maturity Schedule'!$K$9),-'Debt Schedule'!N34) -> 0 | O39: =IF(O34>0,-MIN(O37+O38,O34*'Maturity Schedule'!$K$9),-'Debt Schedule'!O34) -> 0 | P39: =IF(P34>0,-MIN(P37+P38,P34*'Maturity Schedule'!$K$9),-'Debt Schedule'!P34) -> 0 | Q39: =IF(Q34>0,-MIN(Q37+Q38,Q34*'Maturity Schedule'!$K$9),-'Debt Schedule'!Q34) -> 0
C40: Ending balance | I40: ='Maturity Schedule'!E9 -> 489.4 | J40: =SUM(J37:J39) -> 0 | K40: =SUM(K37:K39) -> 0 | L40: =SUM(L37:L39) -> 0 | M40: =SUM(M37:M39) -> 0 | N40: =SUM(N37:N39) -> 0 | O40: =SUM(O37:O39) -> 0 | P40: =SUM(P37:P39) -> 0 | Q40: =SUM(Q37:Q39) -> 0
C41: Cash interest rate | J41: ='Maturity Schedule'!$G$9 -> 0.07 | K41: ='Maturity Schedule'!$G$9 -> 0.07 | L41: ='Maturity Schedule'!$G$9 -> 0.07 | M41: ='Maturity Schedule'!$G$9 -> 0.07 | N41: ='Maturity Schedule'!$G$9 -> 0.07 | O41: ='Maturity Schedule'!$G$9 -> 0.07 | P41: ='Maturity Schedule'!$G$9 -> 0.07 | Q41: ='Maturity Schedule'!$G$9 -> 0.07
C42: Cash interest paid | J42: =J41*AVERAGE(I40:J40) -> 17.129 | K42: =K41*AVERAGE(J40:K40) -> 0 | L42: =L41*AVERAGE(K40:L40) -> 0 | M42: =M41*AVERAGE(L40:M40) -> 0 | N42: =N41*AVERAGE(M40:N40) -> 0 | O42: =O41*AVERAGE(N40:O40) -> 0 | P42: =P41*AVERAGE(O40:P40) -> 0 | Q42: =Q41*AVERAGE(P40:Q40) -> 0
C44: CARD for Senior Notes | J44: =IF(J34>0,J34+J39,0) -> 120.32066 | K44: =IF(K34>0,K34+K39,0) -> 263.33498 | L44: =IF(L34>0,L34+L39,0) -> 399.99001 | M44: =IF(M34>0,M34+M39,0) -> 683.69447 | N44: =IF(N34>0,N34+N39,0) -> 924.67231 | O44: =IF(O34>0,O34+O39,0) -> 1135.8692 | P44: =IF(P34>0,P34+P39,0) -> 1293.0989 | Q44: =IF(Q34>0,Q34+Q39,0) -> 1183.0424
C46: Senior Notes
C47: Beginning balance | J47: =I50 -> 1276.4 | K47: =J50 -> 1148.76 | L47: =K50 -> 1021.12 | M47: =L50 -> 893.48 | N47: =M50 -> 765.84 | O47: =N50 -> 638.2 | P47: =O50 -> 510.56 | Q47: =P50 -> 382.92
C48: Mandatory repayments | J48: =IF(J1='Maturity Schedule'!$I$11,-'Debt Schedule'!J47,-MIN('Debt Schedule'!J47,'Maturity Schedule'!$J$11*'Maturity Schedule'!$E$11)) -> -127.64 | K48: =IF(K1='Maturity Schedule'!$I$11,-'Debt Schedule'!K47,-MIN('Debt Schedule'!K47,'Maturity Schedule'!$J$11*'Maturity Schedule'!$E$11)) -> -127.64 | L48: =IF(L1='Maturity Schedule'!$I$11,-'Debt Schedule'!L47,-MIN('Debt Schedule'!L47,'Maturity Schedule'!$J$11*'Maturity Schedule'!$E$11)) -> -127.64 | M48: =IF(M1='Maturity Schedule'!$I$11,-'Debt Schedule'!M47,-MIN('Debt Schedule'!M47,'Maturity Schedule'!$J$11*'Maturity Schedule'!$E$11)) -> -127.64 | N48: =IF(N1='Maturity Schedule'!$I$11,-'Debt Schedule'!N47,-MIN('Debt Schedule'!N47,'Maturity Schedule'!$J$11*'Maturity Schedule'!$E$11)) -> -127.64 | O48: =IF(O1='Maturity Schedule'!$I$11,-'Debt Schedule'!O47,-MIN('Debt Schedule'!O47,'Maturity Schedule'!$J$11*'Maturity Schedule'!$E$11)) -> -127.64 | P48: =IF(P1='Maturity Schedule'!$I$11,-'Debt Schedule'!P47,-MIN('Debt Schedule'!P47,'Maturity Schedule'!$J$11*'Maturity Schedule'!$E$11)) -> -127.64 | Q48: =IF(Q1='Maturity Schedule'!$I$11,-'Debt Schedule'!Q47,-MIN('Debt Schedule'!Q47,'Maturity Schedule'!$J$11*'Maturity Schedule'!$E$11)) -> -382.92
C49: Optional draw (repayment) | J49: =IF(J44>0,-MIN(J47+J48,J44*'Maturity Schedule'!$K$11),-'Debt Schedule'!J44) -> 0 | K49: =IF(K44>0,-MIN(K47+K48,K44*'Maturity Schedule'!$K$11),-'Debt Schedule'!K44) -> 0 | L49: =IF(L44>0,-MIN(L47+L48,L44*'Maturity Schedule'!$K$11),-'Debt Schedule'!L44) -> 0 | M49: =IF(M44>0,-MIN(M47+M48,M44*'Maturity Schedule'!$K$11),-'Debt Schedule'!M44) -> 0 | N49: =IF(N44>0,-MIN(N47+N48,N44*'Maturity Schedule'!$K$11),-'Debt Schedule'!N44) -> 0 | O49: =IF(O44>0,-MIN(O47+O48,O44*'Maturity Schedule'!$K$11),-'Debt Schedule'!O44) -> 0 | P49: =IF(P44>0,-MIN(P47+P48,P44*'Maturity Schedule'!$K$11),-'Debt Schedule'!P44) -> 0 | Q49: =IF(Q44>0,-MIN(Q47+Q48,Q44*'Maturity Schedule'!$K$11),-'Debt Schedule'!Q44) -> 0
C50: Ending balance | I50: ='Maturity Schedule'!E11 -> 1276.4 | J50: =SUM(J47:J49) -> 1148.76 | K50: =SUM(K47:K49) -> 1021.12 | L50: =SUM(L47:L49) -> 893.48 | M50: =SUM(M47:M49) -> 765.84 | N50: =SUM(N47:N49) -> 638.2 | O50: =SUM(O47:O49) -> 510.56 | P50: =SUM(P47:P49) -> 382.92 | Q50: =SUM(Q47:Q49) -> 0
C51: Cash interest rate | J51: ='Maturity Schedule'!$G$7 -> 0.1 | K51: ='Maturity Schedule'!$G$7 -> 0.1 | L51: ='Maturity Schedule'!$G$7 -> 0.1 | M51: ='Maturity Schedule'!$G$7 -> 0.1 | N51: ='Maturity Schedule'!$G$7 -> 0.1 | O51: ='Maturity Schedule'!$G$7 -> 0.1 | P51: ='Maturity Schedule'!$G$7 -> 0.1 | Q51: ='Maturity Schedule'!$G$7 -> 0.1
C52: Cash interest paid | J52: =J51*AVERAGE(I50:J50) -> 121.258 | K52: =K51*AVERAGE(J50:K50) -> 108.494 | L52: =L51*AVERAGE(K50:L50) -> 95.73 | M52: =M51*AVERAGE(L50:M50) -> 82.966 | N52: =N51*AVERAGE(M50:N50) -> 70.202 | O52: =O51*AVERAGE(N50:O50) -> 57.438 | P52: =P51*AVERAGE(O50:P50) -> 44.674 | Q52: =Q51*AVERAGE(P50:Q50) -> 19.146
C54: Total Debt Cash Interest | J54: =J52+J32+J20+J42 -> 204.87245 | K54: =K52+K32+K20+K42 -> 129.59312 | L54: =L52+L32+L20+L42 -> 95.73 | M54: =M52+M32+M20+M42 -> 82.966 | N54: =N52+N32+N20+N42 -> 70.202 | O54: =O52+O32+O20+O42 -> 57.438 | P54: =P52+P32+P20+P42 -> 44.674 | Q54: =Q52+Q32+Q20+Q42 -> 19.146
C56: Short-Term Lease Liabilities
C57: Beginning balance | J57: =I59 -> 151.9 | K57: =J59 -> 132.95654 | L57: =K59 -> 114.01309 | M57: =L59 -> 95.069628 | N57: =M59 -> 76.12617 | O57: =N59 -> 57.182713 | P57: =O59 -> 38.239255 | Q57: =P59 -> 19.295798
C58: Lease Depreciation | J58: =-IF(J57>0,IF(J57>J66,J66,J57),0) -> -18.943457 | K58: =-IF(K57>0,IF(K57>K66,K66,K57),0) -> -18.943457 | L58: =-IF(L57>0,IF(L57>L66,L66,L57),0) -> -18.943457 | M58: =-IF(M57>0,IF(M57>M66,M66,M57),0) -> -18.943457 | N58: =-IF(N57>0,IF(N57>N66,N66,N57),0) -> -18.943457 | O58: =-IF(O57>0,IF(O57>O66,O66,O57),0) -> -18.943457 | P58: =-IF(P57>0,IF(P57>P66,P66,P57),0) -> -18.943457 | Q58: =-IF(Q57>0,IF(Q57>Q66,Q66,Q57),0) -> -18.943457
C59: Short-Term Lease Liabilities | I59: =BS!I33 -> 151.9 | J59: =SUM(J57:J58) -> 132.95654 | K59: =SUM(K57:K58) -> 114.01309 | L59: =SUM(L57:L58) -> 95.069628 | M59: =SUM(M57:M58) -> 76.12617 | N59: =SUM(N57:N58) -> 57.182713 | O59: =SUM(O57:O58) -> 38.239255 | P59: =SUM(P57:P58) -> 19.295798 | Q59: =SUM(Q57:Q58) -> 0.35234002
C60: Total Lease Liabilities | I60: =BS!I33+BS!I39 -> 732.9
C61: Total Interest Expense | I61: 119.7 | J61: ,
C62: Total 2024 ROU Depreciation Expense | I62: 91.4
C63: Cash interest rate | J63: =I61/I60 -> 0.16332378 | K63: =J63 -> 0.16332378 | L63: =K63 -> 0.16332378 | M63: =L63 -> 0.16332378 | N63: =M63 -> 0.16332378 | O63: =N63 -> 0.16332378 | P63: =O63 -> 0.16332378 | Q63: =P63 -> 0.16332378
C64: Cash interest paid | J64: =J63*AVERAGE(I59:J59) -> 23.261924 | K64: =K63*AVERAGE(J59:K59) -> 20.168007 | L64: =L63*AVERAGE(K59:L59) -> 17.07409 | M64: =M63*AVERAGE(L59:M59) -> 13.980173 | N64: =N63*AVERAGE(M59:N59) -> 10.886255 | O64: =O63*AVERAGE(N59:O59) -> 7.7923383 | P64: =P63*AVERAGE(O59:P59) -> 4.6984212 | Q64: =Q63*AVERAGE(P59:Q59) -> 1.6045041
C65: Lease Principal Rate | J65: =I62/I60 -> 0.12471006 | K65: =J65 -> 0.12471006 | L65: =K65 -> 0.12471006 | M65: =L65 -> 0.12471006 | N65: =M65 -> 0.12471006 | O65: =N65 -> 0.12471006 | P65: =O65 -> 0.12471006 | Q65: =P65 -> 0.12471006
C66: Lease Principal Expense | J66: =J65*$I$59 -> 18.943457 | K66: =K65*$I$59 -> 18.943457 | L66: =L65*$I$59 -> 18.943457 | M66: =M65*$I$59 -> 18.943457 | N66: =N65*$I$59 -> 18.943457 | O66: =O65*$I$59 -> 18.943457 | P66: =P65*$I$59 -> 18.943457 | Q66: =Q65*$I$59 -> 18.943457
C68: Long-Term Lease Liabilities
C69: Beginning balance | J69: =I71 -> 581 | K69: =J71 -> 508.54346 | L69: =K71 -> 436.08691 | M69: =L71 -> 363.63037 | N69: =M71 -> 291.17383 | O69: =N71 -> 218.71729 | P69: =O71 -> 146.26074 | Q69: =P71 -> 73.804202
C70: Lease Depreciation | J70: =-IF(J69>0,IF(J69>J75,J75,J69),0) -> -72.456543 | K70: =-IF(K69>0,IF(K69>K75,K75,K69),0) -> -72.456543 | L70: =-IF(L69>0,IF(L69>L75,L75,L69),0) -> -72.456543 | M70: =-IF(M69>0,IF(M69>M75,M75,M69),0) -> -72.456543 | N70: =-IF(N69>0,IF(N69>N75,N75,N69),0) -> -72.456543 | O70: =-IF(O69>0,IF(O69>O75,O75,O69),0) -> -72.456543 | P70: =-IF(P69>0,IF(P69>P75,P75,P69),0) -> -72.456543 | Q70: =-IF(Q69>0,IF(Q69>Q75,Q75,Q69),0) -> -72.456543
C71: Short-Term Lease Liabilities | I71: =BS!I39 -> 581 | J71: =SUM(J69:J70) -> 508.54346 | K71: =SUM(K69:K70) -> 436.08691 | L71: =SUM(L69:L70) -> 363.63037 | M71: =SUM(M69:M70) -> 291.17383 | N71: =SUM(N69:N70) -> 218.71729 | O71: =SUM(O69:O70) -> 146.26074 | P71: =SUM(P69:P70) -> 73.804202 | Q71: =SUM(Q69:Q70) -> 1.34766
C72: Cash interest rate | J72: =J63 -> 0.16332378 | K72: =K63 -> 0.16332378 | L72: =L63 -> 0.16332378 | M72: =M63 -> 0.16332378 | N72: =N63 -> 0.16332378 | O72: =O63 -> 0.16332378 | P72: =P63 -> 0.16332378 | Q72: =Q63 -> 0.16332378
C73: Cash interest paid | J73: =J72*AVERAGE(I71:J71) -> 88.974179 | K73: =K72*AVERAGE(J71:K71) -> 77.140303 | L73: =L72*AVERAGE(K71:L71) -> 65.306426 | M73: =M72*AVERAGE(L71:M71) -> 53.472549 | N73: =N72*AVERAGE(M71:N71) -> 41.638673 | O73: =O72*AVERAGE(N71:O71) -> 29.804796 | P73: =P72*AVERAGE(O71:P71) -> 17.97092 | Q73: =Q72*AVERAGE(P71:Q71) -> 6.1370432
C74: Lease Principal Rate | J74: =J65 -> 0.12471006 | K74: =K65 -> 0.12471006 | L74: =L65 -> 0.12471006 | M74: =M65 -> 0.12471006 | N74: =N65 -> 0.12471006 | O74: =O65 -> 0.12471006 | P74: =P65 -> 0.12471006 | Q74: =Q65 -> 0.12471006
C75: Lease Principal Expense | J75: =J74*$I$71 -> 72.456543 | K75: =K74*$I$71 -> 72.456543 | L75: =L74*$I$71 -> 72.456543 | M75: =M74*$I$71 -> 72.456543 | N75: =N74*$I$71 -> 72.456543 | O75: =O74*$I$71 -> 72.456543 | P75: =P74*$I$71 -> 72.456543 | Q75: =Q74*$I$71 -> 72.456543
C77: Total Lease Cash interest | J77: =J64+J73 -> 112.2361 | K77: =K64+K73 -> 97.308309 | L77: =L64+L73 -> 82.380516 | M77: =M64+M73 -> 67.452722 | N77: =N64+N73 -> 52.524928 | O77: =O64+O73 -> 37.597135 | P77: =P64+P73 -> 22.669341 | Q77: =Q64+Q73 -> 7.7415473

Sheet Maturity Schedule
C2: Tullow Oil Maturity Schedule
C4: Maturity Schedule | N4: SOFR curve
D5: Maximum | F5: Max debt | G5: Cash | H5: PIK | J5: Mandatory | K5: Cash | P5: 2024 | Q5: =P5+1 -> 2025 | R5: =Q5+1 -> 2026 | S5: =R5+1 -> 2027 | T5: =S5+1 -> 2028 | U5: =T5+1 -> 2029 | V5: =U5+1 -> 2030 | W5: =V5+1 -> 2031 | X5: =W5+1 -> 2032 | ... Z5: =Y5+1 -> 2034
C6: Debt type | D6: revolver draw | E6: Amount | F6: to EBITDA | G6: interest rate | H6: rate | I6: Maturity | J6: Amort. | K6: Sweep | N6: SOFR forward rate | P6: 0.038 | Q6: {=TRANSPOSE('SOFR Forward Rate Curve'!K5:K14)} -> 0.0369 | R6: 0.0309 | S6: 0.0321 | T6: 0.0335 | U6: 0.0349 | V6: 0.0366 | W6: 0.0381 | X6: 0.0394 | Y6: 0.0406 | Z6: 0.0419
C7: New Revolver | E7: 0 | G7: 0.1 | I7: 2034 | J7: 0 | K7: 1
C8: Revolver | E8: 150 | G8: 0.1 | I8: 2025 | J8: 0 | K8: 1
C9: Senior Notes | E9: 489.4 | G9: 0.07 | I9: 2025 | J9: 0 | K9: 0
C10: Secured Notes | E10: 381.9 | G10: 0.158 | I10: 2028 | J10: 0.1 | K10: 0.5
C11: Senior Notes | E11: 1276.4 | G11: 0.1025 | I11: =IF('Debt Schedule'!S5=TRUE,2032,2026) -> 2032 | J11: 0.1 | K11: 0

Sheet DCF
I1: 2024 | J1: =I1+1 -> 2025 | K1: =J1+1 -> 2026 | L1: =K1+1 -> 2027 | M1: =L1+1 -> 2028 | N1: =M1+1 -> 2029 | O1: =N1+1 -> 2030 | P1: =O1+1 -> 2031 | Q1: =P1+1 -> 2032 | T1: Terminal Growth Rates
C2: Tullow Oil Discounted Cash Flow Valuation | T2: -0.005 | U2: =+'Forecast Assumptions'!$D$43 -> 0 | V2: -0.005
C4: Discounted Cash Flow Valuation | T4: Weighted Average Cost of Capital
C5: EBITDA | J5: =IS!J55 -> 819.76174 | K5: =IS!K55 -> 714.23381 | L5: =IS!L55 -> 703.83471 | M5: =IS!M55 -> 794.30656 | N5: =IS!N55 -> 732.25783 | O5: =IS!O55 -> 684.17126 | P5: =IS!P55 -> 622.03947 | Q5: =IS!Q55 -> 583.01422 | T5: =J37 -> 0.24412793 | U5: =K37 -> 0.20779362 | V5: =L37 -> 0.1714593
C6: Depreciation | J6: =-CFS!J10 -> -616.00489 | K6: =-CFS!K10 -> -559.21705 | L6: =-CFS!L10 -> -539.68898 | M6: =-CFS!M10 -> -661.76642 | N6: =-CFS!N10 -> -604.07986 | O6: =-CFS!O10 -> -559.16424 | P6: =-CFS!P10 -> -488.82148 | Q6: =-CFS!Q10 -> -456.08002
C7: EBIT | J7: =SUM(J5:J6) -> 203.75685 | K7: =SUM(K5:K6) -> 155.01677 | L7: =SUM(L5:L6) -> 164.14572 | M7: =SUM(M5:M6) -> 132.54013 | N7: =SUM(N5:N6) -> 128.17797 | O7: =SUM(O5:O6) -> 125.00702 | P7: =SUM(P5:P6) -> 133.218 | Q7: =SUM(Q5:Q6) -> 126.9342 | S7: Terminal Value | T7: Low | U7: Med | V7: High
C8: Income Taxes | J8: =-J7*$J$21 -> -122.45786 | K8: =-K7*$J$21 -> -93.165076 | L8: =-L7*$J$21 -> -98.651578 | M8: =-M7*$J$21 -> -79.65662 | N8: =-N7*$J$21 -> -77.034959 | O8: =-O7*$J$21 -> -75.129219 | P8: =-P7*$J$21 -> -80.064017 | Q8: =-Q7*$J$21 -> -76.287452 | S8: FY 32 Adjusted EBITDA | T8: =$Q$5 -> 583.01422 | U8: =$Q$5 -> 583.01422 | V8: =$Q$5 -> 583.01422
C9: Net Operating Profit After Tax | J9: =SUM(J7:J8) -> 81.298982 | K9: =SUM(K7:K8) -> 61.851689 | L9: =SUM(L7:L8) -> 65.494143 | M9: =SUM(M7:M8) -> 52.883513 | N9: =SUM(N7:N8) -> 51.143009 | O9: =SUM(O7:O8) -> 49.877801 | P9: =SUM(P7:P8) -> 53.153981 | Q9: =SUM(Q7:Q8) -> 50.646744 | S9: 1+ Terminal Growth Rate | T9: =1+T2 -> 0.995 | U9: =1+U2 -> 1 | V9: =1+V2 -> 0.995
S10: Terminal Adjusted EBITDA | T10: =T8*T9 -> 580.09915 | U10: =U8*U9 -> 583.01422 | V10: =V8*V9 -> 580.09915
C11: Depreciation (Add-back) | J11: =-J6 -> 616.00489 | K11: =-K6 -> 559.21705 | L11: =-L6 -> 539.68898 | M11: =-M6 -> 661.76642 | N11: =-N6 -> 604.07986 | O11: =-O6 -> 559.16424 | P11: =-P6 -> 488.82148 | Q11: =-Q6 -> 456.08002 | S11: Terminal Deprecation | T11: =$Q$6 -> -456.08002 | U11: =$Q$6 -> -456.08002 | V11: =$Q$6 -> -456.08002
C12: Capital Expenditures | J12: =CFS!J26 -> -170.8446 | K12: =CFS!K26 -> -153.56644 | L12: =CFS!L26 -> -159.69338 | M12: =CFS!M26 -> -161.82974 | N12: =CFS!N26 -> -163.67816 | O12: =CFS!O26 -> -165.22867 | P12: =CFS!P26 -> -164.3956 | Q12: =CFS!Q26 -> -163.08177 | S12: Terminal Adjusted EBIT | T12: =SUM(T10:T11) -> 124.01912 | U12: =SUM(U10:U11) -> 126.9342 | V12: =SUM(V10:V11) -> 124.01912
C13: Net Working Capital | J13: =-NWC!J17 -> -115.66155 | K13: =-NWC!K17 -> 81.001355 | L13: =-NWC!L17 -> 2.2009898 | M13: =-NWC!M17 -> 13.358095 | N13: =-NWC!N17 -> 13.459308 | O13: =-NWC!O17 -> 13.549602 | P13: =-NWC!P17 -> 18.624776 | Q13: =-NWC!Q17 -> 18.674973 | S13: Income Taxes | T13: =-T12*$J$21 -> -74.535494 | U13: =-U12*$J$21 -> -76.287452 | V13: =-V12*$J$21 -> -74.535494
C14: Unlevered Free Cash Flows | J14: =SUM(J9:J13) -> 410.79772 | K14: =SUM(K9:K13) -> 548.50365 | L14: =SUM(L9:L13) -> 447.69074 | M14: =SUM(M9:M13) -> 566.17829 | N14: =SUM(N9:N13) -> 505.00402 | O14: =SUM(O9:O13) -> 457.36298 | P14: =SUM(P9:P13) -> 396.20463 | Q14: =SUM(Q9:Q13) -> 362.31997 | S14: Terminal NOPAT | T14: =SUM(T12:T13) -> 49.483631 | U14: =SUM(U12:U13) -> 50.646744 | V14: =SUM(V12:V13) -> 49.483631
S15: Terminal Deprecation | T15: =$Q$11 -> 456.08002 | U15: =$Q$11 -> 456.08002 | V15: =$Q$11 -> 456.08002
C16: Dates | J16: =+DATE(J1,12,31) -> 46022 | K16: =+DATE(K1,12,31) -> 46387 | L16: =+DATE(L1,12,31) -> 46752 | M16: =+DATE(M1,12,31) -> 47118 | N16: =+DATE(N1,12,31) -> 47483 | O16: =+DATE(O1,12,31) -> 47848 | P16: =+DATE(P1,12,31) -> 48213 | Q16: =+DATE(Q1,12,31) -> 48579 | S16: Terminal Capital Expenditures | T16: =$Q$12*T9 -> -162.26636 | U16: =$Q$12*U9 -> -163.08177 | V16: =$Q$12*V9 -> -162.26636
C17: PV of Debt-Free Cash Flow @ 24.41% | J17: =+J14/(1+$J$37)^((J16-TODAY())/365) -> 399.6432 | K17: =+K14/(1+$J$37)^((K16-TODAY())/365) -> 428.90281 | L17: =+L14/(1+$J$37)^((L16-TODAY())/365) -> 281.37949 | M17: =+M14/(1+$J$37)^((M16-TODAY())/365) -> 285.85289 | N17: =+N14/(1+$J$37)^((N16-TODAY())/365) -> 204.93643 | O17: =+O14/(1+$J$37)^((O16-TODAY())/365) -> 149.18333 | P17: =+P14/(1+$J$37)^((P16-TODAY())/365) -> 103.87566 | Q17: =+Q14/(1+$J$37)^((Q16-TODAY())/365) -> 76.306507 | S17: Terminal Net Working Capital Change | T17: =$Q$13*T9 -> 18.581598 | U17: =$Q$13*U9 -> 18.674973 | V17: =$Q$13*V9 -> 18.581598
C18: PV of Debt-Free Cash Flow @ 20.78% | J18: =+J14/(1+$K$37)^((J16-TODAY())/365) -> 401.13882 | K18: =+K14/(1+$K$37)^((K16-TODAY())/365) -> 443.45899 | L18: =+L14/(1+$K$37)^((L16-TODAY())/365) -> 299.68108 | M18: =+M14/(1+$K$37)^((M16-TODAY())/365) -> 313.62961 | N18: =+N14/(1+$K$37)^((N16-TODAY())/365) -> 231.61461 | O18: =+O14/(1+$K$37)^((O16-TODAY())/365) -> 173.67583 | P18: =+P14/(1+$K$37)^((P16-TODAY())/365) -> 124.56763 | Q18: =+Q14/(1+$K$37)^((Q16-TODAY())/365) -> 94.267187 | S18: Terminal Debt-Free Cash Flow | T18: =SUM(T14:T17) -> 361.87889 | U18: =SUM(U14:U17) -> 362.31997 | V18: =SUM(V14:V17) -> 361.87889
C19: PV of Debt-Free Cash Flow @ 17.15% | J19: =+J14/(1+$L$37)^((J16-TODAY())/365) -> 402.68598 | K19: =+K14/(1+$L$37)^((K16-TODAY())/365) -> 458.97688 | L19: =+L14/(1+$L$37)^((L16-TODAY())/365) -> 319.78802 | M19: =+M14/(1+$L$37)^((M16-TODAY())/365) -> 345.08159 | N19: =+N14/(1+$L$37)^((N16-TODAY())/365) -> 262.74606 | O19: =+O14/(1+$L$37)^((O16-TODAY())/365) -> 203.13052 | P19: =+P14/(1+$L$37)^((P16-TODAY())/365) -> 150.21265 | Q19: =+Q14/(1+$L$37)^((Q16-TODAY())/365) -> 117.20975 | S19: Terminal Value | T19: =T18/($K$37-T2) -> 1700.6097 | U19: =U18/($K$37-U2) -> 1743.653 | V19: =V18/($K$37-V2) -> 1700.6097
S20: PV of Terminal Value | T20: =+T19/(1+T5)^(($Q$16-TODAY())/365) -> 358.15742 | U20: =+U19/(1+U5)^(($Q$16-TODAY())/365) -> 453.65776 | V20: =+V19/(1+V5)^(($Q$16-TODAY())/365) -> 550.14366
C21: Tax Rate | J21: =+IS!J37 -> 0.601
S22: Enterprise Value Calculation
C23: Weighted Average Cost of Capital (WACC) | S23: PV of Cash Flow | T23: =SUM(J17:Q17) -> 1930.0803 | U23: =SUM(J18:Q18) -> 2082.0338 | V23: =SUM(J19:Q19) -> 2259.8315
C24: Valuation Ranges | J24: Low | K24: Med | L24: High | S24: PV of Terminal Value | T24: =T20 -> 358.15742 | U24: =U20 -> 453.65776 | V24: =V20 -> 550.14366
C25: Risk Free Rate | J25: =K25 -> 0.0411 | K25: 0.0411 | L25: =K25 -> 0.0411 | S25: Enterprise Value Indication | T25: =SUM(T23:T24) -> 2288.2377 | U25: =SUM(U23:U24) -> 2535.6915 | V25: =SUM(V23:V24) -> 2809.9751
C26: Beta | J26: =K26 -> 1.378275 | K26: =+'Forecast Assumptions'!F72 -> 1.378275 | L26: =K26 -> 1.378275 | S26: Debt | T26: =-$K$33 -> -2708.7 | U26: =-$K$33 -> -2708.7 | V26: =-$K$33 -> -2708.7
C27: Equity Risk Premium | J27: =K27 -> 0.0575 | K27: =+'Forecast Assumptions'!D57 -> 0.0575 | L27: =K27 -> 0.0575 | S27: Cash | T27: =+BS!$I$6 -> 555.1 | U27: =+BS!$I$6 -> 555.1 | V27: =+BS!$I$6 -> 555.1
C28: Size Premium | J28: =K28 -> 0.055 | K28: =AVERAGE('Forecast Assumptions'!D60:D61) -> 0.055 | L28: =K28 -> 0.055 | S28: Equity Value | T28: =+SUM(T25:T27) -> 134.63774 | U28: =+SUM(U25:U27) -> 382.09151 | V28: =+SUM(V25:V27) -> 656.37512
C29: Company Specific Premium | J29: =K29 -> 0.085 | K29: ='Forecast Assumptions'!D64 -> 0.085 | L29: =K29 -> 0.085 | S29: Shares Outstanding (in mil.) | T29: =+'Trading Comps'!$R$10 -> 1465 | U29: =+'Trading Comps'!$R$10 -> 1465 | V29: =+'Trading Comps'!$R$10 -> 1465
C30: Country Risk Premium | J30: =K30 -> 0.008 | K30: ='Forecast Assumptions'!D67 -> 0.008 | L30: =K30 -> 0.008 | S30: Implied Share Price | T30: =+T28/T29 -> 0.091902895 | U30: =+U28/U29 -> 0.26081332 | V30: =+V28/V29 -> 0.44803762
C31: Capital Asset Pricing Model (CAPM) | J31: =J25+J26*J27+J28+J29+J30 -> 0.26835081 | K31: =K25+K26*K27+K28+K29+K30 -> 0.26835081 | L31: =L25+L26*L27+L28+L29+L30 -> 0.26835081
C32: Cost of Debt | J32: =K32 -> 0.065468757 | K32: =-IS!I23/BS!I42 -> 0.065468757 | L32: =K32 -> 0.065468757 | S32: Distribution of Value
C33: Total Debt | J33: =K33 -> 2708.7 | K33: =+BS!I32+BS!I33+BS!I38+BS!I39 -> 2708.7 | L33: =K33 -> 2708.7 | S33: Period Cash Flow | T33: =T23/T25 -> 0.84347893 | U33: =U23/U25 -> 0.82109111 | V33: =V23/V25 -> 0.8042176
C34: Market Value of Equity | J34: =K34 -> 146.5 | K34: =+'Trading Comps'!D15*'Trading Comps'!R10 -> 146.5 | L34: =K34 -> 146.5 | S34: Terminal | T34: =T24/T25 -> 0.15652107 | U34: =U24/U25 -> 0.17890889 | V34: =V24/V25 -> 0.1957824
C35: Weight of Debt | J35: 0.9 | K35: 0.75 | L35: 0.6 | S35: Total | T35: =SUM(T33:T34) -> 1 | U35: =SUM(U33:U34) -> 1 | V35: =SUM(V33:V34) -> 1
C36: Weight of Equity | J36: =1-J35 -> 0.1 | K36: =1-K35 -> 0.25 | L36: =1-L35 -> 0.4
C37: WACC | J37: =+J31*J35+J32*J36*(1-$J$21) -> 0.24412793 | K37: =+K31*K35+K32*K36*(1-$J$21) -> 0.20779362 | L37: =+L31*L35+L32*L36*(1-$J$21) -> 0.1714593
C39: Comps Capital Structure | J39: Total Equity | K39: Total Debt | L39: Weight Equity | M39: Weight Debt
C40: BlueNord ASA (OB:BNOR) | J40: 1196.1646 | K40: 1370.9 | L40: =1-M40 -> 0.46596592 | M40: =K40/SUM(J40:K40) -> 0.53403408
C41: DNO ASA (OB:DNO) | J41: 1429.4064 | K41: 803.3 | L41: =1-M41 -> 0.64021243 | M41: =K41/SUM(J41:K41) -> 0.35978757
C42: Energean plc (LSE:ENOG) | J42: 2435.987 | K42: 3284.711 | L42: =1-M42 -> 0.42581989 | M42: =K42/SUM(J42:K42) -> 0.57418011
C43: Northern Oil and Gas, Inc. (NYSE:NOG) | J43: 2099.1941 | K43: 2369.294 | L43: =1-M43 -> 0.46977727 | M43: =K43/SUM(J43:K43) -> 0.53022273
C44: OKEA ASA (OB:OKEA) | J44: 209.59335 | K44: 263.45145 | L44: =1-M44 -> 0.44307294 | M44: =K44/SUM(J44:K44) -> 0.55692706
C45: Savannah Energy PLC (AIM:SAVE) | J45: 178.28565 | K45: 673.518 | L45: =1-M45 -> 0.20930369 | M45: =K45/SUM(J45:K45) -> 0.79069631
C46: Tullow Oil plc (LSE:TLW) | J46: 177.45697 | K46: 2708.7 | L46: =1-M46 -> 0.061485558 | M46: =K46/SUM(J46:K46) -> 0.93851444
C47: Metric | J47: Average | K47: Median | L47: 25th | M47: 75th
C48: Target Weight of Debt | J48: =AVERAGE(M40:M45) -> 0.55764131 | K48: =+MEDIAN(M40:M45) -> 0.54548057 | L48: =+_xlfn.PERCENTILE.INC(M40:M45,0.25) -> 0.53117557 | M48: =+_xlfn.PERCENTILE.INC(M40:M45,0.75) -> 0.56986685

Sheet Liquidation Value
D2: Tullow Oil Liquidation Valuation
D4: Liquidation Valuation | R4: Cap Table | Y4: Class | Z4: Amount
Y5: {=_xlfn.UNIQUE(T7:T19)} -> 1 | Z5: =SUMIFS($S$7:$S$19,$T$7:$T$19,Y5) -> 1975.8
C6: Core Account | D6: Specific Account | F6: 2024A | H6: Estimated Recovery - % | L6: Estimated Liquidation Value | R6: Line Item | S6: Amount | T6: Recovery Rank | U6: Priority class in liquidation | W6: Tullow | Y6: 2 | Z6: =SUMIFS($S$7:$S$19,$T$7:$T$19,Y6) -> 521.1
H7: Low | I7: Med | J7: High | L7: Low | M7: Med | N7: High | R7: Curr. Port. of LT Debt | S7: =+F24 -> 589.4 | T7: 1 | U7: Secured (contractual) | W7: Portion due <12m of the secured debt stack (Super-Senior RCF if drawn; 2026 Senior Secured Notes; $400m Secured Notes Facility) | X7: | | Y7: 3 | Z7: =SUMIFS($S$7:$S$19,$T$7:$T$19,Y7) -> 1414.3
D8: Assets | R8: Long-Term borrowings | S8: =+F32 -> 1386.4 | T8: 1 | U8: Secured (contractual) | W8: Remaining secured debt stack (2026 Senior Secured Notes; $400m Secured Notes Facility; plus SSRCF if drawn) | X8: |
C9: Cash | D9: Cash & Equivalent | F9: =BS!I6 -> 555.1 | H9: 0.96 | I9: 0.98 | J9: 1 | L9: =+$F9*H9 -> 532.896 | M9: =+$F9*I9 -> 543.998 | N9: =+$F9*J9 -> 555.1 | O9: https://www.tullowoil.com/application/files/4417/4288/4975/Tullow_Oil_Plc_-_2024_FY_Report_-_FINAL.pdf | P9: Source says cash is held as bank/short-term deposits on the B/S; so we use 98% to reflect minor trap/FX risk only. | R9: Current income taxes payable | S9: =+F25 -> 175.3 | T9: 2 | U9: Statutory/priority claim | W9: Taxes payable to host governments | X9: |
C10: Accounts Receivable | D10: Receivables – Trade receivables | F10: 137.9 | H10: 0.5 | I10: 0.75 | J10: 0.9 | L10: =+$F10*H10 -> 68.95 | M10: =+$F10*I10 -> 103.425 | N10: =+$F10*J10 -> 124.11 | O10: https://www.tullowoil.com/application/files/4417/4288/4975/Tullow_Oil_Plc_-_2024_FY_Report_-_FINAL.pdf | P10: Source says trade receivables arise from oil/gas liftings with short settlement; so we use 75% (orderly collectability with wind-down timing/credit haircut). | R10: Current provisions | S10: =+F28 -> 24.3 | T10: 2 | U10: Statutory/priority-claim | W10: Near-term ARO/decommissioning and similar statutory items | X10: |
D11: Receivables – Amounts due from JV partners | F11: 357.1 | H11: 0.4 | I11: 0.6 | J11: 0.8 | L11: =+$F11*H11 -> 142.84 | M11: =+$F11*I11 -> 214.26 | N11: =+$F11*J11 -> 285.68 | O11: https://www.tullowoil.com/application/files/4417/4288/4975/Tullow_Oil_Plc_-_2024_FY_Report_-_FINAL.pdf | P11: Source says Note 10 includes significant JV cash-call receivables (e.g., Ghana/TEN related); so we use 60% for contractual claims tempered by sovereign/JV set-off risk. | R11: Non-current provisions (incl. decommissioning/ARO) | S11: =+F35 -> 321.5 | T11: 2 | U11: Statutory/priority-claim | W11: Longer-dated decommissioning obligations | X11: |
C12: Inventories | D12: Inventory | F12: =BS!I13 -> 132.4 | H12: 0.4 | I12: 0.6 | J12: 0.8 | L12: =+$F12*H12 -> 52.96 | M12: =+$F12*I12 -> 79.44 | N12: =+$F12*J12 -> 105.92 | O12: https://www.tullowoil.com/application/files/4417/4288/4975/Tullow_Oil_Plc_-_2024_FY_Report_-_FINAL.pdf | P12: Source says inventory is oil stock + warehouse spares; so we use 60% (crude near market; spares clear slowly). | R12: Payable | S12: =+F22 -> 75.7 | T12: 3 | U12: General unsecured | W12: Trade payables | X12: |
C13: Other Current Assets | D13: Other Current Assets | F13: =BS!I15 -> 24.7 | H13: 0 | I13: 0.25 | J13: 0.5 | L13: =+$F13*H13 -> 0 | M13: =+$F13*I13 -> 6.175 | N13: =+$F13*J13 -> 12.35 | O13: https://www.capitaliq.com/CIQDotNet/Filings/DocumentRedirector.axd?documentId=-1563920100 | P13: Source says provider “Other CA” aggregates prepaids/deposits/misc.; so we use 25% to mirror refundability mix. | R13: Accrued expenses | S13: =F23 -> 373.8 | T13: 3 | U13: General unsecured | W13: Accruals (opex/capex, interest, payroll, etc.) | X13: |
D14: Total Current Assets | F14: =+SUM(F9:F13) -> 1207.2 | L14: =+SUM(L9:L13) -> 797.646 | M14: =+SUM(M9:M13) -> 947.298 | N14: =+SUM(N9:N13) -> 1083.16 | R14: Current trade & other payables – Other payables | S14: =F26 -> 96.8 | T14: 3 | U14: General unsecured | W14: Other current payables per Note 12 | X14: |
R15: Current trade & other payables – Overlifts | S15: =F27 -> 38.3 | T15: 3 | U15: General unsecured | W15: JV overlifts shown in “Trade & other payables” | X15: |
D16: Property Plant & Equipment | F16: =BS!I20 -> 2324.1 | H16: 0.1 | I16: 0.3 | J16: 0.5 | L16: =+$F16*H16 -> 232.41 | M16: =+$F16*I16 -> 697.23 | N16: =+$F16*J16 -> 1162.05 | O16: https://www.tullowoil.com/application/files/4417/4288/4975/Tullow_Oil_Plc_-_2024_FY_Report_-_FINAL.pdf | P16: Source says PP&E is mainly offshore producing assets (Ghana/Jubilee/TEN) subject to impairment testing; so we use 30% (forced-sale pricing with decline/future capex haircuts). | R16: Current derivative liabilities | S16: =F29 -> 11.9 | T16: 3 | U16: General unsecured | W16: Mark-to-market on oil hedges | X16: |
C17: Other Long-Term Assets | D17: Other non-current assets – Amounts due from JV partners | F17: 333.1 | H17: 0.4 | I17: 0.6 | J17: 0.8 | L17: =+$F17*H17 -> 133.24 | M17: =+$F17*I17 -> 199.86 | N17: =+$F17*J17 -> 266.48 | O17: https://www.tullowoil.com/application/files/4417/4288/4975/Tullow_Oil_Plc_-_2024_FY_Report_-_FINAL.pdf | P17: Source says long-dated JV receivables (cash-calls/lease-related); so we use 60% for collectability with timing/sovereign risk. | R17: Long-Term Leases | S17: =F33 -> 581 | T17: 3 | U17: General unsecured | W17: IFRS 16 lease liabilities (non-current) | X17: |
D18: Other non-current assets – VAT recoverable | F18: 7.7 | H18: 0.4 | I18: 0.6 | J18: 0.9 | L18: =+$F18*H18 -> 3.08 | M18: =+$F18*I18 -> 4.62 | N18: =+$F18*J18 -> 6.93 | O18: https://www.tullowoil.com/application/files/4417/4288/4975/Tullow_Oil_Plc_-_2024_FY_Report_-_FINAL.pdf | P18: Source says statutory VAT recoverable; so we use 60% for admin/timing risk (higher potential if claims progressed). | R18: Short-Term Leases | S18: =F34 -> 151.9 | T18: 3 | U18: General unsecured | W18: IFRS 16 current portion | X18: |
D19: Total Assets | F19: =SUM(F14:F18) -> 3872.1 | L19: =SUM(L14:L18) -> 1166.376 | M19: =SUM(M14:M18) -> 1849.008 | N19: =SUM(N14:N18) -> 2518.62 | R19: Other non-current payables | S19: =F36 -> 84.9 | T19: 3 | U19: General unsecured | W19: Non-current JV/other balances | X19: |
D21: Liabilities | R21: Proceeds Waterfall
C22: Accounts Payable | D22: Payable | F22: =BS!I29 -> 75.7 | H22: =V34 -> 0 | I22: =W34 -> 0 | J22: =X34 -> 0.015357421 | L22: =+$F22*H22 -> 0 | M22: =+$F22*I22 -> 0 | N22: =+$F22*J22 -> 1.1625567 | O22: https://www.tullowoil.com/application/files/4417/4288/4975/Tullow_Oil_Plc_-_2024_FY_Report_-_FINAL.pdf | P22: Source says within “trade & other payables”; so we use 100%—operating claims at par. | R22: Account | S22: Low | T22: Med | U22: High | V22: =+S22&" % Rec." -> Low % Rec. | W22: =+T22&" % Rec." -> Med % Rec. | X22: =+U22&" % Rec." -> High % Rec.
C23: Accruals | D23: Accrued Expenses | F23: =BS!I30 -> 373.8 | H23: =V36 -> 0 | I23: =W36 -> 0 | J23: =X36 -> 0.015357421 | L23: =+$F23*H23 -> 0 | M23: =+$F23*I23 -> 0 | N23: =+$F23*J23 -> 5.7406038 | O23: https://www.tullowoil.com/application/files/4417/4288/4975/Tullow_Oil_Plc_-_2024_FY_Report_-_FINAL.pdf | P23: Source says accruals include open/capex/interest/payroll; so we use 100%—par. | R23: Assets Available for Secured Debt | S23: =+L19 -> 1166.376 | T23: =+M19 -> 1849.008 | U23: =+N19 -> 2518.62
C24: Short-Term Debt | D24: Curr. Port. of LT Debt | F24: =BS!I32 -> 589.4 | H24: =V24 -> 0.54222305 | I24: =W24 -> 0.85956394 | J24: =X24 -> 1 | L24: =+$F24*H24 -> 319.58626 | M24: =+$F24*I24 -> 506.62699 | N24: =+$F24*J24 -> 589.4 | O24: https://www.tullowoil.com/application/files/4417/4288/4975/Tullow_Oil_Plc_-_2024_FY_Report_-_FINAL.pdf | P24: Source says current borrowings (incl. current portion of LT debt) disclosed; so we use 100%—par in waterfall. | R24: =+"Less: Distribution to "&R7 -> Less: Distribution to Curr. Port. of LT Debt | S24: =-$S$7 -> -589.4 | T24: =-$S$7 -> -589.4 | U24: =-$S$7 -> -589.4 | V24: =IF(SUM(ABS(S24),ABS(S26),ABS(S28))>S23,S23/SUM(ABS(S24),ABS(S26),ABS(S28)),100%) -> 0.54222305 | W24: =IF(SUM(ABS(T24),ABS(T26),ABS(T28))>T23,T23/SUM(ABS(T24),ABS(T26),ABS(T28)),100%) -> 0.85956394 | X24: =IF(SUM(ABS(U24),ABS(U26),ABS(U28))>U23,U23/SUM(ABS(U24),ABS(U26),ABS(U28)),100%) -> 1
C25: Taxes | D25: Curr. Income Taxes Payable | F25: =BS!I34 -> 175.3 | H25: =V28 -> 0 | I25: =W28 -> 0 | J25: =X28 -> 1 | L25: =+$F25*H25 -> 0 | M25: =+$F25*I25 -> 0 | N25: =+$F25*J25 -> 175.3 | O25: https://www.tullowoil.com/application/files/4417/4288/4975/Tullow_Oil_Plc_-_2024_FY_Report_-_FINAL.pdf | P25: Source says statutory tax payable shown separately; so we use 100%—priority statutory obligations. | R25: Assets Available for Secured Debt | S25: =+IF(ABS(S24)>S23,0,IF(S23+S24>0,S23+S24,S24-S23)) -> 576.976 | T25: =+IF(ABS(T24)>T23,0,IF(T23+T24>0,T23+T24,T24-T23)) -> 1259.608 | U25: =+IF(ABS(U24)>U23,0,IF(U23+U24>0,U23+U24,U24-U23)) -> 1929.22
C26: Other Current Liabilities | D26: Current trade & other payables – Other payables | F26: 96.8 | H26: =V38 -> 0 | I26: =W38 -> 0 | J26: =X38 -> 0.015357421 | L26: =+$F26*H26 -> 0 | M26: =+$F26*I26 -> 0 | N26: =+$F26*J26 -> 1.4865983 | O26: https://www.tullowoil.com/application/files/4417/4288/4975/Tullow_Oil_Plc_-_2024_FY_Report_-_FINAL.pdf | P26: Source says contractual other payables; so we use 100%—par. | R26: =+"Less: Distribution to "&R8 -> Less: Distribution to Long-Term borrowings | S26: =-S8 -> -1386.4 | T26: =-$S$8 -> -1386.4 | U26: =-$S$8 -> -1386.4 | V26: =V24 -> 0.54222305 | W26: =W24 -> 0.85956394 | X26: =X24 -> 1
D27: Current trade & other payables – Overlifts | F27: 38.3 | H27: =V40 -> 0 | I27: =W40 -> 0 | J27: =X40 -> 0.015357421 | L27: =+$F27*H27 -> 0 | M27: =+$F27*I27 -> 0 | N27: =+$F27*J27 -> 0.58818921 | O27: https://www.tullowoil.com/application/files/4417/4288/4975/Tullow_Oil_Plc_-_2024_FY_Report_-_FINAL.pdf | P27: Source says overlifts are entitlement payables measured at market; so we use 100%—full settlement. | R27: Assets Available for Statutory Debt | S27: =+IF(ABS(S26)>S25,0,IF(S25+S26>0,S25+S26,S26-S25)) -> 0 | T27: =+IF(ABS(T26)>T25,0,IF(T25+T26>0,T25+T26,T26-T25)) -> 0 | U27: =+IF(ABS(U26)>U25,0,IF(U25+U26>0,U25+U26,U26-U25)) -> 542.82 | V27: =IF(S27=0,"",MIN(1,MAX(0,ABS(S26)/ABS(S27))))
D28: Current provisions | F28: 24.3 | H28: =V28 -> 0 | I28: =W28 -> 0 | J28: =X28 -> 1 | L28: =+$F28*H28 -> 0 | M28: =+$F28*I28 -> 0 | N28: =+$F28*J28 -> 24.3 | O28: https://www.tullowoil.com/application/files/4417/4288/4975/Tullow_Oil_Plc_-_2024_FY_Report_-_FINAL.pdf | P28: Source says near-term field/claim items; so we use 105% as settlements often exceed book in a wind-down. | R28: =+"Less: Distribution to "&R9 -> Less: Distribution to Current income taxes payable | S28: =-$S$9 -> -175.3 | T28: =-$S$9 -> -175.3 | U28: =-$S$9 -> -175.3 | V28: =IF(INDEX($Y$5:$Z$7,2,2)>S27,S27/INDEX($Y$5:$Z$7,2,2),100%) -> 0 | W28: =IF(INDEX($Y$5:$Z$7,2,2)>T27,T27/INDEX($Y$5:$Z$7,2,2),100%) -> 0 | X28: =IF(INDEX($Y$5:$Z$7,2,2)>U27,U27/INDEX($Y$5:$Z$7,2,2),100%) -> 1
D29: Current derivative liabilities | F29: 11.9 | H29: =V42 -> 0 | I29: =W42 -> 0 | J29: =X42 -> 0.015357421 | L29: =+$F29*H29 -> 0 | M29: =+$F29*I29 -> 0 | N29: =+$F29*J29 -> 0.18275331 | O29: https://www.tullowoil.com/application/files/4417/4288/4975/Tullow_Oil_Plc_-_2024_FY_Report_-_FINAL.pdf | P29: Source says fair-valued derivatives; so we use 100%—assume full settlement if not netted. | R29: Assets Available for Statutory Debt | S29: =+IF(ABS(S28)>S27,0,IF(S27+S28>0,S27+S28,S28-S27)) -> 0 | T29: =+IF(ABS(T28)>T27,0,IF(T27+T28>0,T27+T28,T28-T27)) -> 0 | U29: =+IF(ABS(U28)>U27,0,IF(U27+U28>0,U27+U28,U28-U27)) -> 367.52 | V29: =IF(S29=0,"",MIN(1,MAX(0,ABS(S28)/ABS(S29))))
D30: Total Current Liabilities | F30: =SUM(F22:F29) -> 1385.5 | L30: =SUM(L22:L29) -> 319.58626 | M30: =SUM(M22:M29) -> 506.62699 | N30: =SUM(N22:N29) -> 798.1607 | R30: =+"Less: Distribution to "&R10 -> Less: Distribution to Current provisions | S30: =-$S$10 -> -24.3 | T30: =-$S$10 -> -24.3 | U30: =-$S$10 -> -24.3 | V30: =V28 -> 0 | W30: =W28 -> 0 | X30: =X28 -> 1
R31: Assets Available for Statutory Debt | S31: =+IF(ABS(S30)>S29,0,IF(S29+S30>0,S29+S30,S30-S29)) -> 0 | T31: =+IF(ABS(T30)>T29,0,IF(T29+T30>0,T29+T30,T30-T29)) -> 0 | U31: =+IF(ABS(U30)>U29,0,IF(U29+U30>0,U29+U30,U30-U29)) -> 343.22 | V31: =IF(S31=0,"",MIN(1,MAX(0,ABS(S30)/ABS(S31))))
C32: Long-Term Debt | D32: Long-Term borrowings | F32: =BS!I38 -> 1386.4 | H32: =V26 -> 0.54222305 | I32: =W26 -> 0.85956394 | J32: =X26 -> 1 | L32: =+$F32*H32 -> 751.73803 | M32: =+$F32*I32 -> 1191.6995 | N32: =+$F32*J32 -> 1386.4 | R32: =+"Less: Distribution to "&R11 -> Less: Distribution to Non-current provisions (incl. decommissioning/ARO) | S32: =-$S$11 -> -321.5 | T32: =-$S$11 -> -321.5 | U32: =-$S$11 -> -321.5 | V32: =V30 -> 0 | W32: =W30 -> 0 | X32: =X30 -> 1
D33: Long-Term Leases | F33: =BS!I39 -> 581 | H33: =V44 -> 0 | I33: =W44 -> 0 | J33: =X44 -> 0.015357421 | L33: =+$F33*H33 -> 0 | M33: =+$F33*I33 -> 0 | N33: =+$F33*J33 -> 8.9226614 | O33: https://www.tullowoil.com/application/files/4417/4288/4975/Tullow_Oil_Plc_-_2024_FY_Report_-_FINAL.pdf | P33: Source says gross borrowings by maturity; so we use 100%—par for liability side math. | R33: Assets Available for General Unsecured | S33: =+IF(ABS(S32)>S31,0,IF(S31+S32>0,S31+S32,S32-S31)) -> 0 | T33: =+IF(ABS(T32)>T31,0,IF(T31+T32>0,T31+T32,T32-T31)) -> 0 | U33: =+IF(ABS(U32)>U31,0,IF(U31+U32>0,U31+U32,U32-U31)) -> 21.72 | V33: =IF(S33=0,"",MIN(1,MAX(0,ABS(S32)/ABS(S33))))
D34: Short-Term Leases | F34: =BS!I33 -> 151.9 | H34: =V46 -> 0 | I34: =W46 -> 0 | J34: =X46 -> 0.015357421 | L34: =+$F34*H34 -> 0 | M34: =+$F34*I34 -> 0 | N34: =+$F34*J34 -> 2.3327922 | O34: https://www.tullowoil.com/application/files/4417/4288/4975/Tullow_Oil_Plc_-_2024_FY_Report_-_FINAL.pdf | P34: Source says IFRS 16 non-current lease liabilities; so we use 100%—contractual. | R34: =+"Less: Distribution to "&R12 -> Less: Distribution to Payable | S34: =-$S$12 -> -75.7 | T34: =-$S$12 -> -75.7 | U34: =-$S$12 -> -75.7 | V34: =IF(INDEX($Y$5:$Z$7,3,2)>S33,S33/INDEX($Y$5:$Z$7,3,2)) -> 0 | W34: =IF(INDEX($Y$5:$Z$7,3,2)>T33,T33/INDEX($Y$5:$Z$7,3,2)) -> 0 | X34: =IF(INDEX($Y$5:$Z$7,3,2)>U33,U33/INDEX($Y$5:$Z$7,3,2)) -> 0.015357421
C35: Other Non-Current Liabilities | D35: Non-current provisions (incl. decommissioning/ARO) | F35: 321.5 | H35: =V32 -> 0 | I35: =W32 -> 0 | J35: =X32 -> 1 | L35: =+$F35*H35 -> 0 | M35: =+$F35*I35 -> 0 | N35: =+$F35*J35 -> 321.5 | O35: https://www.tullowoil.com/application/files/4417/4288/4975/Tullow_Oil_Plc_-_2024_FY_Report_-_FINAL.pdf | P35: Source says provisions include field decommissioning and other long-tail obligations; so we use 105% since wind-down often increases cash outlay (acceleration/contractor premia). | R35: Assets Available for General Unsecured | S35: =+IF(ABS(S34)>S33,0,IF(S33+S34>0,S33+S34,S34-S33)) -> 0 | T35: =+IF(ABS(T34)>T33,0,IF(T33+T34>0,T33+T34,T34-T33)) -> 0 | U35: =+IF(ABS(U34)>U33,0,IF(U33+U34>0,U33+U34,U34-U33)) -> 0 | V35: =IF(S35=0,"",MIN(1,MAX(0,ABS(S34)/ABS(S35)))) | X35: =IF(U35=0,"",MIN(1,MAX(0,ABS(U34)/ABS(U35))))
D36: Other non-current payables | F36: 84.9 | H36: =V48 -> 0 | I36: =W48 -> 0 | J36: =X48 -> 0.015357421 | L36: =+$F36*H36 -> 0 | M36: =+$F36*I36 -> 0 | N36: =+$F36*J36 -> 1.303845 | O36: https://www.tullowoil.com/application/files/4417/4288/4975/Tullow_Oil_Plc_-_2024_FY_Report_-_FINAL.pdf | P36: Source says long-dated contractual/JV-related payables; so we use 100% (contractual amounts assumed payable at par). | R36: =+"Less: Distribution to "&R13 -> Less: Distribution to Accrued expenses | S36: =-$S$13 -> -373.8 | T36: =-$S$13 -> -373.8 | U36: =-$S$13 -> -373.8 | V36: =V34 -> 0 | W36: =W34 -> 0 | X36: =X34 -> 0.015357421
D37: Total Liabilities | F37: =SUM(F30:F36) -> 3911.2 | L37: =SUM(L32:L36)+L30 -> 1071.3243 | M37: =SUM(M32:M36)+M30 -> 1698.3264 | N37: =SUM(N32:N36)+N30 -> 2518.62 | R37: Assets Available for General Unsecured | S37: =+IF(ABS(S36)>S35,0,IF(S35+S36>0,S35+S36,S36-S35)) -> 0 | T37: =+IF(ABS(T36)>T35,0,IF(T35+T36>0,T35+T36,T36-T35)) -> 0 | U37: =+IF(ABS(U36)>U35,0,IF(U35+U36>0,U35+U36,U36-U35)) -> 0 | V37: =IF(S37=0,"",MIN(1,MAX(0,ABS(S36)/ABS(S37)))) | X37: =IF(U37=0,"",MIN(1,MAX(0,ABS(U36)/ABS(U37))))
R38: =+"Less: Distribution to "&R14 -> Less: Distribution to Current trade & other payables – Other payables | S38: =-$S$14 -> -96.8 | T38: =-$S$14 -> -96.8 | U38: =-$S$14 -> -96.8 | V38: =V36 -> 0 | W38: =W36 -> 0 | X38: =X36 -> 0.015357421
D39: Equity Value | R39: Assets Available for General Unsecured | S39: =+IF(ABS(S38)>S37,0,IF(S37+S38>0,S37+S38,S38-S37)) -> 0 | T39: =+IF(ABS(T38)>T37,0,IF(T37+T38>0,T37+T38,T38-T37)) -> 0 | U39: =+IF(ABS(U38)>U37,0,IF(U37+U38>0,U37+U38,U38-U37)) -> 0 | V39: =IF(S39=0,"",MIN(1,MAX(0,ABS(S38)/ABS(S39)))) | X39: =IF(U39=0,"",MIN(1,MAX(0,ABS(U38)/ABS(U39))))
D40: Assets | L40: =L19 -> 1166.376 | M40: =M19 -> 1849.008 | N40: =N19 -> 2518.62 | R40: =+"Less: Distribution to "&R15 -> Less: Distribution to Current trade & other payables – Overlifts | S40: =-$S$15 -> -38.3 | T40: =-$S$15 -> -38.3 | U40: =-$S$15 -> -38.3 | V40: =V38 -> 0 | W40: =W38 -> 0 | X40: =X38 -> 0.015357421
D41: Liabilities | L41: =L37 -> 1071.3243 | M41: =M37 -> 1698.3264 | N41: =N37 -> 2518.62 | R41: Assets Available for General Unsecured | S41: =+IF(ABS(S40)>S39,0,IF(S39+S40>0,S39+S40,S40-S39)) -> 0 | T41: =+IF(ABS(T40)>T39,0,IF(T39+T40>0,T39+T40,T40-T39)) -> 0 | U41: =+IF(ABS(U40)>U39,0,IF(U39+U40>0,U39+U40,U40-U39)) -> 0 | V41: =IF(S41=0,"",MIN(1,MAX(0,ABS(S40)/ABS(S41)))) | X41: =IF(U41=0,"",MIN(1,MAX(0,ABS(U40)/ABS(U41))))
D42: Equity Value | L42: =+L40-L41 -> 95.0517 | M42: =+M40-M41 -> 150.68156 | N42: =+N40-N41 -> 0 | R42: =+"Less: Distribution to "&R16 -> Less: Distribution to Current derivative liabilities | S42: =-$S$16 -> -11.9 | T42: =-$S$16 -> -11.9 | U42: =-$S$16 -> -11.9 | V42: =V40 -> 0 | W42: =W40 -> 0 | X42: =X40 -> 0.015357421
R43: Assets Available for General Unsecured | S43: =+IF(ABS(S42)>S41,0,IF(S41+S42>0,S41+S42,S42-S41)) -> 0 | T43: =+IF(ABS(T42)>T41,0,IF(T41+T42>0,T41+T42,T42-T41)) -> 0 | U43: =+IF(ABS(U42)>U41,0,IF(U41+U42>0,U41+U42,U42-U41)) -> 0 | V43: =IF(S43=0,"",MIN(1,MAX(0,ABS(S42)/ABS(S43)))) | X43: =IF(U43=0,"",MIN(1,MAX(0,ABS(U42)/ABS(U43))))
D44: Enterprise Value | R44: =+"Less: Distribution to "&R17 -> Less: Distribution to Long-Term Leases | S44: =-$S$17 -> -581 | T44: =-$S$17 -> -581 | U44: =-$S$17 -> -581 | V44: =V42 -> 0 | W44: =W42 -> 0 | X44: =X42 -> 0.015357421
D45: =+D42 -> Equity Value | L45: =+L42 -> 95.0517 | M45: =+M42 -> 150.68156 | N45: =+N42 -> 0 | R45: Assets Available for General Unsecured | S45: =+IF(ABS(S44)>S43,0,IF(S43+S44>0,S43+S44,S44-S43)) -> 0 | T45: =+IF(ABS(T44)>T43,0,IF(T43+T44>0,T43+T44,T44-T43)) -> 0 | U45: =+IF(ABS(U44)>U43,0,IF(U43+U44>0,U43+U44,U44-U43)) -> 0 | V45: =IF(S45=0,"",MIN(1,MAX(0,ABS(S44)/ABS(S45)))) | X45: =IF(U45=0,"",MIN(1,MAX(0,ABS(U44)/ABS(U45))))
D46: Net Debt | L46: =(L32+L24+L33+L34)-L9 -> 538.4283 | M46: =(M32+M24+M33+M34)-M9 -> 1154.3284 | N46: =(N32+N24+N33+N34)-N9 -> 1431.9555 | R46: =+"Less: Distribution to "&R18 -> Less: Distribution to Short-Term Leases | S46: =-$S$18 -> -151.9 | T46: =-$S$18 -> -151.9 | U46: =-$S$18 -> -151.9 | V46: =V44 -> 0 | W46: =W44 -> 0 | X46: =X44 -> 0.015357421
D47: Enterprise Value | L47: =SUM(L45:L46) -> 633.48 | M47: =SUM(M45:M46) -> 1305.01 | N47: =SUM(N45:N46) -> 1431.9555 | R47: Assets Available for General Unsecured | S47: =+IF(ABS(S46)>S45,0,IF(S45+S46>0,S45+S46,S46-S45)) -> 0 | T47: =+IF(ABS(T46)>T45,0,IF(T45+T46>0,T45+T46,T46-T45)) -> 0 | U47: =+IF(ABS(U46)>U45,0,IF(U45+U46>0,U45+U46,U46-U45)) -> 0 | V47: =IF(S47=0,"",MIN(1,MAX(0,ABS(S46)/ABS(S47)))) | X47: =IF(U47=0,"",MIN(1,MAX(0,ABS(U46)/ABS(U47))))
R48: =+"Less: Distribution to "&R19 -> Less: Distribution to Other non-current payables | S48: =-$S$19 -> -84.9 | T48: =-$S$19 -> -84.9 | U48: =-$S$19 -> -84.9 | V48: =V46 -> 0 | W48: =W46 -> 0 | X48: =X46 -> 0.015357421
R49: Value Available for Equity Holders Equity Value | S49: =+IF(ABS(S48)>S47,0,IF(S47+S48>0,S47+S48,S48-S47)) -> 0 | T49: =+IF(ABS(T48)>T47,0,IF(T47+T48>0,T47+T48,T48-T47)) -> 0 | U49: =+IF(ABS(U48)>U47,0,IF(U47+U48>0,U47+U48,U48-U47)) -> 0
O75: Account (2024A USD $m)
O76: Cash & cash equivalents (555.1)
O77: Receivables – Trade receivables (137.9)
O78: Receivables – Amounts due from JV partners (current) (350.2)
O79: Receivables – Under lifts (20.9)
O80: Receivables – Prepayments (17.1)
O81: Receivables – Other current assets (3.7)
O82: Inventories (132.4)
O83: PP&E (2,324.1)
O84: Other non-current assets – Amounts due from JV partners (333.1)
O85: Other non-current assets – VAT recoverable (7.7)

Sheet Trading Comps
C2: Tullow Oil Liquidation Valuation
C4: Tullow Oil | Trading Multiples Valuation | N4: Tullow Oil | Information
N5: Sales (TTM) | R5: 1280
E6: Multiples | N6: EBITDA (TTM) | R6: 666.9
C7: Company Name | D7: Price | E7: EV/EBITDA | F7: EV/Sales | G7: P/Sales | H7: Equity Beta | I7: ETR | J7: D/E | K7: Asset Beta | L7: Lev. Ratio | N7: Net income (TTM) | R7: -153.7
C8: DNO ASA (OB:DNO) | D8: 1.3718342 | E8: 5.542663 | F8: 2.818872 | G8: 1.705871 | H8: 1.5053169 | I8: =+'Forecast Assumptions'!D46 -> 1.038 | J8: 116.49 | K8: =+IFERROR(H8/(1+(1-I8)*J8),"NM") -> -0.4393008 | L8: 2.215 | N8: Total debt | R8: 2474.7
C9: Nostrum Oil & Gas PLC (LSE:NOG) | D9: 0.047019885 | E9: 10.063805 | F9: 3.663753 | G9: 0.061005 | H9: -0.038316671 | I9: =+'Forecast Assumptions'!D47 -> NA | J9: NM | K9: =+IFERROR(H9/(1+(1-I9)*J9),"NM") -> NM | L9: 9.907 | N9: Cash | R9: 194.1
C10: OKEA ASA (OB:OKEA) | D10: 1.8034336 | E10: 0.288709 | F10: 0.179529 | G10: 0.203765 | H10: 1.518016 | I10: =+'Forecast Assumptions'!D48 -> 0.83 | J10: 392.587 | K10: =+IFERROR(H10/(1+(1-I10)*J10),"NM") -> 0.022409517 | L10: 1.2 | N10: Shares outstanding (in mil.) | R10: 1465
C11: Savannah Energy PLC (AIM:SAVE) | D11: 0.09128162 | E11: 6.744013 | F11: 3.425685 | G11: 0.546481 | H11: 0.46733886 | I11: =+'Forecast Assumptions'!D49 -> NA | J11: 153.917 | K11: =+IFERROR(H11/(1+(1-I11)*J11),"NM") -> NM | L11: 5.23
C12: Energean PLC (LSE:ENOG) | D12: 12.66122 | E12: 6.184671 | F12: 4.438525 | G12: 1.962098 | H12: 1.2812809 | I12: =+'Forecast Assumptions'!D50 -> 0.32 | J12: 543.626 | K12: =+IFERROR(H12/(1+(1-I12)*J12),"NM") -> 0.0034567022 | L12: 3.442 | N12: Tullow Oil | Implied Equity Prices
C13: BlueNord ASA (OB:BNOR) | D13: 45.727808 | E13: 4.768973 | F13: 2.48094 | G13: 1.440422 | H13: 1.0849802 | I13: =+'Forecast Assumptions'!D51 -> NA | J13: 147.756 | K13: =+IFERROR(H13/(1+(1-I13)*J13),"NM") -> NM | L13: 2.125 | N13: Statistic | P13: EV/EBITDA | Q13: EV/Sales | R13: P/Sales
N14: 25th | P14: =((E18*$R$6)-$R$8+$R$9)/$R$10 -> 0.10433862 | Q14: =((F18*$R$5)-$R$8+$R$9)/$R$10 -> 0.1082264 | R14: =(G18*$R$5)/$R$10 -> 0.14685051
C15: Tullow Oil | D15: 0.1 | E15: 2.6 | F15: 1.9 | G15: 0.15 | H15: 1.46 | I15: =+'Forecast Assumptions'!D6 -> 0.601 | J15: NM | K15: =+IFERROR(H15/(1+(1-I15)*J15),"NM") -> NM | L15: =(BS!I42-BS!I6)/IS!I55 -> 3.3836969 | N15: Median | P15: =((E19*$R$6)-$R$8+$R$9)/$R$10 -> 1.1125457 | Q15: =((F19*$R$5)-$R$8+$R$9)/$R$10 -> 1.171274 | R15: =(G19*R5)/$R$10 -> 0.86799858
N16: 75th | P16: =((E21*$R$6)-$R$8+$R$9)/$R$10 -> 1.8911089 | Q16: =((F21*$R$5)-$R$8+$R$9)/$R$10 -> 1.8136047 | R16: =(G21*$R$5)/$R$10 -> 1.5464215
C17: Minimum | E17: =MIN(E8:E13) -> 0.288709 | F17: =MIN(F8:F13) -> 0.179529 | G17: =MIN(G8:G13) -> 0.061005 | H17: =MIN(H8:H13) -> -0.038316671 | J17: =MIN(J8:J13) -> 116.49 | K17: =MIN(K8:K13) -> -0.4393008 | L17: =MIN(L8:L13) -> 1.2
C18: 25th percentile | E18: =_xlfn.QUARTILE.EXC(E8:E13, 1) -> 3.648907 | F18: =_xlfn.QUARTILE.EXC(F8:F13, 1) -> 1.9055872 | G18: =_xlfn.QUARTILE.EXC(G8:G13, 1) -> 0.168075 | H18: =_xlfn.QUARTILE.EXC(H8:H13, 1) -> 0.34092498 | J18: =_xlfn.QUARTILE.EXC(J8:J13, 1) -> 132.123 | K18: =_xlfn.QUARTILE.EXC(K8:K13, 1) -> -0.4393008 | L18: =_xlfn.QUARTILE.EXC(L8:L13, 1) -> 1.89375
C19: Median | E19: =MEDIAN(E8:E13) -> 5.863667 | F19: =MEDIAN(F8:F13) -> 3.1222785 | G19: =MEDIAN(G8:G13) -> 0.9934515 | H19: =MEDIAN(H8:H13) -> 1.1831305 | J19: =MEDIAN(J8:J13) -> 153.917 | K19: =MEDIAN(K8:K13) -> 0.0034567022 | L19: =MEDIAN(L8:L13) -> 2.8285
C20: Mean | E20: =AVERAGE(E8:E13) -> 5.5988057 | F20: =AVERAGE(F8:F13) -> 2.8345507 | G20: =AVERAGE(G8:G13) -> 0.986607 | H20: =AVERAGE(H8:H13) -> 0.96976936 | J20: =AVERAGE(J8:J13) -> 270.8752 | K20: =AVERAGE(K8:K13) -> -0.13781153 | L20: =AVERAGE(L8:L13) -> 4.0198333
C21: 75th percentile | E21: =_xlfn.QUARTILE.EXC(E8:E13, 3) -> 7.573961 | F21: =_xlfn.QUARTILE.EXC(F8:F13, 3) -> 3.857446 | G21: =_xlfn.QUARTILE.EXC(G8:G13, 3) -> 1.7699277 | H21: =_xlfn.QUARTILE.EXC(H8:H13, 3) -> 1.5084917 | J21: =_xlfn.QUARTILE.EXC(J8:J13, 3) -> 468.1065 | K21: =_xlfn.QUARTILE.EXC(K8:K13, 3) -> 0.022409517 | L21: =_xlfn.QUARTILE.EXC(L8:L13, 3) -> 6.39925
C22: Maximum | E22: =MAX(E8:E13) -> 10.063805 | F22: =MAX(F8:F13) -> 4.438525 | G22: =MAX(G8:G13) -> 1.962098 | H22: =MAX(H8:H13) -> 1.518016 | J22: =MAX(J8:J13) -> 543.626 | K22: =MAX(K8:K13) -> 0.022409517 | L22: =MAX(L8:L13) -> 9.907

Sheet Precedent Transactions 
C2: Tullow Oil Liquidation Valuation
C4: Tullow Oil | Precedent Transaction Valuation
C6: Date | D6: Target | E6: Acquirer | F6: Transaction Value ($ in millions) | G6: EV/EBITDA | H6: EV/Sales | J6: Tullow Oil | Information
C7: 44286 | D7: Premier Oil plc (LSE:PMO) | E7: Harbour Energy plc (LSE:HBR) | F7: 285.7 | G7: NA | H7: NA | J7: Sales (LTM) | N7: ='Trading Comps'!R5 -> 1280
C8: 44742 | D8: Siccar Point Energy Limited | E8: Ithaca Energy (UK) Limited | F8: 1622.514 | G8: 1.9131288 | H8: 6.2983591 | J8: EBITDA (LTM) | N8: ='Trading Comps'!R6 -> 666.9
C9: 45085 | D9: Hurricane Energy plc (AIM:HUR) | E9: Prax Global Finance I PLC | F9: 238.61047 | G9: 1.111948 | H9: 0.75377508 | J9: Total debt | N9: ='Trading Comps'!R8 -> 2474.7
C10: 45601 | D10: Trinity Exploration plc (AIM:TRIN) | E10: Lease Operators Limited | F10: 30.884035 | G10: 1.6549055 | H10: 0.42957061 | J10: Cash | N10: ='Trading Comps'!R9 -> 194.1
C11: 45184 | D11: Egdon Resources plc (AIM:EDR) | E11: Petrichor Partners LP | F11: 11.461876 | G11: 3.871603 | H11: 2.467529 | J11: Shares outstanding (in mil.) | N11: ='Trading Comps'!R10 -> 1465
C12: 45642 | D12: Tethys Oil AB (STO:TETY) | E12: Roc Oil Company Pty Limited (:ROC) | F12: 145.57143 | G12: 2.392157 | H12: 1.2405838
C13: 45740 | D13: Serinus Energy plc | E13: Xtellus Capital Partners, Inc. | F13: 4.5515221 | G13: 3.9345307 | H13: 0.3806539 | J13: Tullow Oil | Implied Equity Prices
C14: 44900 | D14: Wentworth Resources plc | E14: Etablissements Maurel & Prom S.A. (ENXTPA:MAU) | F14: 37.278013 | G14: 2.1367731 | H14: 1.3167241 | M14: Multiples
C15: 45107 | D15: Suncor Energy UK Limited | E15: Equinor UK Limited | F15: 905.92019 | G15: NA | H15: NA | J15: Statistic | M15: EV/EBITDA | N15: EV/Sales
C16: 45296 | D16: KUFPEC Norway AS | E16: ORLEN Upstream Norway AS | F16: 445 | G16: NA | H16: NA | J16: Median | M16: =(($G$21*$N$8)-$N$9+$N$10)/$N$11 -> -0.52588959 | N16: =(($H$21*$N$7)-$N$9+$N$10)/$N$11 -> -0.43953785
C17: 45596 | D17: Gran Tierra UK Limited | E17: Gran Tierra Energy Inc. (NYSEAM:GTE) | F17: 322.83023 | G17: 4.350355 | H17: 1.5963431
C19: Minimum | G19: =MIN(G7:G17) -> 1.111948 | H19: =MIN(H7:H17) -> 0.3806539
C20: 25th percentile | G20: =_xlfn.QUARTILE.INC(G7:G17,1) -> 1.848573 | H20: =_xlfn.QUARTILE.INC(H7:H17,1) -> 0.67272396
C21: Median | G21: =MEDIAN(G7:G17) -> 2.2644651 | H21: =MEDIAN(H7:H17) -> 1.2786539
C22: Mean | G22: =AVERAGE(G7:G17) -> 2.6706751 | H22: =AVERAGE(H7:H17) -> 1.8104423
C23: 75th percentile | G23: =_xlfn.QUARTILE.INC(G7:G17,3) -> 3.8873349 | H23: =_xlfn.QUARTILE.INC(H7:H17,3) -> 1.8141395
C24: Maximum | G24: =MAX(G7:G17) -> 4.350355 | H24: =MAX(H7:H17) -> 6.2983591

Sheet Forecast Assumptions
C2: Tullow Oil | Forecast Assumptions (mm$)
C4: Forecast Assumptions | D4: Value | E4: Rationale | H4: Source
C5: Accrued expenses and prepaid expenses (% of Revenue), since SG&A is a much smaller account and is a less reliable predictor.
C6: Fwd. Adj. Effective Tax Rate | D6: 0.601 | E6: Adjusted for non-recurring write-offs, exploration costs, and disposals. Using 2024E adj. effective tax rate. | H6: Tullow Oil
C7: Minimum Cash Balance | D7: 300 | E7: Company doesn't explicitly have a minimum cash balance but we assume one of $300M conservatively, as they've historically been above that cash level.
C9: Covenants | D9: Value | E9: Rationale | H9: Source
C10: RCF Covenants | E10: No maintenance covenants on RCF per 2021 PLC report (pg. 133). | H10: Tullow Oil
C11: RCF Availability | D11: 500 | E11: Determined from the NPV of 2P reserves / 1.1x Senior Notes outstanding (pg. 133). | H11: Tullow Oil
C12: 2026 Senior Secured Notes | E12: Incurrence covenants allow debt payments only if 2P Reserve Coverage >= 2.0x and Consolidated Leverage Ratio < 1.5x (pg. 33). | H12: Tullow Oil
C13: Required 2P Reserve Cov. | D13: 2
C14: Max Consolidated Lev. | D14: 1.5
C15: Senior Notes Covenants | E15: No maintenance covenants, incurrence covenants are the same as the 2026 Senior Secured Notes. | H15: Tullow Oil
C17: Oil Price Forecast | D17: 2025 | E17: 2026 | F17: 2032 | G17: Comments
C18: Oil Price:
C19: EIA | D19: 71.5 | E19: 59 | F19: 73 | G19: The EIA's October 2025 STEO (Short-Term Energy Outlook) forecasts Brent to fall to an average of $62/bbl. in Q4 2025 and $52/bbl. in 2026 as oversupply builds. The $73 long-term value is based on older, pre-2025 data, as more recent forecasts are more bearish. | H19: |
C20: Goldman Sachs | D20: 69 | E20: 53 | F20: 50 | G20: In October 2025, Goldman Sachs expected Brent prices to drift towards the low $50s by the end of 2026, driven by an expanding global surplus. The bank also provided bear-case scenarios that could see prices drop below $40 if a recession and full OPEC+ unwind occurred. | H20: |
C21: Fitch Ratings | D21: 70 | E21: 65 | F21: 60 | G21: Fitch Ratings' long-term price deck from November 2025 assumes Brent at $70/bbl. for 2025, $65 for 2026, and $60 for 2028 and beyond, reflecting a balanced market view despite short-term volatility. | H21: |
C22: Morgan Stanley | D22: N/A | E22: 60 | F22: 65 | G22: In November 2025, Morgan Stanley raised its near-term Brent forecast to $60/bbl. for the first half of 2026 after OPEC+ decided to pause production hikes, citing reduced volatility from OPEC+ involvement. | H22: |
C23: World Bank | D23: 73 | E23: 60 | F23: 73 | G23: The World Bank's October 2025 Commodity Markets Outlook forecasts Brent to fall from an average of $68/bbl. in 2025 to $60/bbl. in 2026 due to an expanded oil glut, reaching a five-year low. The long-term $73 figure is a historical average/assumption from older reports. | H23: |
C24: Average Price | D24: =AVERAGE(D19:D23) -> 70.875 | E24: =AVERAGE(E19:E23) -> 59.4 | F24: =AVERAGE(F19:F23) -> 64.2
C26: Gas Price Forecast | D26: 2025 | E26: 2026 | F26: 2032 | G26: Comments
C27: Gas Price:
C28: EIA | D28: 3.8 | E28: 4 | F28: 4.2 | G28: The U.S. Energy Information Administration (EIA) has also weighed in with its long-term outlook. In its Annual Energy Outlook 2025, the EIA forecasts Henry Hub prices to reach $3.80/MMBtu by 2030, $4.20/MMBtu by 2040, and $4.95/MMBtu by 2050 in their reference case scenario. | H28: |
C30: Year | D30: WI Oil (boe/d) | E30: WI Gas (boe/d) | F30: Total WI (boe/d) | G30: Rationale | H30: Source
C31: 2025 | D31: 37000 | E31: 6000 | F31: =+SUM(D31:E31) -> 43000 | G31: Production is assumed to be 40,000 to 45,000 barrels of oil per day adjusted for the Gabon asset removal. | H31: Tullow Oil – 2025 H1 Results
C32: 2026 | D32: 39000 | E32: 6500 | F32: =+SUM(D32:E32) -> 45500 | G32: Increased capital spending and uplift in production driven by recommenced drilling including four additional Jubilee wells planned. | H32: Tullow Oil – 2025 H1 Results
C33: 2027 | D33: 38500 | E33: 6800 | F33: =+SUM(D33:E33) -> 45300 | G33: Production begins declining modestly after 2026 activity peak, with optimization measures supporting volumes. | H33: Tullow Oil – 2025 H1 Results
C34: 2028 | D34: 37000 | E34: 7000 | F34: =+SUM(D34:E34) -> 44000 | G34: Production moderates, with assumed mid-cycle pricing recovery and improved financing terms post-refinancing period. | H34: Tullow Oil – 2025 H1 Results
C35: 2029 | D35: 35500 | E35: 7200 | F35: =+SUM(D35:E35) -> 42700 | G35: Expected continued natural decline with incremental gas growth as the Ghana MoU allows for improved gas monetization. | H35: Tullow Oil – Ghana Licenses MoU
C36: 2030 | D36: 34000 | E36: 7400 | F36: =+SUM(D36:E36) -> 41400 | G36: Post-refinancing capital structure expected to reduce borrowing cost as deleveraging targets are approached. | H36: Tullow Oil – 2025 H1 Results
C37: 2031 | D37: 32000 | E37: 7600 | F37: =+SUM(D37:E37) -> 39600 | G37: Normalization of realized pricing and plateauing of corporate efficiencies following cost-saving initiatives. | H37: Tullow Oil – 2025 H1 Results
C38: 2032 | D38: 30000 | E38: 7800 | F38: =+SUM(D38:E38) -> 37800 | G38: Production transitions into sustaining mode requiring lower capital expenditures as fields mature. | H38: Tullow Oil – 2025 H1 Results
C39: 2033 | D39: 28000 | E39: 8000 | F39: =+SUM(D39:E39) -> 36000 | G39: Late-life field tail where decline continues and decommissioning allocations gradually increase. | H39: Tullow Oil – 2025 H1 Results
C40: 2034 | D40: 26000 | E40: 8000 | F40: =+SUM(D40:E40) -> 34000 | G40: Near-end-game profile reflecting the Ghana license horizon through 2040, approaching final years before economic limit. | H40: Tullow Oil – Ghana Licenses MoU
C42: Discounted Cash Flow Assumptions | D42: Value | E42: Rationale | H42: Source
C43: Terminal Growth Rate | D43: 0 | E43: Source indicates that the terminal growth rate is 0%. | H43: TGS 2023 Q4 Earnings Release
C45: Trading Comps Effective Tax Rate:
C46: DNO ASA (OB:DNO) | D46: 1.038 | E46: Per page 63 of the 2024 annual report. | H46: DNO ASA
C47: Nostrum Oil & Gas PLC (LSE:NOG) | D47: NA
C48: OKEA ASA (OB:OKEA) | D48: 0.83 | E48: Per investor presentation as of H1 2025 (slide 18). | H48: OKEA
C49: Savannah Energy PLC (AIM:SAVE) | D49: NA
C50: Energean PLC (LSE:ENOG) | D50: 0.32 | E50: Per the 2025 annual report (page 65). | H50: Energean
C51: BlueNord ASA (OB:BNOR) | D51: NA
C53: European Beta:
C54: O&G E&P Beta | D54: 0.69 | H54: NYU Stern
C56: Equity Risk Premium (Damodaran Approach):
C57: Eurozone Equity Risk Premium | D57: 0.0575 | E57: Using the Kroll recommended equity risk premium range. | H57: Kroll
C59: Size Premium:
C60: Low End Premium | D60: 0.045 | E60: Kroll Range for ~133M EU E&P Smaller Market cap company's.
C61: High End Premium | D61: 0.065 | H61: NYU Stern
C63: Company Specific Premium:
C64: Higher end of the range due to D/E ratio | D64: 0.085 | E64: Tullow is distressed so we selected the higher end of the range for Rp. | H64: CSRP
C66: Country Specific Premium:
C67: Higher end of the range due to D/E ratio | D67: 0.008 | E67: NYU outlines the UK at having a .8% CSP. | H67: NYU Stern
C69: Equity Beta Calculation:
C70: Scenario | D70: D/E | E70: Tax Rate | F70: Equity Beta
C71: Moderate leverage, partial shield | D71: 1.5 | E71: =+$D$6 -> 0.601 | F71: =+$D$54*(1+(1-E71)*D71) -> 1.102965
C72: High leverage, partial shield | D72: 2.5 | E72: =+$D$6 -> 0.601 | F72: =+$D$54*(1+(1-E72)*D72) -> 1.378275
C73: Very high leverage, partial shield | D73: 3 | E73: =+$D$6 -> 0.601 | F73: =+$D$54*(1+(1-E73)*D73) -> 1.51593
C75: Other Assumptions | D75: Value | E75: Comments | H75: Source
C76: Gabon Asset Sale Proceeds | D76: 307 | E76: Recognized upon completion of sale in July 2025. | H76: Tullow Oil
C77: Gabon Asset NBV | D77: 168.2 | E77: Page 26 provides the net book value of the Gabon asset. | H77: Tullow Oil
C78: Kenya Asset Sale Proceeds | D78: 120 | E78: Paid out in three tranches. Tranche A ($40M) upon completion of the sale. Tranche B ($40M) in 2026. Tranche C over 5 years from 2028 to 2032 ($40M). | H78: Tullow Oil
C79: Kenya Asset NBV | D79: 109.1 | E79: Page 27 provides the net book value of the Kenya asset. | H79: Tullow Oil
C81: Proceeds and NBV Reduction Table:
C82: Year | D82: 2025 | E82: 2026 | F82: 2027 | G82: 2028 | H82: 2029 | I82: 2030 | J82: 2031 | K82: 2032
C83: Gabon Proceeds | D83: =+D76 -> 307 | E83: 0 | G83: 0 | H83: 0 | I83: 0 | J83: 0 | K83: 0
C84: Gabon NBV | D84: =+D77 -> 168.2 | E84: 0 | G84: 0 | H84: 0 | I84: 0 | J84: 0 | K84: 0
C85: Kenya Proceeds | D85: 40 | E85: 40 | G85: 8 | H85: 8 | I85: 8 | J85: 8 | K85: 8
C86: % of Total Sale | D86: =+D85/$D$78 -> 0.33333333 | E86: =+E85/$D$78 -> 0.33333333 | G86: =+G85/$D$78 -> 0.066666667 | H86: =+H85/$D$78 -> 0.066666667 | I86: =+I85/$D$78 -> 0.066666667 | J86: =+J85/$D$78 -> 0.066666667 | K86: =+K85/$D$78 -> 0.066666667
C87: NBV Reduction | D87: =+D86*$D$79 -> 36.366667 | E87: =+E86*$D$79 -> 36.366667 | G87: =+G86*$D$79 -> 7.2733333 | H87: =+H86*$D$79 -> 7.2733333 | I87: =+I86*$D$79 -> 7.2733333 | J87: =+J86*$D$79 -> 7.2733333 | K87: =+K86*$D$79 -> 7.2733333
C88: Total Proceeds | D88: =+D83+D85 -> 347 | E88: =+E83+E85 -> 40 | F88: =+F83+F85 -> 0 | G88: =+G83+G85 -> 8 | H88: =+H83+H85 -> 8 | I88: =+I83+I85 -> 8 | J88: =+J83+J85 -> 8 | K88: =+K83+K85 -> 8
C89: Total Gains | D89: =+D83-D84+D85-D87 -> 142.43333 | E89: =+E83-E84+E85-E87 -> 3.6333333 | F89: =+F83-F84+F85-F87 -> 0 | G89: =+G83-G84+G85-G87 -> 0.72666667 | H89: =+H83-H84+H85-H87 -> 0.72666667 | I89: =+I83-I84+I85-I87 -> 0.72666667 | J89: =+J83-J84+J85-J87 -> 0.72666667 | K89: =+K83-K84+K85-K87 -> 0.72666667

Sheet Revenue Build
I1: 2024 | J1: 2025 | K1: 2026 | L1: 2027 | M1: 2028 | N1: 2029 | O1: 2030 | P1: 2031 | Q1: 2032
C2: Revenue Build
C4: ="Revenue Breakout" -> Revenue Breakout
C5: Total Revenue | J5: =J15*J18/1000000 -> 1145.735 | K5: =K15*K18/1000000 -> 996.45 | L5: =L15*L18/1000000 -> 1003.6441 | M5: =M15*M18/1000000 -> 986.084 | N5: =N15*N18/1000000 -> 967.85955 | O5: =O15*O18/1000000 -> 948.9708 | P5: =P15*P18/1000000 -> 917.829 | Q5: =Q15*Q18/1000000 -> 885.7674
C7: Markets Revenue by Segment Daily
C8: Oil Barrel | J8: {=+TRANSPOSE('Forecast Assumptions'!D31:D38)} -> 37000 | K8: 39000 | L8: 38500 | M8: 37000 | N8: 35500 | O8: 34000 | P8: 32000 | Q8: 30000
C9: Gas Barrel | J9: {=+TRANSPOSE('Forecast Assumptions'!E31:E38)} -> 6000 | K9: 6500 | L9: 6800 | M9: 7000 | N9: 7200 | O9: 7400 | P9: 7600 | Q9: 7800
C10: Total Barrels | J10: =SUM(J8:J9) -> 43000 | K10: =SUM(K8:K9) -> 45500 | L10: =SUM(L8:L9) -> 45300 | M10: =SUM(M8:M9) -> 44000 | N10: =SUM(N8:N9) -> 42700 | O10: =SUM(O8:O9) -> 41400 | P10: =SUM(P8:P9) -> 39600 | Q10: =SUM(Q8:Q9) -> 37800
C12: Markets Revenue by Segment Yearly
C13: Oil Barrel | J13: =+J8*365 -> 13505000 | K13: =+K8*365 -> 14235000 | L13: =+L8*365 -> 14052500 | M13: =+M8*365 -> 13505000 | N13: =+N8*365 -> 12957500 | O13: =+O8*365 -> 12410000 | P13: =+P8*365 -> 11680000 | Q13: =+Q8*365 -> 10950000
C14: Gas Barrel | J14: =+J9*365 -> 2190000 | K14: =+K9*365 -> 2372500 | L14: =+L9*365 -> 2482000 | M14: =+M9*365 -> 2555000 | N14: =+N9*365 -> 2628000 | O14: =+O9*365 -> 2701000 | P14: =+P9*365 -> 2774000 | Q14: =+Q9*365 -> 2847000
C15: Total Barrels | J15: =SUM(J13:J14) -> 15695000 | K15: =SUM(K13:K14) -> 16607500 | L15: =SUM(L13:L14) -> 16534500 | M15: =SUM(M13:M14) -> 16060000 | N15: =SUM(N13:N14) -> 15585500 | O15: =SUM(O13:O14) -> 15111000 | P15: =SUM(P13:P14) -> 14454000 | Q15: =SUM(Q13:Q14) -> 13797000
C17: Price
C18: Realized Oil Price | I18: 76.63 | J18: ='Forecast Assumptions'!D23 -> 73 | K18: ='Forecast Assumptions'!E23 -> 60 | L18: 60.7 | M18: 61.4 | N18: 62.1 | O18: 62.8 | P18: 63.5 | Q18: ='Forecast Assumptions'!F24 -> 64.2
C19: Realized Gas Price | I19: 2.39 | J19: ='Forecast Assumptions'!D28 -> 3.8 | K19: ='Forecast Assumptions'!E28 -> 4 | L19: 4.0333333 | M19: 4.0666667 | N19: 4.1 | O19: 4.1333333 | P19: 4.1666667 | Q19: =+'Forecast Assumptions'!F28 -> 4.2

Sheet SOFR Forward Rate Curve
C2: SOFR Forward Rate Forecast
C4: Reset Date | D4: 1-month Term SOFR | E4: 3-month Term SOFR | F4: 1-Month ISDA SOFR | H4: Year | I4: Reset Date | J4: 1-month Term SOFR | K4: 3-month Term SOFR | L4: 1-Month ISDA SOFR
C5: 45939 | D5: 0.0405 | E5: 0.0391 | F5: 0.0436 | H5: 2025 | I5: {=MAX(_xlfn._xlws.FILTER(C5:C124,YEAR(C5:C124)=$H5))} -> 46000 | J5: =_xlfn.XLOOKUP($I5,$C:$C,D:D) -> 0.0376 | K5: =_xlfn.XLOOKUP($I5,$C:$C,E:E) -> 0.0369 | L5: =_xlfn.XLOOKUP($I5,$C:$C,F:F) -> 0.0398
C6: 45971 | D6: 0.039 | E6: 0.0378 | F6: 0.0398 | H6: =H5+1 -> 2026 | I6: {=MAX(_xlfn._xlws.FILTER(C6:C125,YEAR(C6:C125)=$H6))} -> 46365 | J6: =_xlfn.XLOOKUP($I6,$C:$C,D:D) -> 0.0309 | K6: =_xlfn.XLOOKUP($I6,$C:$C,E:E) -> 0.0309 | L6: =_xlfn.XLOOKUP($I6,$C:$C,F:F) -> 0.0319
C7: 46000 | D7: 0.0376 | E7: 0.0369 | F7: 0.0398 | H7: =H6+1 -> 2027 | I7: {=MAX(_xlfn._xlws.FILTER(C7:C126,YEAR(C7:C126)=$H7))} -> 46730 | J7: =_xlfn.XLOOKUP($I7,$C:$C,D:D) -> 0.0321 | K7: =_xlfn.XLOOKUP($I7,$C:$C,E:E) -> 0.0321 | L7: =_xlfn.XLOOKUP($I7,$C:$C,F:F) -> 0.0332
C8: 46031 | D8: 0.0365 | E8: 0.0361 | F8: 0.0378 | H8: =H7+1 -> 2028 | I8: {=MAX(_xlfn._xlws.FILTER(C8:C127,YEAR(C8:C127)=$H8))} -> 47098 | J8: =_xlfn.XLOOKUP($I8,$C:$C,D:D) -> 0.0335 | K8: =_xlfn.XLOOKUP($I8,$C:$C,E:E) -> 0.0335 | L8: =_xlfn.XLOOKUP($I8,$C:$C,F:F) -> 0.0347
C9: 46062 | D9: 0.0362 | E9: 0.0354 | F9: 0.0377 | H9: =H8+1 -> 2029 | I9: {=MAX(_xlfn._xlws.FILTER(C9:C128,YEAR(C9:C128)=$H9))} -> 47462 | J9: =_xlfn.XLOOKUP($I9,$C:$C,D:D) -> 0.0349 | K9: =_xlfn.XLOOKUP($I9,$C:$C,E:E) -> 0.0349 | L9: =_xlfn.XLOOKUP($I9,$C:$C,F:F) -> 0.0361
C10: 46090 | D10: 0.0353 | E10: 0.0349 | F10: 0.0377 | H10: =H9+1 -> 2030 | I10: {=MAX(_xlfn._xlws.FILTER(C10:C129,YEAR(C10:C129)=$H10))} -> 47826 | J10: =_xlfn.XLOOKUP($I10,$C:$C,D:D) -> 0.0366 | K10: =_xlfn.XLOOKUP($I10,$C:$C,E:E) -> 0.0366 | L10: =_xlfn.XLOOKUP($I10,$C:$C,F:F) -> 0.0378
C11: 46121 | D11: 0.0348 | E11: 0.0343 | F11: 0.0357 | H11: =H10+1 -> 2031 | I11: {=MAX(_xlfn._xlws.FILTER(C11:C130,YEAR(C11:C130)=$H11))} -> 48191 | J11: =_xlfn.XLOOKUP($I11,$C:$C,D:D) -> 0.0381 | K11: =_xlfn.XLOOKUP($I11,$C:$C,E:E) -> 0.0381 | L11: =_xlfn.XLOOKUP($I11,$C:$C,F:F) -> 0.0392
C12: 46153 | D12: 0.0345 | E12: 0.0336 | F12: 0.0356 | H12: =H11+1 -> 2032 | I12: {=MAX(_xlfn._xlws.FILTER(C12:C131,YEAR(C12:C131)=$H12))} -> 48557 | J12: =_xlfn.XLOOKUP($I12,$C:$C,D:D) -> 0.0394 | K12: =_xlfn.XLOOKUP($I12,$C:$C,E:E) -> 0.0394 | L12: =_xlfn.XLOOKUP($I12,$C:$C,F:F) -> 0.0406
C13: 46182 | D13: 0.0335 | E13: 0.0329 | F13: 0.0356 | H13: =H12+1 -> 2033 | I13: {=MAX(_xlfn._xlws.FILTER(C13:C132,YEAR(C13:C132)=$H13))} -> 48922 | J13: =_xlfn.XLOOKUP($I13,$C:$C,D:D) -> 0.0407 | K13: =_xlfn.XLOOKUP($I13,$C:$C,E:E) -> 0.0406 | L13: =_xlfn.XLOOKUP($I13,$C:$C,F:F) -> 0.0418
C14: 46212 | D14: 0.0328 | E14: 0.0324 | F14: 0.033 | H14: =H13+1 -> 2034 | I14: {=MAX(_xlfn._xlws.FILTER(C14:C133,YEAR(C14:C133)=$H14))} -> 49289 | J14: =_xlfn.XLOOKUP($I14,$C:$C,D:D) -> 0.0419 | K14: =_xlfn.XLOOKUP($I14,$C:$C,E:E) -> 0.0419 | L14: =_xlfn.XLOOKUP($I14,$C:$C,F:F) -> 0.0431
C15: 46244 | D15: 0.0324 | E15: 0.0317 | F15: 0.0329 | H15: =H14+1 -> 2035 | I15: {=MAX(_xlfn._xlws.FILTER(C15:C134,YEAR(C15:C134)=$H15))} -> 49562 | J15: =_xlfn.XLOOKUP($I15,$C:$C,D:D) -> 0.0419 | K15: =_xlfn.XLOOKUP($I15,$C:$C,E:E) -> 0.0428 | L15: =_xlfn.XLOOKUP($I15,$C:$C,F:F) -> 0.0431
C16: 46274 | D16: 0.0318 | E16: 0.0313 | F16: 0.0329
C17: 46304 | D17: 0.0309 | E17: 0.031 | F17: 0.0319
C18: 46335 | D18: 0.0309 | E18: 0.0309 | F18: 0.0319
C19: 46365 | D19: 0.0309 | E19: 0.0309 | F19: 0.0319
C20: 46398 | D20: 0.0309 | E20: 0.031 | F20: 0.0319
C21: 46427 | D21: 0.0309 | E21: 0.0309 | F21: 0.0319
C22: 46455 | D22: 0.0309 | E22: 0.0309 | F22: 0.0319
C23: 46486 | D23: 0.0309 | E23: 0.031 | F23: 0.0323
C24: 46517 | D24: 0.0309 | E24: 0.0309 | F24: 0.0323
C25: 46547 | D25: 0.0309 | E25: 0.0309 | F25: 0.0323
C26: 46577 | D26: 0.0309 | E26: 0.031 | F26: 0.0323
C27: 46608 | D27: 0.0309 | E27: 0.0312 | F27: 0.0323
... C124: 49562 | D124: 0.0419 | E124: 0.0428 | F124: 0.0431
